Workbook
Name CatReceita: OFFSET(Config!$B$6,0,0,MAX(1,SUMPRODUCT(--(LEN(Config!$B$6:$B$1000)>0))),1)
Name CatDespesa: OFFSET(Config!$D$6,0,0,MAX(1,SUMPRODUCT(--(LEN(Config!$D$6:$D$1000)>0))),1)
Name CatOutras: OFFSET(Config!$G$6,0,0,MAX(1,SUMPRODUCT(--(LEN(Config!$G$6:$G$1000)>0))),1)
Name Potes: OFFSET(Config!$I$6,0,0,MAX(1,SUMPRODUCT(--(LEN(Config!$I$6:$I$1000)>0))),1)
Name Pessoas: OFFSET(Config!$K$6,0,0,MAX(1,SUMPRODUCT(--(LEN(Config!$K$6:$K$1000)>0))),1)
Name ListaContas: OFFSET(Config!$M$6,0,0,MAX(1,SUMPRODUCT(--(LEN(Config!$M$6:$M$1000)>0))),1)
Name ListaCartoes: OFFSET(Config!$Q$6,0,0,MAX(1,SUMPRODUCT(--(LEN(Config!$Q$6:$Q$1000)>0))),1)
Name FormasPagamento: OFFSET(Config!$W$6,0,0,MAX(1,SUMPRODUCT(--(LEN(Config!$W$6:$W$1000)>0))),1)
Name Tipos: OFFSET(Config!$Y$6,0,0,MAX(1,SUMPRODUCT(--(LEN(Config!$Y$6:$Y$1000)>0))),1)
Name Situacoes: OFFSET(Config!$AA$6,0,0,MAX(1,SUMPRODUCT(--(LEN(Config!$AA$6:$AA$1000)>0))),1)
Name Anos: OFFSET(Config!$AG$6,0,0,MAX(1,SUMPRODUCT(--(LEN(Config!$AG$6:$AG$1000)>0))),1)
Name Meses: Config!$AD$6:$AD$17
Name MesesAbrev: Config!$AE$6:$AE$17
Name ListaFavoritos: OFFSET(Atalhos!$B$6,0,0,MAX(1,SUMPRODUCT(--(LEN(Atalhos!$B$6:$B$515)>0))),1)
Name MesNum: Calc!$B$2
Name Categorias: OFFSET(Calc!$AM$2,0,0,MAX(1,Calc!$B$20+Calc!$B$21+Calc!$B$27),1)
Name Contas: OFFSET(Calc!$AO$2,0,0,MAX(1,Calc!$B$22+Calc!$B$23),1)
Name MesSelecionado: Dashboard!$R$3
Name AnoSelecionado: Dashboard!$V$3

Sheet Inicio
B2: Central da Família | R2: MÊS DE REFERÊNCIA
B3: Tudo do dia a dia num lugar só: lance, confira as contas do mês e acompanhe o que vence. | R3: =MesSelecionado&" / "&AnoSelecionado | V3: =HYPERLINK("#Dashboard!A1","trocar no Dashboard ➜")
B5: =HYPERLINK("#Lancamentos!B"&(ROWS(tbLancamentos[Data])+5),"✚ Novo lançamento") | F5: =HYPERLINK("#ContasMes!A1","✔ Contas do mês") | J5: =HYPERLINK("#Parcelar!A1","⟳ Parcelar / repetir") | N5: =HYPERLINK("#Dashboard!A1","▦ Dashboard") | R5: =HYPERLINK("#Orcamento!A1","◎ Orçamento") | V5: =HYPERLINK("#Atalhos!A1","★ Favoritos")
B10: SALDO DO MÊS | F10: CONTAS FIXAS LANÇADAS | J10: A PAGAR NO MÊS | N10: ORÇAMENTO USADO | R10: A RECEBER (ACERTOS) | V10: INVESTIMENTOS (LÍQUIDO)
B11: =Calc!B13 | F11: =ContasMes!B6 | J11: =Calc!B28 | N11: =Calc!B18 | R11: =0 | V11: =0
B12: Poupança | C12: =Calc!B15 | F12: Falta lançar | G12: =ContasMes!G6 | J12: Atrasadas | K12: =Calc!B29 | N12: Meta total | O12: =Calc!B17 | R12: Parcelas | S12: =SUM(tbDividas[Saldo devedor]) | V12: Metas | W12: =SUM(tbMetas[Valor atual])
B15: Próximos vencimentos e atrasados | N15: Últimos lançamentos
B16: Vence | D16: Descrição | I16: Valor | K16: Status | N16: Data | P16: Descrição | U16: Categoria | W16: Valor
B17: =Calc!AW2 | D17: =Calc!AX2 | I17: =Calc!AY2 | K17: =Calc!AZ2 | N17: =Calc!BC2 | P17: =Calc!BD2 | U17: =Calc!BF2 | W17: =Calc!BE2
B18: =Calc!AW3 | D18: =Calc!AX3 | I18: =Calc!AY3 | K18: =Calc!AZ3 | N18: =Calc!BC3 | P18: =Calc!BD3 | U18: =Calc!BF3 | W18: =Calc!BE3
B19: =Calc!AW4 | D19: =Calc!AX4 | I19: =Calc!AY4 | K19: =Calc!AZ4 | N19: =Calc!BC4 | P19: =Calc!BD4 | U19: =Calc!BF4 | W19: =Calc!BE4
B20: =Calc!AW5 | D20: =Calc!AX5 | I20: =Calc!AY5 | K20: =Calc!AZ5 | N20: =Calc!BC5 | P20: =Calc!BD5 | U20: =Calc!BF5 | W20: =Calc!BE5
B21: =Calc!AW6 | D21: =Calc!AX6 | I21: =Calc!AY6 | K21: =Calc!AZ6 | N21: =Calc!BC6 | P21: =Calc!BD6 | U21: =Calc!BF6 | W21: =Calc!BE6
B22: =Calc!AW7 | D22: =Calc!AX7 | I22: =Calc!AY7 | K22: =Calc!AZ7 | N22: =Calc!BC7 | P22: =Calc!BD7 | U22: =Calc!BF7 | W22: =Calc!BE7
B23: =Calc!AW8 | D23: =Calc!AX8 | I23: =Calc!AY8 | K23: =Calc!AZ8 | N23: =Calc!BC8 | P23: =Calc!BD8 | U23: =Calc!BF8 | W23: =Calc!BE8
B24: =Calc!AW9 | D24: =Calc!AX9 | I24: =Calc!AY9 | K24: =Calc!AZ9 | N24: =Calc!BC9 | P24: =Calc!BD9 | U24: =Calc!BF9 | W24: =Calc!BE9
B26: Lançar em 10 segundos | N26: Rotina da família
B27: 1. ✚ Novo lançamento (botão acima) leva à primeira linha vazia. | N27: Toda semana: lançar os gastos (5 min) e conferir Próximos vencimentos.
B28: 2. Ctrl+; põe a data de hoje → Tab. | N28: Quando pagar uma conta: trocar Pendente ➜ Pago em Lançamentos.
B29: 3. Descrição: escolha um favorito (Alt+↓) ou digite → Tab. | N29: Início do mês: abrir ✔ Contas do mês e colar o bloco das contas que faltam.
B30: 4. Valor → Enter. Tipo, Categoria, Situação e Pote se preenchem sozinhos. | N30: Fim do mês: olhar o Dashboard e o Orçamento; ajustar metas se precisar.
B31: 5. Conta futura? Troque a Situação para Pendente; ela aparece em Próximos vencimentos. | N31: Sempre que mudar: novos favoritos em ★ Favoritos; listas na aba Config.
B32: Compra parcelada ou lançamento que se repete? Use ⟳ Parcelar / repetir. | N32: Atalhos úteis: Ctrl+D copia a célula de cima • Alt+↓ abre a lista • Ctrl+↓ vai ao fim.

Sheet Dashboard
B2: Finanças da Família | N2: =HYPERLINK("#Inicio!A1","⌂ Início") | R2: MÊS | V2: ANO
B3: Visão mensal — escolha o mês e o ano nos seletores à direita; tudo se atualiza sozinho. | N3: =HYPERLINK("#Lancamentos!B"&(ROWS(tbLancamentos[Data])+5),"✚ Novo lançamento") | R3: Setembro | V3: 2026
B6: RECEITAS DO MÊS | F6: GASTOS DO MÊS | J6: SALDO DO MÊS | N6: TAXA DE POUPANÇA | R6: GASTOS VS. MÊS ANTERIOR | V6: % DO ORÇAMENTO UTILIZADO
B7: =Calc!B9 | F7: =Calc!B10 | J7: =Calc!B13 | N7: =Calc!B15 | R7: =Calc!B16 | V7: =Calc!B18
B8: Mês anterior | C8: =Calc!B11 | F8: Mês anterior | G8: =Calc!B12 | J8: Mês anterior | K8: =Calc!B14 | N8: Mês anterior | O8: =Calc!B19 | R8: Diferença | S8: =Calc!B25 | V8: Meta total | W8: =Calc!B17
B51: Top 5 maiores gastos do mês | N51: Orçado × Realizado por categoria
B52: Data | D52: Descrição | I52: Categoria | K52: Valor | N52: Categoria | Q52: Meta | S52: Realizado | U52: Diferença | W52: % usado
B53: =Calc!AH2 | D53: =Calc!AI2 | I53: =Calc!AJ2 | K53: =Calc!AK2 | N53: =Calc!Z2 | Q53: =Calc!AA2 | S53: =Calc!AB2 | U53: =Q53-S53 | W53: =Calc!AC2
B54: =Calc!AH3 | D54: =Calc!AI3 | I54: =Calc!AJ3 | K54: =Calc!AK3 | N54: =Calc!Z3 | Q54: =Calc!AA3 | S54: =Calc!AB3 | U54: =Q54-S54 | W54: =Calc!AC3
B55: =Calc!AH4 | D55: =Calc!AI4 | I55: =Calc!AJ4 | K55: =Calc!AK4 | N55: =Calc!Z4 | Q55: =Calc!AA4 | S55: =Calc!AB4 | U55: =Q55-S55 | W55: =Calc!AC4
B56: =Calc!AH5 | D56: =Calc!AI5 | I56: =Calc!AJ5 | K56: =Calc!AK5 | N56: =Calc!Z5 | Q56: =Calc!AA5 | S56: =Calc!AB5 | U56: =Q56-S56 | W56: =Calc!AC5
B57: =Calc!AH6 | D57: =Calc!AI6 | I57: =Calc!AJ6 | K57: =Calc!AK6 | N57: =Calc!Z6 | Q57: =Calc!AA6 | S57: =Calc!AB6 | U57: =Q57-S57 | W57: =Calc!AC6
N58: =Calc!Z7 | Q58: =Calc!AA7 | S58: =Calc!AB7 | U58: =Q58-S58 | W58: =Calc!AC7
B59: Como usar | N59: =Calc!Z8 | Q59: =Calc!AA8 | S59: =Calc!AB8 | U59: =Q59-S59 | W59: =Calc!AC8
B60: 1. Lance receitas e gastos na aba Lançamentos (valor sempre positivo). | N60: =Calc!Z9 | Q60: =Calc!AA9 | S60: =Calc!AB9 | U60: =Q60-S60 | W60: =Calc!AC9
B61: 2. Troque o mês/ano no topo: tudo se atualiza sozinho. | N61: =Calc!Z10 | Q61: =Calc!AA10 | S61: =Calc!AB10 | U61: =Q61-S61 | W61: =Calc!AC10
B62: 3. Ajuste metas na aba Orçamento e listas na aba Config. | N62: =Calc!Z11 | Q62: =Calc!AA11 | S62: =Calc!AB11 | U62: =Q62-S62 | W62: =Calc!AC11
B63: 4. Só entra nos totais o que tem 'Conta no mês?' = sim. | N63: =Calc!Z12 | Q63: =Calc!AA12 | S63: =Calc!AB12 | U63: =Q63-S63 | W63: =Calc!AC12
B64: % usado: verde até 80% • amarelo 80–100% • vermelho acima de 100%. | N64: =Calc!Z13 | Q64: =Calc!AA13 | S64: =Calc!AB13 | U64: =Q64-S64 | W64: =Calc!AC13

Sheet Lancamentos
B2: Lançamentos | E2: =HYPERLINK("#Lancamentos!B"&(ROWS(tbLancamentos[Data])+5),"✚ Ir para a próxima linha vazia") | G2: =HYPERLINK("#Inicio!A1","⌂ Início")
B3: Digite Data, Descrição e Valor: com um favorito, Tipo, Categoria, Situação e Pote se preenchem sozinhos. Clique no [+] acima das colunas para ver os detalhes (conta, parcela, vencimento...). Linhas com "EXEMPLO" na Observação são dados fictícios: filtre e apague quando quiser.
B4: Data | C4: Descrição | D4: Valor | E4: Tipo | F4: Categoria | G4: Situação | H4: Pote | I4: Quem | J4: Conta | K4: Forma de pagamento | L4: Parcela | M4: Vencimento | N4: Competência | O4: Subcategoria | P4: Descontar de | Q4: Observação | R4: Mês | S4: Ano | T4: Conta no mês?
B5: 46115 | C5: Plano de saúde familiar | D5: 890 | E5: Despesa | F5: Saúde | G5: Pago | H5: Essenciais | J5: Conta corrente Itaú | K5: Débito automático | O5: Plano de saúde | Q5: EXEMPLO | R5: =IF(AND(tbLancamentos[[#This Row],[Data]]="",tbLancamentos[[#This Row],[Competência]]=""),"",MONTH(IF(tbLancamentos[[#This Row],[Competência]]<>"",tbLancamentos[[#This Row],[Competência]],tbLancamentos[[#This Row],[Data]]))) | S5: =IF(AND(tbLancamentos[[#This Row],[Data]]="",tbLancamentos[[#This Row],[Competência]]=""),"",YEAR(IF(tbLancamentos[[#This Row],[Competência]]<>"",tbLancamentos[[#This Row],[Competência]],tbLancamentos[[#This Row],[Data]]))) | T5: =IF(tbLancamentos[[#This Row],[Valor]]="","",IF(AND(tbLancamentos[[#This Row],[Tipo]]<>"Investimento",OR(tbLancamentos[[#This Row],[Situação]]="",tbLancamentos[[#This Row],[Situação]]="Pago",tbLancamentos[[#This Row],[Situação]]="Recebido",tbLancamentos[[#This Row],[Situação]]="Descontar Depois")),"sim","não"))
B6: 46117 | C6: Salário — titular | D6: 7800 | E6: Receita | F6: Salário | G6: Recebido | J6: Conta corrente Itaú | K6: Transferência | O6: Mensal | Q6: EXEMPLO | R6: =IF(AND(tbLancamentos[[#This Row],[Data]]="",tbLancamentos[[#This Row],[Competência]]=""),"",MONTH(IF(tbLancamentos[[#This Row],[Competência]]<>"",tbLancamentos[[#This Row],[Competência]],tbLancamentos[[#This Row],[Data]]))) | S6: =IF(AND(tbLancamentos[[#This Row],[Data]]="",tbLancamentos[[#This Row],[Competência]]=""),"",YEAR(IF(tbLancamentos[[#This Row],[Competência]]<>"",tbLancamentos[[#This Row],[Competência]],tbLancamentos[[#This Row],[Data]]))) | T6: =IF(tbLancamentos[[#This Row],[Valor]]="","",IF(AND(tbLancamentos[[#This Row],[Tipo]]<>"Investimento",OR(tbLancamentos[[#This Row],[Situação]]="",tbLancamentos[[#This Row],[Situação]]="Pago",tbLancamentos[[#This Row],[Situação]]="Recebido",tbLancamentos[[#This Row],[Situação]]="Descontar Depois")),"sim","não"))
B7: 46117 | C7: Salário — cônjuge | D7: 5200 | E7: Receita | F7: Salário | G7: Recebido | J7: Conta Nubank | K7: Transferência | O7: Mensal | Q7: EXEMPLO | R7: =IF(AND(tbLancamentos[[#This Row],[Data]]="",tbLancamentos[[#This Row],[Competência]]=""),"",MONTH(IF(tbLancamentos[[#This Row],[Competência]]<>"",tbLancamentos[[#This Row],[Competência]],tbLancamentos[[#This Row],[Data]]))) | S7: =IF(AND(tbLancamentos[[#This Row],[Data]]="",tbLancamentos[[#This Row],[Competência]]=""),"",YEAR(IF(tbLancamentos[[#This Row],[Competência]]<>"",tbLancamentos[[#This Row],[Competência]],tbLancamentos[[#This Row],[Data]]))) | T7: =IF(tbLancamentos[[#This Row],[Valor]]="","",IF(AND(tbLancamentos[[#This Row],[Tipo]]<>"Investimento",OR(tbLancamentos[[#This Row],[Situação]]="",tbLancamentos[[#This Row],[Situação]]="Pago",tbLancamentos[[#This Row],[Situação]]="Recebido",tbLancamentos[[#This Row],[Situação]]="Descontar Depois")),"sim","não"))
B8: 46119 | C8: Mercado do mês | D8: 842.37 | E8: Despesa | F8: Alimentação | G8: Pago | H8: Essenciais | J8: Cartão Nubank | K8: Cartão de crédito | O8: Mercado | Q8: EXEMPLO | R8: =IF(AND(tbLancamentos[[#This Row],[Data]]="",tbLancamentos[[#This Row],[Competência]]=""),"",MONTH(IF(tbLancamentos[[#This Row],[Competência]]<>"",tbLancamentos[[#This Row],[Competência]],tbLancamentos[[#This Row],[Data]]))) | S8: =IF(AND(tbLancamentos[[#This Row],[Data]]="",tbLancamentos[[#This Row],[Competência]]=""),"",YEAR(IF(tbLancamentos[[#This Row],[Competência]]<>"",tbLancamentos[[#This Row],[Competência]],tbLancamentos[[#This Row],[Data]]))) | T8: =IF(tbLancamentos[[#This Row],[Valor]]="","",IF(AND(tbLancamentos[[#This Row],[Tipo]]<>"Investimento",OR(tbLancamentos[[#This Row],[Situação]]="",tbLancamentos[[#This Row],[Situação]]="Pago",tbLancamentos[[#This Row],[Situação]]="Recebido",tbLancamentos[[#This Row],[Situação]]="Descontar Depois")),"sim","não"))
B9: 46120 | C9: Mensalidade escolar | D9: 1450 | E9: Despesa | F9: Educação | G9: Pago | H9: Essenciais | J9: Conta corrente Itaú | K9: Boleto | O9: Escola | Q9: EXEMPLO | R9: =IF(AND(tbLancamentos[[#This Row],[Data]]="",tbLancamentos[[#This Row],[Competência]]=""),"",MONTH(IF(tbLancamentos[[#This Row],[Competência]]<>"",tbLancamentos[[#This Row],[Competência]],tbLancamentos[[#This Row],[Data]]))) | S9: =IF(AND(tbLancamentos[[#This Row],[Data]]="",tbLancamentos[[#This Row],[Competência]]=""),"",YEAR(IF(tbLancamentos[[#This Row],[Competência]]<>"",tbLancamentos[[#This Row],[Competência]],tbLancamentos[[#This Row],[Data]]))) | T9: =IF(tbLancamentos[[#This Row],[Valor]]="","",IF(AND(tbLancamentos[[#This Row],[Tipo]]<>"Investimento",OR(tbLancamentos[[#This Row],[Situação]]="",tbLancamentos[[#This Row],[Situação]]="Pago",tbLancamentos[[#This Row],[Situação]]="Recebido",tbLancamentos[[#This Row],[Situação]]="Descontar Depois")),"sim","não"))
B10: 46122 | C10: Aluguel do apartamento | D10: 2350 | E10: Despesa | F10: Moradia | G10: Pago | H10: Essenciais | J10: Conta corrente Itaú | K10: Boleto | O10: Aluguel/Financiamento | Q10: EXEMPLO | R10: =IF(AND(tbLancamentos[[#This Row],[Data]]="",tbLancamentos[[#This Row],[Competência]]=""),"",MONTH(IF(tbLancamentos[[#This Row],[Competência]]<>"",tbLancamentos[[#This Row],[Competência]],tbLancamentos[[#This Row],[Data]]))) | S10: =IF(AND(tbLancamentos[[#This Row],[Data]]="",tbLancamentos[[#This Row],[Competência]]=""),"",YEAR(IF(tbLancamentos[[#This Row],[Competência]]<>"",tbLancamentos[[#This Row],[Competência]],tbLancamentos[[#This Row],[Data]]))) | T10: =IF(tbLancamentos[[#This Row],[Valor]]="","",IF(AND(tbLancamentos[[#This Row],[Tipo]]<>"Investimento",OR(tbLancamentos[[#This Row],[Situação]]="",tbLancamentos[[#This Row],[Situação]]="Pago",tbLancamentos[[#This Row],[Situação]]="Recebido",tbLancamentos[[#This Row],[Situação]]="Descontar Depois")),"sim","não"))
B11: 46122 | C11: Conta de energia | D11: 312.4 | E11: Despesa | F11: Contas da casa | G11: Pago | H11: Essenciais | J11: Conta corrente Itaú | K11: Débito automático | O11: Energia | Q11: EXEMPLO | R11: =IF(AND(tbLancamentos[[#This Row],[Data]]="",tbLancamentos[[#This Row],[Competência]]=""),"",MONTH(IF(tbLancamentos[[#This Row],[Competência]]<>"",tbLancamentos[[#This Row],[Competência]],tbLancamentos[[#This Row],[Data]]))) | S11: =IF(AND(tbLancamentos[[#This Row],[Data]]="",tbLancamentos[[#This Row],[Competência]]=""),"",YEAR(IF(tbLancamentos[[#This Row],[Competência]]<>"",tbLancamentos[[#This Row],[Competência]],tbLancamentos[[#This Row],[Data]]))) | T11: =IF(tbLancamentos[[#This Row],[Valor]]="","",IF(AND(tbLancamentos[[#This Row],[Tipo]]<>"Investimento",OR(tbLancamentos[[#This Row],[Situação]]="",tbLancamentos[[#This Row],[Situação]]="Pago",tbLancamentos[[#This Row],[Situação]]="Recebido",tbLancamentos[[#This Row],[Situação]]="Descontar Depois")),"sim","não"))
B12: 46124 | C12: Streaming + academia | D12: 174.8 | E12: Despesa | F12: Assinaturas | G12: Pago | H12: Essenciais | J12: Cartão Nubank | K12: Cartão de crédito | O12: Streaming | Q12: EXEMPLO | R12: =IF(AND(tbLancamentos[[#This Row],[Data]]="",tbLancamentos[[#This Row],[Competência]]=""),"",MONTH(IF(tbLancamentos[[#This Row],[Competência]]<>"",tbLancamentos[[#This Row],[Competência]],tbLancamentos[[#This Row],[Data]]))) | S12: =IF(AND(tbLancamentos[[#This Row],[Data]]="",tbLancamentos[[#This Row],[Competência]]=""),"",YEAR(IF(tbLancamentos[[#This Row],[Competência]]<>"",tbLancamentos[[#This Row],[Competência]],tbLancamentos[[#This Row],[Data]]))) | T12: =IF(tbLancamentos[[#This Row],[Valor]]="","",IF(AND(tbLancamentos[[#This Row],[Tipo]]<>"Investimento",OR(tbLancamentos[[#This Row],[Situação]]="",tbLancamentos[[#This Row],[Situação]]="Pago",tbLancamentos[[#This Row],[Situação]]="Recebido",tbLancamentos[[#This Row],[Situação]]="Descontar Depois")),"sim","não"))
B13: 46127 | C13: Combustível | D13: 310 | E13: Despesa | F13: Transporte | G13: Pago | H13: Essenciais | J13: Cartão Itaú | K13: Cartão de crédito | O13: Combustível | Q13: EXEMPLO | R13: =IF(AND(tbLancamentos[[#This Row],[Data]]="",tbLancamentos[[#This Row],[Competência]]=""),"",MONTH(IF(tbLancamentos[[#This Row],[Competência]]<>"",tbLancamentos[[#This Row],[Competência]],tbLancamentos[[#This Row],[Data]]))) | S13: =IF(AND(tbLancamentos[[#This Row],[Data]]="",tbLancamentos[[#This Row],[Competência]]=""),"",YEAR(IF(tbLancamentos[[#This Row],[Competência]]<>"",tbLancamentos[[#This Row],[Competência]],tbLancamentos[[#This Row],[Data]]))) | T13: =IF(tbLancamentos[[#This Row],[Valor]]="","",IF(AND(tbLancamentos[[#This Row],[Tipo]]<>"Investimento",OR(tbLancamentos[[#This Row],[Situação]]="",tbLancamentos[[#This Row],[Situação]]="Pago",tbLancamentos[[#This Row],[Situação]]="Recebido",tbLancamentos[[#This Row],[Situação]]="Descontar Depois")),"sim","não"))
B14: 46130 | C14: Farmácia | D14: 142.35 | E14: Despesa | F14: Saúde | G14: Pago | H14: Essenciais | J14: Cartão Nubank | K14: Cartão de crédito | O14: Farmácia | Q14: EXEMPLO | R14: =IF(AND(tbLancamentos[[#This Row],[Data]]="",tbLancamentos[[#This Row],[Competência]]=""),"",MONTH(IF(tbLancamentos[[#This Row],[Competência]]<>"",tbLancamentos[[#This Row],[Competência]],tbLancamentos[[#This Row],[Data]]))) | S14: =IF(AND(tbLancamentos[[#This Row],[Data]]="",tbLancamentos[[#This Row],[Competência]]=""),"",YEAR(IF(tbLancamentos[[#This Row],[Competência]]<>"",tbLancamentos[[#This Row],[Competência]],tbLancamentos[[#This Row],[Data]]))) | T14: =IF(tbLancamentos[[#This Row],[Valor]]="","",IF(AND(tbLancamentos[[#This Row],[Tipo]]<>"Investimento",OR(tbLancamentos[[#This Row],[Situação]]="",tbLancamentos[[#This Row],[Situação]]="Pago",tbLancamentos[[#This Row],[Situação]]="Recebido",tbLancamentos[[#This Row],[Situação]]="Descontar Depois")),"sim","não"))
B15: 46138 | C15: Pizza de sábado | D15: 118 | E15: Despesa | F15: Restaurantes e delivery | G15: Pago | H15: Lazer | J15: Cartão Nubank | K15: Cartão de crédito | O15: Delivery | Q15: EXEMPLO | R15: =IF(AND(tbLancamentos[[#This Row],[Data]]="",tbLancamentos[[#This Row],[Competência]]=""),"",MONTH(IF(tbLancamentos[[#This Row],[Competência]]<>"",tbLancamentos[[#This Row],[Competência]],tbLancamentos[[#This Row],[Data]]))) | S15: =IF(AND(tbLancamentos[[#This Row],[Data]]="",tbLancamentos[[#This Row],[Competência]]=""),"",YEAR(IF(tbLancamentos[[#This Row],[Competência]]<>"",tbLancamentos[[#This Row],[Competência]],tbLancamentos[[#This Row],[Data]]))) | T15: =IF(tbLancamentos[[#This Row],[Valor]]="","",IF(AND(tbLancamentos[[#This Row],[Tipo]]<>"Investimento",OR(tbLancamentos[[#This Row],[Situação]]="",tbLancamentos[[#This Row],[Situação]]="Pago",tbLancamentos[[#This Row],[Situação]]="Recebido",tbLancamentos[[#This Row],[Situação]]="Descontar Depois")),"sim","não"))
B16: 46139 | C16: Cinema / passeio | D16: 64 | E16: Despesa | F16: Lazer | G16: Pago | H16: Lazer | J16: Conta Nubank | K16: PIX | O16: Cinema | Q16: EXEMPLO | R16: =IF(AND(tbLancamentos[[#This Row],[Data]]="",tbLancamentos[[#This Row],[Competência]]=""),"",MONTH(IF(tbLancamentos[[#This Row],[Competência]]<>"",tbLancamentos[[#This Row],[Competência]],tbLancamentos[[#This Row],[Data]]))) | S16: =IF(AND(tbLancamentos[[#This Row],[Data]]="",tbLancamentos[[#This Row],[Competência]]=""),"",YEAR(IF(tbLancamentos[[#This Row],[Competência]]<>"",tbLancamentos[[#This Row],[Competência]],tbLancamentos[[#This Row],[Data]]))) | T16: =IF(tbLancamentos[[#This Row],[Valor]]="","",IF(AND(tbLancamentos[[#This Row],[Tipo]]<>"Investimento",OR(tbLancamentos[[#This Row],[Situação]]="",tbLancamentos[[#This Row],[Situação]]="Pago",tbLancamentos[[#This Row],[Situação]]="Recebido",tbLancamentos[[#This Row],[Situação]]="Descontar Depois")),"sim","não"))
B17: 46145 | C17: Plano de saúde familiar | D17: 890 | E17: Despesa | F17: Saúde | G17: Pago | H17: Essenciais | J17: Conta corrente Itaú | K17: Débito automático | O17: Plano de saúde | Q17: EXEMPLO | R17: =IF(AND(tbLancamentos[[#This Row],[Data]]="",tbLancamentos[[#This Row],[Competência]]=""),"",MONTH(IF(tbLancamentos[[#This Row],[Competência]]<>"",tbLancamentos[[#This Row],[Competência]],tbLancamentos[[#This Row],[Data]]))) | S17: =IF(AND(tbLancamentos[[#This Row],[Data]]="",tbLancamentos[[#This Row],[Competência]]=""),"",YEAR(IF(tbLancamentos[[#This Row],[Competência]]<>"",tbLancamentos[[#This Row],[Competência]],tbLancamentos[[#This Row],[Data]]))) | T17: =IF(tbLancamentos[[#This Row],[Valor]]="","",IF(AND(tbLancamentos[[#This Row],[Tipo]]<>"Investimento",OR(tbLancamentos[[#This Row],[Situação]]="",tbLancamentos[[#This Row],[Situação]]="Pago",tbLancamentos[[#This Row],[Situação]]="Recebido",tbLancamentos[[#This Row],[Situação]]="Descontar Depois")),"sim","não"))
B18: 46147 | C18: Salário — titular | D18: 7800 | E18: Receita | F18: Salário | G18: Recebido | J18: Conta corrente Itaú | K18: Transferência | O18: Mensal | Q18: EXEMPLO | R18: =IF(AND(tbLancamentos[[#This Row],[Data]]="",tbLancamentos[[#This Row],[Competência]]=""),"",MONTH(IF(tbLancamentos[[#This Row],[Competência]]<>"",tbLancamentos[[#This Row],[Competência]],tbLancamentos[[#This Row],[Data]]))) | S18: =IF(AND(tbLancamentos[[#This Row],[Data]]="",tbLancamentos[[#This Row],[Competência]]=""),"",YEAR(IF(tbLancamentos[[#This Row],[Competência]]<>"",tbLancamentos[[#This Row],[Competência]],tbLancamentos[[#This Row],[Data]]))) | T18: =IF(tbLancamentos[[#This Row],[Valor]]="","",IF(AND(tbLancamentos[[#This Row],[Tipo]]<>"Investimento",OR(tbLancamentos[[#This Row],[Situação]]="",tbLancamentos[[#This Row],[Situação]]="Pago",tbLancamentos[[#This Row],[Situação]]="Recebido",tbLancamentos[[#This Row],[Situação]]="Descontar Depois")),"sim","não"))
B19: 46147 | C19: Salário — cônjuge | D19: 5200 | E19: Receita | F19: Salário | G19: Recebido | J19: Conta Nubank | K19: Transferência | O19: Mensal | Q19: EXEMPLO | R19: =IF(AND(tbLancamentos[[#This Row],[Data]]="",tbLancamentos[[#This Row],[Competência]]=""),"",MONTH(IF(tbLancamentos[[#This Row],[Competência]]<>"",tbLancamentos[[#This Row],[Competência]],tbLancamentos[[#This Row],[Data]]))) | S19: =IF(AND(tbLancamentos[[#This Row],[Data]]="",tbLancamentos[[#This Row],[Competência]]=""),"",YEAR(IF(tbLancamentos[[#This Row],[Competência]]<>"",tbLancamentos[[#This Row],[Competência]],tbLancamentos[[#This Row],[Data]]))) | T19: =IF(tbLancamentos[[#This Row],[Valor]]="","",IF(AND(tbLancamentos[[#This Row],[Tipo]]<>"Investimento",OR(tbLancamentos[[#This Row],[Situação]]="",tbLancamentos[[#This Row],[Situação]]="Pago",tbLancamentos[[#This Row],[Situação]]="Recebido",tbLancamentos[[#This Row],[Situação]]="Descontar Depois")),"sim","não"))
B20: 46149 | C20: Mercado do mês | D20: 915.6 | E20: Despesa | F20: Alimentação | G20: Pago | H20: Essenciais | J20: Cartão Nubank | K20: Cartão de crédito | O20: Mercado | Q20: EXEMPLO | R20: =IF(AND(tbLancamentos[[#This Row],[Data]]="",tbLancamentos[[#This Row],[Competência]]=""),"",MONTH(IF(tbLancamentos[[#This Row],[Competência]]<>"",tbLancamentos[[#This Row],[Competência]],tbLancamentos[[#This Row],[Data]]))) | S20: =IF(AND(tbLancamentos[[#This Row],[Data]]="",tbLancamentos[[#This Row],[Competência]]=""),"",YEAR(IF(tbLancamentos[[#This Row],[Competência]]<>"",tbLancamentos[[#This Row],[Competência]],tbLancamentos[[#This Row],[Data]]))) | T20: =IF(tbLancamentos[[#This Row],[Valor]]="","",IF(AND(tbLancamentos[[#This Row],[Tipo]]<>"Investimento",OR(tbLancamentos[[#This Row],[Situação]]="",tbLancamentos[[#This Row],[Situação]]="Pago",tbLancamentos[[#This Row],[Situação]]="Recebido",tbLancamentos[[#This Row],[Situação]]="Descontar Depois")),"sim","não"))
B21: 46150 | C21: Mensalidade escolar | D21: 1450 | E21: Despesa | F21: Educação | G21: Pago | H21: Essenciais | J21: Conta corrente Itaú | K21: Boleto | O21: Escola | Q21: EXEMPLO | R21: =IF(AND(tbLancamentos[[#This Row],[Data]]="",tbLancamentos[[#This Row],[Competência]]=""),"",MONTH(IF(tbLancamentos[[#This Row],[Competência]]<>"",tbLancamentos[[#This Row],[Competência]],tbLancamentos[[#This Row],[Data]]))) | S21: =IF(AND(tbLancamentos[[#This Row],[Data]]="",tbLancamentos[[#This Row],[Competência]]=""),"",YEAR(IF(tbLancamentos[[#This Row],[Competência]]<>"",tbLancamentos[[#This Row],[Competência]],tbLancamentos[[#This Row],[Data]]))) | T21: =IF(tbLancamentos[[#This Row],[Valor]]="","",IF(AND(tbLancamentos[[#This Row],[Tipo]]<>"Investimento",OR(tbLancamentos[[#This Row],[Situação]]="",tbLancamentos[[#This Row],[Situação]]="Pago",tbLancamentos[[#This Row],[Situação]]="Recebido",tbLancamentos[[#This Row],[Situação]]="Descontar Depois")),"sim","não"))
B22: 46152 | C22: Aluguel do apartamento | D22: 2350 | E22: Despesa | F22: Moradia | G22: Pago | H22: Essenciais | J22: Conta corrente Itaú | K22: Boleto | O22: Aluguel/Financiamento | Q22: EXEMPLO | R22: =IF(AND(tbLancamentos[[#This Row],[Data]]="",tbLancamentos[[#This Row],[Competência]]=""),"",MONTH(IF(tbLancamentos[[#This Row],[Competência]]<>"",tbLancamentos[[#This Row],[Competência]],tbLancamentos[[#This Row],[Data]]))) | S22: =IF(AND(tbLancamentos[[#This Row],[Data]]="",tbLancamentos[[#This Row],[Competência]]=""),"",YEAR(IF(tbLancamentos[[#This Row],[Competência]]<>"",tbLancamentos[[#This Row],[Competência]],tbLancamentos[[#This Row],[Data]]))) | T22: =IF(tbLancamentos[[#This Row],[Valor]]="","",IF(AND(tbLancamentos[[#This Row],[Tipo]]<>"Investimento",OR(tbLancamentos[[#This Row],[Situação]]="",tbLancamentos[[#This Row],[Situação]]="Pago",tbLancamentos[[#This Row],[Situação]]="Recebido",tbLancamentos[[#This Row],[Situação]]="Descontar Depois")),"sim","não"))
B23: 46152 | C23: Conta de energia | D23: 286.15 | E23: Despesa | F23: Contas da casa | G23: Pago | H23: Essenciais | J23: Conta corrente Itaú | K23: Débito automático | O23: Energia | Q23: EXEMPLO | R23: =IF(AND(tbLancamentos[[#This Row],[Data]]="",tbLancamentos[[#This Row],[Competência]]=""),"",MONTH(IF(tbLancamentos[[#This Row],[Competência]]<>"",tbLancamentos[[#This Row],[Competência]],tbLancamentos[[#This Row],[Data]]))) | S23: =IF(AND(tbLancamentos[[#This Row],[Data]]="",tbLancamentos[[#This Row],[Competência]]=""),"",YEAR(IF(tbLancamentos[[#This Row],[Competência]]<>"",tbLancamentos[[#This Row],[Competência]],tbLancamentos[[#This Row],[Data]]))) | T23: =IF(tbLancamentos[[#This Row],[Valor]]="","",IF(AND(tbLancamentos[[#This Row],[Tipo]]<>"Investimento",OR(tbLancamentos[[#This Row],[Situação]]="",tbLancamentos[[#This Row],[Situação]]="Pago",tbLancamentos[[#This Row],[Situação]]="Recebido",tbLancamentos[[#This Row],[Situação]]="Descontar Depois")),"sim","não"))
B24: 46154 | C24: Streaming + academia | D24: 174.8 | E24: Despesa | F24: Assinaturas | G24: Pago | H24: Essenciais | J24: Cartão Nubank | K24: Cartão de crédito | O24: Streaming | Q24: EXEMPLO | R24: =IF(AND(tbLancamentos[[#This Row],[Data]]="",tbLancamentos[[#This Row],[Competência]]=""),"",MONTH(IF(tbLancamentos[[#This Row],[Competência]]<>"",tbLancamentos[[#This Row],[Competência]],tbLancamentos[[#This Row],[Data]]))) | S24: =IF(AND(tbLancamentos[[#This Row],[Data]]="",tbLancamentos[[#This Row],[Competência]]=""),"",YEAR(IF(tbLancamentos[[#This Row],[Competência]]<>"",tbLancamentos[[#This Row],[Competência]],tbLancamentos[[#This Row],[Data]]))) | T24: =IF(tbLancamentos[[#This Row],[Valor]]="","",IF(AND(tbLancamentos[[#This Row],[Tipo]]<>"Investimento",OR(tbLancamentos[[#This Row],[Situação]]="",tbLancamentos[[#This Row],[Situação]]="Pago",tbLancamentos[[#This Row],[Situação]]="Recebido",tbLancamentos[[#This Row],[Situação]]="Descontar Depois")),"sim","não"))
B25: 46154 | C25: Projeto freelance — site | D25: 1800 | E25: Receita | F25: Freelance / Extras | G25: Recebido | J25: Conta Nubank | K25: PIX | O25: Projeto | Q25: EXEMPLO | R25: =IF(AND(tbLancamentos[[#This Row],[Data]]="",tbLancamentos[[#This Row],[Competência]]=""),"",MONTH(IF(tbLancamentos[[#This Row],[Competência]]<>"",tbLancamentos[[#This Row],[Competência]],tbLancamentos[[#This Row],[Data]]))) | S25: =IF(AND(tbLancamentos[[#This Row],[Data]]="",tbLancamentos[[#This Row],[Competência]]=""),"",YEAR(IF(tbLancamentos[[#This Row],[Competência]]<>"",tbLancamentos[[#This Row],[Competência]],tbLancamentos[[#This Row],[Data]]))) | T25: =IF(tbLancamentos[[#This Row],[Valor]]="","",IF(AND(tbLancamentos[[#This Row],[Tipo]]<>"Investimento",OR(tbLancamentos[[#This Row],[Situação]]="",tbLancamentos[[#This Row],[Situação]]="Pago",tbLancamentos[[#This Row],[Situação]]="Recebido",tbLancamentos[[#This Row],[Situação]]="Descontar Depois")),"sim","não"))
B26: 46157 | C26: Combustível | D26: 285.5 | E26: Despesa | F26: Transporte | G26: Pago | H26: Essenciais | J26: Cartão Itaú | K26: Cartão de crédito | O26: Combustível | Q26: EXEMPLO | R26: =IF(AND(tbLancamentos[[#This Row],[Data]]="",tbLancamentos[[#This Row],[Competência]]=""),"",MONTH(IF(tbLancamentos[[#This Row],[Competência]]<>"",tbLancamentos[[#This Row],[Competência]],tbLancamentos[[#This Row],[Data]]))) | S26: =IF(AND(tbLancamentos[[#This Row],[Data]]="",tbLancamentos[[#This Row],[Competência]]=""),"",YEAR(IF(tbLancamentos[[#This Row],[Competência]]<>"",tbLancamentos[[#This Row],[Competência]],tbLancamentos[[#This Row],[Data]]))) | T26: =IF(tbLancamentos[[#This Row],[Valor]]="","",IF(AND(tbLancamentos[[#This Row],[Tipo]]<>"Investimento",OR(tbLancamentos[[#This Row],[Situação]]="",tbLancamentos[[#This Row],[Situação]]="Pago",tbLancamentos[[#This Row],[Situação]]="Recebido",tbLancamentos[[#This Row],[Situação]]="Descontar Depois")),"sim","não"))
B27: 46166 | C27: Presente dia das mães | D27: 289.9 | E27: Despesa | F27: Compras | G27: Pago | H27: Essenciais | J27: Cartão Itaú | K27: Cartão de crédito | O27: Presentes | Q27: EXEMPLO | R27: =IF(AND(tbLancamentos[[#This Row],[Data]]="",tbLancamentos[[#This Row],[Competência]]=""),"",MONTH(IF(tbLancamentos[[#This Row],[Competência]]<>"",tbLancamentos[[#This Row],[Competência]],tbLancamentos[[#This Row],[Data]]))) | S27: =IF(AND(tbLancamentos[[#This Row],[Data]]="",tbLancamentos[[#This Row],[Competência]]=""),"",YEAR(IF(tbLancamentos[[#This Row],[Competência]]<>"",tbLancamentos[[#This Row],[Competência]],tbLancamentos[[#This Row],[Data]]))) | T27: =IF(tbLancamentos[[#This Row],[Valor]]="","",IF(AND(tbLancamentos[[#This Row],[Tipo]]<>"Investimento",OR(tbLancamentos[[#This Row],[Situação]]="",tbLancamentos[[#This Row],[Situação]]="Pago",tbLancamentos[[#This Row],[Situação]]="Recebido",tbLancamentos[[#This Row],[Situação]]="Descontar Depois")),"sim","não"))
B28: 46169 | C28: Cinema / passeio | D28: 180 | E28: Despesa | F28: Lazer | G28: Pago | H28: Lazer | J28: Conta Nubank | K28: PIX | O28: Cinema | Q28: EXEMPLO | R28: =IF(AND(tbLancamentos[[#This Row],[Data]]="",tbLancamentos[[#This Row],[Competência]]=""),"",MONTH(IF(tbLancamentos[[#This Row],[Competência]]<>"",tbLancamentos[[#This Row],[Competência]],tbLancamentos[[#This Row],[Data]]))) | S28: =IF(AND(tbLancamentos[[#This Row],[Data]]="",tbLancamentos[[#This Row],[Competência]]=""),"",YEAR(IF(tbLancamentos[[#This Row],[Competência]]<>"",tbLancamentos[[#This Row],[Competência]],tbLancamentos[[#This Row],[Data]]))) | T28: =IF(tbLancamentos[[#This Row],[Valor]]="","",IF(AND(tbLancamentos[[#This Row],[Tipo]]<>"Investimento",OR(tbLancamentos[[#This Row],[Situação]]="",tbLancamentos[[#This Row],[Situação]]="Pago",tbLancamentos[[#This Row],[Situação]]="Recebido",tbLancamentos[[#This Row],[Situação]]="Descontar Depois")),"sim","não"))
B29: 46176 | C29: Plano de saúde familiar | D29: 890 | E29: Despesa | F29: Saúde | G29: Pago | H29: Essenciais | J29: Conta corrente Itaú | K29: Débito automático | O29: Plano de saúde | Q29: EXEMPLO | R29: =IF(AND(tbLancamentos[[#This Row],[Data]]="",tbLancamentos[[#This Row],[Competência]]=""),"",MONTH(IF(tbLancamentos[[#This Row],[Competência]]<>"",tbLancamentos[[#This Row],[Competência]],tbLancamentos[[#This Row],[Data]]))) | S29: =IF(AND(tbLancamentos[[#This Row],[Data]]="",tbLancamentos[[#This Row],[Competência]]=""),"",YEAR(IF(tbLancamentos[[#This Row],[Competência]]<>"",tbLancamentos[[#This Row],[Competência]],tbLancamentos[[#This Row],[Data]]))) | T29: =IF(tbLancamentos[[#This Row],[Valor]]="","",IF(AND(tbLancamentos[[#This Row],[Tipo]]<>"Investimento",OR(tbLancamentos[[#This Row],[Situação]]="",tbLancamentos[[#This Row],[Situação]]="Pago",tbLancamentos[[#This Row],[Situação]]="Recebido",tbLancamentos[[#This Row],[Situação]]="Descontar Depois")),"sim","não"))
B30: 46178 | C30: Salário — titular | D30: 7800 | E30: Receita | F30: Salário | G30: Recebido | J30: Conta corrente Itaú | K30: Transferência | O30: Mensal | Q30: EXEMPLO | R30: =IF(AND(tbLancamentos[[#This Row],[Data]]="",tbLancamentos[[#This Row],[Competência]]=""),"",MONTH(IF(tbLancamentos[[#This Row],[Competência]]<>"",tbLancamentos[[#This Row],[Competência]],tbLancamentos[[#This Row],[Data]]))) | S30: =IF(AND(tbLancamentos[[#This Row],[Data]]="",tbLancamentos[[#This Row],[Competência]]=""),"",YEAR(IF(tbLancamentos[[#This Row],[Competência]]<>"",tbLancamentos[[#This Row],[Competência]],tbLancamentos[[#This Row],[Data]]))) | T30: =IF(tbLancamentos[[#This Row],[Valor]]="","",IF(AND(tbLancamentos[[#This Row],[Tipo]]<>"Investimento",OR(tbLancamentos[[#This Row],[Situação]]="",tbLancamentos[[#This Row],[Situação]]="Pago",tbLancamentos[[#This Row],[Situação]]="Recebido",tbLancamentos[[#This Row],[Situação]]="Descontar Depois")),"sim","não"))
B31: 46178 | C31: Salário — cônjuge | D31: 5200 | E31: Receita | F31: Salário | G31: Recebido | J31: Conta Nubank | K31: Transferência | O31: Mensal | Q31: EXEMPLO | R31: =IF(AND(tbLancamentos[[#This Row],[Data]]="",tbLancamentos[[#This Row],[Competência]]=""),"",MONTH(IF(tbLancamentos[[#This Row],[Competência]]<>"",tbLancamentos[[#This Row],[Competência]],tbLancamentos[[#This Row],[Data]]))) | S31: =IF(AND(tbLancamentos[[#This Row],[Data]]="",tbLancamentos[[#This Row],[Competência]]=""),"",YEAR(IF(tbLancamentos[[#This Row],[Competência]]<>"",tbLancamentos[[#This Row],[Competência]],tbLancamentos[[#This Row],[Data]]))) | T31: =IF(tbLancamentos[[#This Row],[Valor]]="","",IF(AND(tbLancamentos[[#This Row],[Tipo]]<>"Investimento",OR(tbLancamentos[[#This Row],[Situação]]="",tbLancamentos[[#This Row],[Situação]]="Pago",tbLancamentos[[#This Row],[Situação]]="Recebido",tbLancamentos[[#This Row],[Situação]]="Descontar Depois")),"sim","não"))
B32: 46180 | C32: Mercado do mês | D32: 788.45 | E32: Despesa | F32: Alimentação | G32: Pago | H32: Essenciais | J32: Cartão Nubank | K32: Cartão de crédito | O32: Mercado | Q32: EXEMPLO | R32: =IF(AND(tbLancamentos[[#This Row],[Data]]="",tbLancamentos[[#This Row],[Competência]]=""),"",MONTH(IF(tbLancamentos[[#This Row],[Competência]]<>"",tbLancamentos[[#This Row],[Competência]],tbLancamentos[[#This Row],[Data]]))) | S32: =IF(AND(tbLancamentos[[#This Row],[Data]]="",tbLancamentos[[#This Row],[Competência]]=""),"",YEAR(IF(tbLancamentos[[#This Row],[Competência]]<>"",tbLancamentos[[#This Row],[Competência]],tbLancamentos[[#This Row],[Data]]))) | T32: =IF(tbLancamentos[[#This Row],[Valor]]="","",IF(AND(tbLancamentos[[#This Row],[Tipo]]<>"Investimento",OR(tbLancamentos[[#This Row],[Situação]]="",tbLancamentos[[#This Row],[Situação]]="Pago",tbLancamentos[[#This Row],[Situação]]="Recebido",tbLancamentos[[#This Row],[Situação]]="Descontar Depois")),"sim","não"))
B33: 46181 | C33: Mensalidade escolar | D33: 1450 | E33: Despesa | F33: Educação | G33: Pago | H33: Essenciais | J33: Conta corrente Itaú | K33: Boleto | O33: Escola | Q33: EXEMPLO | R33: =IF(AND(tbLancamentos[[#This Row],[Data]]="",tbLancamentos[[#This Row],[Competência]]=""),"",MONTH(IF(tbLancamentos[[#This Row],[Competência]]<>"",tbLancamentos[[#This Row],[Competência]],tbLancamentos[[#This Row],[Data]]))) | S33: =IF(AND(tbLancamentos[[#This Row],[Data]]="",tbLancamentos[[#This Row],[Competência]]=""),"",YEAR(IF(tbLancamentos[[#This Row],[Competência]]<>"",tbLancamentos[[#This Row],[Competência]],tbLancamentos[[#This Row],[Data]]))) | T33: =IF(tbLancamentos[[#This Row],[Valor]]="","",IF(AND(tbLancamentos[[#This Row],[Tipo]]<>"Investimento",OR(tbLancamentos[[#This Row],[Situação]]="",tbLancamentos[[#This Row],[Situação]]="Pago",tbLancamentos[[#This Row],[Situação]]="Recebido",tbLancamentos[[#This Row],[Situação]]="Descontar Depois")),"sim","não"))
B34: 46183 | C34: Aluguel do apartamento | D34: 2350 | E34: Despesa | F34: Moradia | G34: Pago | H34: Essenciais | J34: Conta corrente Itaú | K34: Boleto | O34: Aluguel/Financiamento | Q34: EXEMPLO | R34: =IF(AND(tbLancamentos[[#This Row],[Data]]="",tbLancamentos[[#This Row],[Competência]]=""),"",MONTH(IF(tbLancamentos[[#This Row],[Competência]]<>"",tbLancamentos[[#This Row],[Competência]],tbLancamentos[[#This Row],[Data]]))) | S34: =IF(AND(tbLancamentos[[#This Row],[Data]]="",tbLancamentos[[#This Row],[Competência]]=""),"",YEAR(IF(tbLancamentos[[#This Row],[Competência]]<>"",tbLancamentos[[#This Row],[Competência]],tbLancamentos[[#This Row],[Data]]))) | T34: =IF(tbLancamentos[[#This Row],[Valor]]="","",IF(AND(tbLancamentos[[#This Row],[Tipo]]<>"Investimento",OR(tbLancamentos[[#This Row],[Situação]]="",tbLancamentos[[#This Row],[Situação]]="Pago",tbLancamentos[[#This Row],[Situação]]="Recebido",tbLancamentos[[#This Row],[Situação]]="Descontar Depois")),"sim","não"))
B35: 46183 | C35: Conta de energia | D35: 274.8 | E35: Despesa | F35: Contas da casa | G35: Pago | H35: Essenciais | J35: Conta corrente Itaú | K35: Débito automático | O35: Energia | Q35: EXEMPLO | R35: =IF(AND(tbLancamentos[[#This Row],[Data]]="",tbLancamentos[[#This Row],[Competência]]=""),"",MONTH(IF(tbLancamentos[[#This Row],[Competência]]<>"",tbLancamentos[[#This Row],[Competência]],tbLancamentos[[#This Row],[Data]]))) | S35: =IF(AND(tbLancamentos[[#This Row],[Data]]="",tbLancamentos[[#This Row],[Competência]]=""),"",YEAR(IF(tbLancamentos[[#This Row],[Competência]]<>"",tbLancamentos[[#This Row],[Competência]],tbLancamentos[[#This Row],[Data]]))) | T35: =IF(tbLancamentos[[#This Row],[Valor]]="","",IF(AND(tbLancamentos[[#This Row],[Tipo]]<>"Investimento",OR(tbLancamentos[[#This Row],[Situação]]="",tbLancamentos[[#This Row],[Situação]]="Pago",tbLancamentos[[#This Row],[Situação]]="Recebido",tbLancamentos[[#This Row],[Situação]]="Descontar Depois")),"sim","não"))
B36: 46185 | C36: Streaming + academia | D36: 174.8 | E36: Despesa | F36: Assinaturas | G36: Pago | H36: Essenciais | J36: Cartão Nubank | K36: Cartão de crédito | O36: Streaming | Q36: EXEMPLO | R36: =IF(AND(tbLancamentos[[#This Row],[Data]]="",tbLancamentos[[#This Row],[Competência]]=""),"",MONTH(IF(tbLancamentos[[#This Row],[Competência]]<>"",tbLancamentos[[#This Row],[Competência]],tbLancamentos[[#This Row],[Data]]))) | S36: =IF(AND(tbLancamentos[[#This Row],[Data]]="",tbLancamentos[[#This Row],[Competência]]=""),"",YEAR(IF(tbLancamentos[[#This Row],[Competência]]<>"",tbLancamentos[[#This Row],[Competência]],tbLancamentos[[#This Row],[Data]]))) | T36: =IF(tbLancamentos[[#This Row],[Valor]]="","",IF(AND(tbLancamentos[[#This Row],[Tipo]]<>"Investimento",OR(tbLancamentos[[#This Row],[Situação]]="",tbLancamentos[[#This Row],[Situação]]="Pago",tbLancamentos[[#This Row],[Situação]]="Recebido",tbLancamentos[[#This Row],[Situação]]="Descontar Depois")),"sim","não"))
B37: 46187 | C37: Festa junina da escola | D37: 95 | E37: Despesa | F37: Lazer | G37: Pago | H37: Lazer | J37: Carteira | K37: Dinheiro | O37: Passeios | Q37: EXEMPLO | R37: =IF(AND(tbLancamentos[[#This Row],[Data]]="",tbLancamentos[[#This Row],[Competência]]=""),"",MONTH(IF(tbLancamentos[[#This Row],[Competência]]<>"",tbLancamentos[[#This Row],[Competência]],tbLancamentos[[#This Row],[Data]]))) | S37: =IF(AND(tbLancamentos[[#This Row],[Data]]="",tbLancamentos[[#This Row],[Competência]]=""),"",YEAR(IF(tbLancamentos[[#This Row],[Competência]]<>"",tbLancamentos[[#This Row],[Competência]],tbLancamentos[[#This Row],[Data]]))) | T37: =IF(tbLancamentos[[#This Row],[Valor]]="","",IF(AND(tbLancamentos[[#This Row],[Tipo]]<>"Investimento",OR(tbLancamentos[[#This Row],[Situação]]="",tbLancamentos[[#This Row],[Situação]]="Pago",tbLancamentos[[#This Row],[Situação]]="Recebido",tbLancamentos[[#This Row],[Situação]]="Descontar Depois")),"sim","não"))
B38: 46188 | C38: Combustível | D38: 342.1 | E38: Despesa | F38: Transporte | G38: Pago | H38: Essenciais | J38: Cartão Itaú | K38: Cartão de crédito | O38: Combustível | Q38: EXEMPLO | R38: =IF(AND(tbLancamentos[[#This Row],[Data]]="",tbLancamentos[[#This Row],[Competência]]=""),"",MONTH(IF(tbLancamentos[[#This Row],[Competência]]<>"",tbLancamentos[[#This Row],[Competência]],tbLancamentos[[#This Row],[Data]]))) | S38: =IF(AND(tbLancamentos[[#This Row],[Data]]="",tbLancamentos[[#This Row],[Competência]]=""),"",YEAR(IF(tbLancamentos[[#This Row],[Competência]]<>"",tbLancamentos[[#This Row],[Competência]],tbLancamentos[[#This Row],[Data]]))) | T38: =IF(tbLancamentos[[#This Row],[Valor]]="","",IF(AND(tbLancamentos[[#This Row],[Tipo]]<>"Investimento",OR(tbLancamentos[[#This Row],[Situação]]="",tbLancamentos[[#This Row],[Situação]]="Pago",tbLancamentos[[#This Row],[Situação]]="Recebido",tbLancamentos[[#This Row],[Situação]]="Descontar Depois")),"sim","não"))
B39: 46194 | C39: Revisão do carro | D39: 780 | E39: Despesa | F39: Transporte | G39: Pago | H39: Essenciais | J39: Cartão Itaú | K39: Cartão de crédito | O39: Manutenção do carro | Q39: EXEMPLO | R39: =IF(AND(tbLancamentos[[#This Row],[Data]]="",tbLancamentos[[#This Row],[Competência]]=""),"",MONTH(IF(tbLancamentos[[#This Row],[Competência]]<>"",tbLancamentos[[#This Row],[Competência]],tbLancamentos[[#This Row],[Data]]))) | S39: =IF(AND(tbLancamentos[[#This Row],[Data]]="",tbLancamentos[[#This Row],[Competência]]=""),"",YEAR(IF(tbLancamentos[[#This Row],[Competência]]<>"",tbLancamentos[[#This Row],[Competência]],tbLancamentos[[#This Row],[Data]]))) | T39: =IF(tbLancamentos[[#This Row],[Valor]]="","",IF(AND(tbLancamentos[[#This Row],[Tipo]]<>"Investimento",OR(tbLancamentos[[#This Row],[Situação]]="",tbLancamentos[[#This Row],[Situação]]="Pago",tbLancamentos[[#This Row],[Situação]]="Recebido",tbLancamentos[[#This Row],[Situação]]="Descontar Depois")),"sim","não"))
B40: 46200 | C40: Cinema / passeio | D40: 72.5 | E40: Despesa | F40: Lazer | G40: Pago | H40: Lazer | J40: Conta Nubank | K40: PIX | O40: Cinema | Q40: EXEMPLO | R40: =IF(AND(tbLancamentos[[#This Row],[Data]]="",tbLancamentos[[#This Row],[Competência]]=""),"",MONTH(IF(tbLancamentos[[#This Row],[Competência]]<>"",tbLancamentos[[#This Row],[Competência]],tbLancamentos[[#This Row],[Data]]))) | S40: =IF(AND(tbLancamentos[[#This Row],[Data]]="",tbLancamentos[[#This Row],[Competência]]=""),"",YEAR(IF(tbLancamentos[[#This Row],[Competência]]<>"",tbLancamentos[[#This Row],[Competência]],tbLancamentos[[#This Row],[Data]]))) | T40: =IF(tbLancamentos[[#This Row],[Valor]]="","",IF(AND(tbLancamentos[[#This Row],[Tipo]]<>"Investimento",OR(tbLancamentos[[#This Row],[Situação]]="",tbLancamentos[[#This Row],[Situação]]="Pago",tbLancamentos[[#This Row],[Situação]]="Recebido",tbLancamentos[[#This Row],[Situação]]="Descontar Depois")),"sim","não"))
B41: 46206 | C41: Plano de saúde familiar | D41: 890 | E41: Despesa | F41: Saúde | G41: Pago | H41: Essenciais | J41: Conta corrente Itaú | K41: Débito automático | O41: Plano de saúde | Q41: EXEMPLO | R41: =IF(AND(tbLancamentos[[#This Row],[Data]]="",tbLancamentos[[#This Row],[Competência]]=""),"",MONTH(IF(tbLancamentos[[#This Row],[Competência]]<>"",tbLancamentos[[#This Row],[Competência]],tbLancamentos[[#This Row],[Data]]))) | S41: =IF(AND(tbLancamentos[[#This Row],[Data]]="",tbLancamentos[[#This Row],[Competência]]=""),"",YEAR(IF(tbLancamentos[[#This Row],[Competência]]<>"",tbLancamentos[[#This Row],[Competência]],tbLancamentos[[#This Row],[Data]]))) | T41: =IF(tbLancamentos[[#This Row],[Valor]]="","",IF(AND(tbLancamentos[[#This Row],[Tipo]]<>"Investimento",OR(tbLancamentos[[#This Row],[Situação]]="",tbLancamentos[[#This Row],[Situação]]="Pago",tbLancamentos[[#This Row],[Situação]]="Recebido",tbLancamentos[[#This Row],[Situação]]="Descontar Depois")),"sim","não"))
B42: 46208 | C42: Salário — titular | D42: 7800 | E42: Receita | F42: Salário | G42: Recebido | J42: Conta corrente Itaú | K42: Transferência | O42: Mensal | Q42: EXEMPLO | R42: =IF(AND(tbLancamentos[[#This Row],[Data]]="",tbLancamentos[[#This Row],[Competência]]=""),"",MONTH(IF(tbLancamentos[[#This Row],[Competência]]<>"",tbLancamentos[[#This Row],[Competência]],tbLancamentos[[#This Row],[Data]]))) | S42: =IF(AND(tbLancamentos[[#This Row],[Data]]="",tbLancamentos[[#This Row],[Competência]]=""),"",YEAR(IF(tbLancamentos[[#This Row],[Competência]]<>"",tbLancamentos[[#This Row],[Competência]],tbLancamentos[[#This Row],[Data]]))) | T42: =IF(tbLancamentos[[#This Row],[Valor]]="","",IF(AND(tbLancamentos[[#This Row],[Tipo]]<>"Investimento",OR(tbLancamentos[[#This Row],[Situação]]="",tbLancamentos[[#This Row],[Situação]]="Pago",tbLancamentos[[#This Row],[Situação]]="Recebido",tbLancamentos[[#This Row],[Situação]]="Descontar Depois")),"sim","não"))
B43: 46208 | C43: Salário — cônjuge | D43: 5200 | E43: Receita | F43: Salário | G43: Recebido | J43: Conta Nubank | K43: Transferência | O43: Mensal | Q43: EXEMPLO | R43: =IF(AND(tbLancamentos[[#This Row],[Data]]="",tbLancamentos[[#This Row],[Competência]]=""),"",MONTH(IF(tbLancamentos[[#This Row],[Competência]]<>"",tbLancamentos[[#This Row],[Competência]],tbLancamentos[[#This Row],[Data]]))) | S43: =IF(AND(tbLancamentos[[#This Row],[Data]]="",tbLancamentos[[#This Row],[Competência]]=""),"",YEAR(IF(tbLancamentos[[#This Row],[Competência]]<>"",tbLancamentos[[#This Row],[Competência]],tbLancamentos[[#This Row],[Data]]))) | T43: =IF(tbLancamentos[[#This Row],[Valor]]="","",IF(AND(tbLancamentos[[#This Row],[Tipo]]<>"Investimento",OR(tbLancamentos[[#This Row],[Situação]]="",tbLancamentos[[#This Row],[Situação]]="Pago",tbLancamentos[[#This Row],[Situação]]="Recebido",tbLancamentos[[#This Row],[Situação]]="Descontar Depois")),"sim","não"))
B44: 46210 | C44: Mercado do mês | D44: 1012.3 | E44: Despesa | F44: Alimentação | G44: Pago | H44: Essenciais | J44: Cartão Nubank | K44: Cartão de crédito | O44: Mercado | Q44: EXEMPLO | R44: =IF(AND(tbLancamentos[[#This Row],[Data]]="",tbLancamentos[[#This Row],[Competência]]=""),"",MONTH(IF(tbLancamentos[[#This Row],[Competência]]<>"",tbLancamentos[[#This Row],[Competência]],tbLancamentos[[#This Row],[Data]]))) | S44: =IF(AND(tbLancamentos[[#This Row],[Data]]="",tbLancamentos[[#This Row],[Competência]]=""),"",YEAR(IF(tbLancamentos[[#This Row],[Competência]]<>"",tbLancamentos[[#This Row],[Competência]],tbLancamentos[[#This Row],[Data]]))) | T44: =IF(tbLancamentos[[#This Row],[Valor]]="","",IF(AND(tbLancamentos[[#This Row],[Tipo]]<>"Investimento",OR(tbLancamentos[[#This Row],[Situação]]="",tbLancamentos[[#This Row],[Situação]]="Pago",tbLancamentos[[#This Row],[Situação]]="Recebido",tbLancamentos[[#This Row],[Situação]]="Descontar Depois")),"sim","não"))
B45: 46211 | C45: Mensalidade escolar | D45: 1450 | E45: Despesa | F45: Educação | G45: Pago | H45: Essenciais | J45: Conta corrente Itaú | K45: Boleto | O45: Escola | Q45: EXEMPLO | R45: =IF(AND(tbLancamentos[[#This Row],[Data]]="",tbLancamentos[[#This Row],[Competência]]=""),"",MONTH(IF(tbLancamentos[[#This Row],[Competência]]<>"",tbLancamentos[[#This Row],[Competência]],tbLancamentos[[#This Row],[Data]]))) | S45: =IF(AND(tbLancamentos[[#This Row],[Data]]="",tbLancamentos[[#This Row],[Competência]]=""),"",YEAR(IF(tbLancamentos[[#This Row],[Competência]]<>"",tbLancamentos[[#This Row],[Competência]],tbLancamentos[[#This Row],[Data]]))) | T45: =IF(tbLancamentos[[#This Row],[Valor]]="","",IF(AND(tbLancamentos[[#This Row],[Tipo]]<>"Investimento",OR(tbLancamentos[[#This Row],[Situação]]="",tbLancamentos[[#This Row],[Situação]]="Pago",tbLancamentos[[#This Row],[Situação]]="Recebido",tbLancamentos[[#This Row],[Situação]]="Descontar Depois")),"sim","não"))
B46: 46211 | C46: Viagem de férias — hotel | D46: 1650 | E46: Despesa | F46: Lazer | G46: Pago | H46: Lazer | J46: Cartão Itaú | K46: Cartão de crédito | O46: Viagens | Q46: EXEMPLO | R46: =IF(AND(tbLancamentos[[#This Row],[Data]]="",tbLancamentos[[#This Row],[Competência]]=""),"",MONTH(IF(tbLancamentos[[#This Row],[Competência]]<>"",tbLancamentos[[#This Row],[Competência]],tbLancamentos[[#This Row],[Data]]))) | S46: =IF(AND(tbLancamentos[[#This Row],[Data]]="",tbLancamentos[[#This Row],[Competência]]=""),"",YEAR(IF(tbLancamentos[[#This Row],[Competência]]<>"",tbLancamentos[[#This Row],[Competência]],tbLancamentos[[#This Row],[Data]]))) | T46: =IF(tbLancamentos[[#This Row],[Valor]]="","",IF(AND(tbLancamentos[[#This Row],[Tipo]]<>"Investimento",OR(tbLancamentos[[#This Row],[Situação]]="",tbLancamentos[[#This Row],[Situação]]="Pago",tbLancamentos[[#This Row],[Situação]]="Recebido",tbLancamentos[[#This Row],[Situação]]="Descontar Depois")),"sim","não"))
B47: 46213 | C47: Aluguel do apartamento | D47: 2350 | E47: Despesa | F47: Moradia | G47: Pago | H47: Essenciais | J47: Conta corrente Itaú | K47: Boleto | O47: Aluguel/Financiamento | Q47: EXEMPLO | R47: =IF(AND(tbLancamentos[[#This Row],[Data]]="",tbLancamentos[[#This Row],[Competência]]=""),"",MONTH(IF(tbLancamentos[[#This Row],[Competência]]<>"",tbLancamentos[[#This Row],[Competência]],tbLancamentos[[#This Row],[Data]]))) | S47: =IF(AND(tbLancamentos[[#This Row],[Data]]="",tbLancamentos[[#This Row],[Competência]]=""),"",YEAR(IF(tbLancamentos[[#This Row],[Competência]]<>"",tbLancamentos[[#This Row],[Competência]],tbLancamentos[[#This Row],[Data]]))) | T47: =IF(tbLancamentos[[#This Row],[Valor]]="","",IF(AND(tbLancamentos[[#This Row],[Tipo]]<>"Investimento",OR(tbLancamentos[[#This Row],[Situação]]="",tbLancamentos[[#This Row],[Situação]]="Pago",tbLancamentos[[#This Row],[Situação]]="Recebido",tbLancamentos[[#This Row],[Situação]]="Descontar Depois")),"sim","não"))
B48: 46213 | C48: Conta de energia | D48: 301.22 | E48: Despesa | F48: Contas da casa | G48: Pago | H48: Essenciais | J48: Conta corrente Itaú | K48: Débito automático | O48: Energia | Q48: EXEMPLO | R48: =IF(AND(tbLancamentos[[#This Row],[Data]]="",tbLancamentos[[#This Row],[Competência]]=""),"",MONTH(IF(tbLancamentos[[#This Row],[Competência]]<>"",tbLancamentos[[#This Row],[Competência]],tbLancamentos[[#This Row],[Data]]))) | S48: =IF(AND(tbLancamentos[[#This Row],[Data]]="",tbLancamentos[[#This Row],[Competência]]=""),"",YEAR(IF(tbLancamentos[[#This Row],[Competência]]<>"",tbLancamentos[[#This Row],[Competência]],tbLancamentos[[#This Row],[Data]]))) | T48: =IF(tbLancamentos[[#This Row],[Valor]]="","",IF(AND(tbLancamentos[[#This Row],[Tipo]]<>"Investimento",OR(tbLancamentos[[#This Row],[Situação]]="",tbLancamentos[[#This Row],[Situação]]="Pago",tbLancamentos[[#This Row],[Situação]]="Recebido",tbLancamentos[[#This Row],[Situação]]="Descontar Depois")),"sim","não"))
B49: 46215 | C49: Streaming + academia | D49: 174.8 | E49: Despesa | F49: Assinaturas | G49: Pago | H49: Essenciais | J49: Cartão Nubank | K49: Cartão de crédito | O49: Streaming | Q49: EXEMPLO | R49: =IF(AND(tbLancamentos[[#This Row],[Data]]="",tbLancamentos[[#This Row],[Competência]]=""),"",MONTH(IF(tbLancamentos[[#This Row],[Competência]]<>"",tbLancamentos[[#This Row],[Competência]],tbLancamentos[[#This Row],[Data]]))) | S49: =IF(AND(tbLancamentos[[#This Row],[Data]]="",tbLancamentos[[#This Row],[Competência]]=""),"",YEAR(IF(tbLancamentos[[#This Row],[Competência]]<>"",tbLancamentos[[#This Row],[Competência]],tbLancamentos[[#This Row],[Data]]))) | T49: =IF(tbLancamentos[[#This Row],[Valor]]="","",IF(AND(tbLancamentos[[#This Row],[Tipo]]<>"Investimento",OR(tbLancamentos[[#This Row],[Situação]]="",tbLancamentos[[#This Row],[Situação]]="Pago",tbLancamentos[[#This Row],[Situação]]="Recebido",tbLancamentos[[#This Row],[Situação]]="Descontar Depois")),"sim","não"))
B50: 46218 | C50: Combustível | D50: 398 | E50: Despesa | F50: Transporte | G50: Pago | H50: Essenciais | J50: Cartão Itaú | K50: Cartão de crédito | O50: Combustível | Q50: EXEMPLO | R50: =IF(AND(tbLancamentos[[#This Row],[Data]]="",tbLancamentos[[#This Row],[Competência]]=""),"",MONTH(IF(tbLancamentos[[#This Row],[Competência]]<>"",tbLancamentos[[#This Row],[Competência]],tbLancamentos[[#This Row],[Data]]))) | S50: =IF(AND(tbLancamentos[[#This Row],[Data]]="",tbLancamentos[[#This Row],[Competência]]=""),"",YEAR(IF(tbLancamentos[[#This Row],[Competência]]<>"",tbLancamentos[[#This Row],[Competência]],tbLancamentos[[#This Row],[Data]]))) | T50: =IF(tbLancamentos[[#This Row],[Valor]]="","",IF(AND(tbLancamentos[[#This Row],[Tipo]]<>"Investimento",OR(tbLancamentos[[#This Row],[Situação]]="",tbLancamentos[[#This Row],[Situação]]="Pago",tbLancamentos[[#This Row],[Situação]]="Recebido",tbLancamentos[[#This Row],[Situação]]="Descontar Depois")),"sim","não"))
B51: 46222 | C51: Reembolso plano de saúde | D51: 320 | E51: Receita | F51: Reembolsos | G51: Recebido | J51: Conta corrente Itaú | K51: Transferência | O51: Consulta | Q51: EXEMPLO | R51: =IF(AND(tbLancamentos[[#This Row],[Data]]="",tbLancamentos[[#This Row],[Competência]]=""),"",MONTH(IF(tbLancamentos[[#This Row],[Competência]]<>"",tbLancamentos[[#This Row],[Competência]],tbLancamentos[[#This Row],[Data]]))) | S51: =IF(AND(tbLancamentos[[#This Row],[Data]]="",tbLancamentos[[#This Row],[Competência]]=""),"",YEAR(IF(tbLancamentos[[#This Row],[Competência]]<>"",tbLancamentos[[#This Row],[Competência]],tbLancamentos[[#This Row],[Data]]))) | T51: =IF(tbLancamentos[[#This Row],[Valor]]="","",IF(AND(tbLancamentos[[#This Row],[Tipo]]<>"Investimento",OR(tbLancamentos[[#This Row],[Situação]]="",tbLancamentos[[#This Row],[Situação]]="Pago",tbLancamentos[[#This Row],[Situação]]="Recebido",tbLancamentos[[#This Row],[Situação]]="Descontar Depois")),"sim","não"))
B52: 46230 | C52: Cinema / passeio | D52: 145 | E52: Despesa | F52: Lazer | G52: Pago | H52: Lazer | J52: Conta Nubank | K52: PIX | O52: Cinema | Q52: EXEMPLO | R52: =IF(AND(tbLancamentos[[#This Row],[Data]]="",tbLancamentos[[#This Row],[Competência]]=""),"",MONTH(IF(tbLancamentos[[#This Row],[Competência]]<>"",tbLancamentos[[#This Row],[Competência]],tbLancamentos[[#This Row],[Data]]))) | S52: =IF(AND(tbLancamentos[[#This Row],[Data]]="",tbLancamentos[[#This Row],[Competência]]=""),"",YEAR(IF(tbLancamentos[[#This Row],[Competência]]<>"",tbLancamentos[[#This Row],[Competência]],tbLancamentos[[#This Row],[Data]]))) | T52: =IF(tbLancamentos[[#This Row],[Valor]]="","",IF(AND(tbLancamentos[[#This Row],[Tipo]]<>"Investimento",OR(tbLancamentos[[#This Row],[Situação]]="",tbLancamentos[[#This Row],[Situação]]="Pago",tbLancamentos[[#This Row],[Situação]]="Recebido",tbLancamentos[[#This Row],[Situação]]="Descontar Depois")),"sim","não"))
B53: 46237 | C53: Plano de saúde familiar | D53: 890 | E53: Despesa | F53: Saúde | G53: Pago | H53: Essenciais | J53: Conta corrente Itaú | K53: Débito automático | O53: Plano de saúde | Q53: EXEMPLO | R53: =IF(AND(tbLancamentos[[#This Row],[Data]]="",tbLancamentos[[#This Row],[Competência]]=""),"",MONTH(IF(tbLancamentos[[#This Row],[Competência]]<>"",tbLancamentos[[#This Row],[Competência]],tbLancamentos[[#This Row],[Data]]))) | S53: =IF(AND(tbLancamentos[[#This Row],[Data]]="",tbLancamentos[[#This Row],[Competência]]=""),"",YEAR(IF(tbLancamentos[[#This Row],[Competência]]<>"",tbLancamentos[[#This Row],[Competência]],tbLancamentos[[#This Row],[Data]]))) | T53: =IF(tbLancamentos[[#This Row],[Valor]]="","",IF(AND(tbLancamentos[[#This Row],[Tipo]]<>"Investimento",OR(tbLancamentos[[#This Row],[Situação]]="",tbLancamentos[[#This Row],[Situação]]="Pago",tbLancamentos[[#This Row],[Situação]]="Recebido",tbLancamentos[[#This Row],[Situação]]="Descontar Depois")),"sim","não"))
B54: 46239 | C54: Salário — titular | D54: 7800 | E54: Receita | F54: Salário | G54: Recebido | J54: Conta corrente Itaú | K54: Transferência | O54: Mensal | Q54: EXEMPLO | R54: =IF(AND(tbLancamentos[[#This Row],[Data]]="",tbLancamentos[[#This Row],[Competência]]=""),"",MONTH(IF(tbLancamentos[[#This Row],[Competência]]<>"",tbLancamentos[[#This Row],[Competência]],tbLancamentos[[#This Row],[Data]]))) | S54: =IF(AND(tbLancamentos[[#This Row],[Data]]="",tbLancamentos[[#This Row],[Competência]]=""),"",YEAR(IF(tbLancamentos[[#This Row],[Competência]]<>"",tbLancamentos[[#This Row],[Competência]],tbLancamentos[[#This Row],[Data]]))) | T54: =IF(tbLancamentos[[#This Row],[Valor]]="","",IF(AND(tbLancamentos[[#This Row],[Tipo]]<>"Investimento",OR(tbLancamentos[[#This Row],[Situação]]="",tbLancamentos[[#This Row],[Situação]]="Pago",tbLancamentos[[#This Row],[Situação]]="Recebido",tbLancamentos[[#This Row],[Situação]]="Descontar Depois")),"sim","não"))
B55: 46239 | C55: Salário — cônjuge | D55: 5200 | E55: Receita | F55: Salário | G55: Recebido | J55: Conta Nubank | K55: Transferência | O55: Mensal | Q55: EXEMPLO | R55: =IF(AND(tbLancamentos[[#This Row],[Data]]="",tbLancamentos[[#This Row],[Competência]]=""),"",MONTH(IF(tbLancamentos[[#This Row],[Competência]]<>"",tbLancamentos[[#This Row],[Competência]],tbLancamentos[[#This Row],[Data]]))) | S55: =IF(AND(tbLancamentos[[#This Row],[Data]]="",tbLancamentos[[#This Row],[Competência]]=""),"",YEAR(IF(tbLancamentos[[#This Row],[Competência]]<>"",tbLancamentos[[#This Row],[Competência]],tbLancamentos[[#This Row],[Data]]))) | T55: =IF(tbLancamentos[[#This Row],[Valor]]="","",IF(AND(tbLancamentos[[#This Row],[Tipo]]<>"Investimento",OR(tbLancamentos[[#This Row],[Situação]]="",tbLancamentos[[#This Row],[Situação]]="Pago",tbLancamentos[[#This Row],[Situação]]="Recebido",tbLancamentos[[#This Row],[Situação]]="Descontar Depois")),"sim","não"))
B56: 46241 | C56: Mercado do mês | D56: 876.9 | E56: Despesa | F56: Alimentação | G56: Pago | H56: Essenciais | J56: Cartão Nubank | K56: Cartão de crédito | O56: Mercado | Q56: EXEMPLO | R56: =IF(AND(tbLancamentos[[#This Row],[Data]]="",tbLancamentos[[#This Row],[Competência]]=""),"",MONTH(IF(tbLancamentos[[#This Row],[Competência]]<>"",tbLancamentos[[#This Row],[Competência]],tbLancamentos[[#This Row],[Data]]))) | S56: =IF(AND(tbLancamentos[[#This Row],[Data]]="",tbLancamentos[[#This Row],[Competência]]=""),"",YEAR(IF(tbLancamentos[[#This Row],[Competência]]<>"",tbLancamentos[[#This Row],[Competência]],tbLancamentos[[#This Row],[Data]]))) | T56: =IF(tbLancamentos[[#This Row],[Valor]]="","",IF(AND(tbLancamentos[[#This Row],[Tipo]]<>"Investimento",OR(tbLancamentos[[#This Row],[Situação]]="",tbLancamentos[[#This Row],[Situação]]="Pago",tbLancamentos[[#This Row],[Situação]]="Recebido",tbLancamentos[[#This Row],[Situação]]="Descontar Depois")),"sim","não"))
B57: 46242 | C57: Mensalidade escolar | D57: 1450 | E57: Despesa | F57: Educação | G57: Pago | H57: Essenciais | J57: Conta corrente Itaú | K57: Boleto | O57: Escola | Q57: EXEMPLO | R57: =IF(AND(tbLancamentos[[#This Row],[Data]]="",tbLancamentos[[#This Row],[Competência]]=""),"",MONTH(IF(tbLancamentos[[#This Row],[Competência]]<>"",tbLancamentos[[#This Row],[Competência]],tbLancamentos[[#This Row],[Data]]))) | S57: =IF(AND(tbLancamentos[[#This Row],[Data]]="",tbLancamentos[[#This Row],[Competência]]=""),"",YEAR(IF(tbLancamentos[[#This Row],[Competência]]<>"",tbLancamentos[[#This Row],[Competência]],tbLancamentos[[#This Row],[Data]]))) | T57: =IF(tbLancamentos[[#This Row],[Valor]]="","",IF(AND(tbLancamentos[[#This Row],[Tipo]]<>"Investimento",OR(tbLancamentos[[#This Row],[Situação]]="",tbLancamentos[[#This Row],[Situação]]="Pago",tbLancamentos[[#This Row],[Situação]]="Recebido",tbLancamentos[[#This Row],[Situação]]="Descontar Depois")),"sim","não"))
B58: 46243 | C58: Projeto freelance — logo | D58: 2400 | E58: Receita | F58: Freelance / Extras | G58: Recebido | J58: Conta Nubank | K58: PIX | O58: Projeto | Q58: EXEMPLO | R58: =IF(AND(tbLancamentos[[#This Row],[Data]]="",tbLancamentos[[#This Row],[Competência]]=""),"",MONTH(IF(tbLancamentos[[#This Row],[Competência]]<>"",tbLancamentos[[#This Row],[Competência]],tbLancamentos[[#This Row],[Data]]))) | S58: =IF(AND(tbLancamentos[[#This Row],[Data]]="",tbLancamentos[[#This Row],[Competência]]=""),"",YEAR(IF(tbLancamentos[[#This Row],[Competência]]<>"",tbLancamentos[[#This Row],[Competência]],tbLancamentos[[#This Row],[Data]]))) | T58: =IF(tbLancamentos[[#This Row],[Valor]]="","",IF(AND(tbLancamentos[[#This Row],[Tipo]]<>"Investimento",OR(tbLancamentos[[#This Row],[Situação]]="",tbLancamentos[[#This Row],[Situação]]="Pago",tbLancamentos[[#This Row],[Situação]]="Recebido",tbLancamentos[[#This Row],[Situação]]="Descontar Depois")),"sim","não"))
B59: 46244 | C59: Aluguel do apartamento | D59: 2350 | E59: Despesa | F59: Moradia | G59: Pago | H59: Essenciais | J59: Conta corrente Itaú | K59: Boleto | O59: Aluguel/Financiamento | Q59: EXEMPLO | R59: =IF(AND(tbLancamentos[[#This Row],[Data]]="",tbLancamentos[[#This Row],[Competência]]=""),"",MONTH(IF(tbLancamentos[[#This Row],[Competência]]<>"",tbLancamentos[[#This Row],[Competência]],tbLancamentos[[#This Row],[Data]]))) | S59: =IF(AND(tbLancamentos[[#This Row],[Data]]="",tbLancamentos[[#This Row],[Competência]]=""),"",YEAR(IF(tbLancamentos[[#This Row],[Competência]]<>"",tbLancamentos[[#This Row],[Competência]],tbLancamentos[[#This Row],[Data]]))) | T59: =IF(tbLancamentos[[#This Row],[Valor]]="","",IF(AND(tbLancamentos[[#This Row],[Tipo]]<>"Investimento",OR(tbLancamentos[[#This Row],[Situação]]="",tbLancamentos[[#This Row],[Situação]]="Pago",tbLancamentos[[#This Row],[Situação]]="Recebido",tbLancamentos[[#This Row],[Situação]]="Descontar Depois")),"sim","não"))
B60: 46244 | C60: Conta de energia | D60: 329.64 | E60: Despesa | F60: Contas da casa | G60: Pago | H60: Essenciais | J60: Conta corrente Itaú | K60: Débito automático | O60: Energia | Q60: EXEMPLO | R60: =IF(AND(tbLancamentos[[#This Row],[Data]]="",tbLancamentos[[#This Row],[Competência]]=""),"",MONTH(IF(tbLancamentos[[#This Row],[Competência]]<>"",tbLancamentos[[#This Row],[Competência]],tbLancamentos[[#This Row],[Data]]))) | S60: =IF(AND(tbLancamentos[[#This Row],[Data]]="",tbLancamentos[[#This Row],[Competência]]=""),"",YEAR(IF(tbLancamentos[[#This Row],[Competência]]<>"",tbLancamentos[[#This Row],[Competência]],tbLancamentos[[#This Row],[Data]]))) | T60: =IF(tbLancamentos[[#This Row],[Valor]]="","",IF(AND(tbLancamentos[[#This Row],[Tipo]]<>"Investimento",OR(tbLancamentos[[#This Row],[Situação]]="",tbLancamentos[[#This Row],[Situação]]="Pago",tbLancamentos[[#This Row],[Situação]]="Recebido",tbLancamentos[[#This Row],[Situação]]="Descontar Depois")),"sim","não"))
B61: 46246 | C61: Streaming + academia | D61: 174.8 | E61: Despesa | F61: Assinaturas | G61: Pago | H61: Essenciais | J61: Cartão Nubank | K61: Cartão de crédito | O61: Streaming | Q61: EXEMPLO | R61: =IF(AND(tbLancamentos[[#This Row],[Data]]="",tbLancamentos[[#This Row],[Competência]]=""),"",MONTH(IF(tbLancamentos[[#This Row],[Competência]]<>"",tbLancamentos[[#This Row],[Competência]],tbLancamentos[[#This Row],[Data]]))) | S61: =IF(AND(tbLancamentos[[#This Row],[Data]]="",tbLancamentos[[#This Row],[Competência]]=""),"",YEAR(IF(tbLancamentos[[#This Row],[Competência]]<>"",tbLancamentos[[#This Row],[Competência]],tbLancamentos[[#This Row],[Data]]))) | T61: =IF(tbLancamentos[[#This Row],[Valor]]="","",IF(AND(tbLancamentos[[#This Row],[Tipo]]<>"Investimento",OR(tbLancamentos[[#This Row],[Situação]]="",tbLancamentos[[#This Row],[Situação]]="Pago",tbLancamentos[[#This Row],[Situação]]="Recebido",tbLancamentos[[#This Row],[Situação]]="Descontar Depois")),"sim","não"))
B62: 46249 | C62: Combustível | D62: 305.4 | E62: Despesa | F62: Transporte | G62: Pago | H62: Essenciais | J62: Cartão Itaú | K62: Cartão de crédito | O62: Combustível | Q62: EXEMPLO | R62: =IF(AND(tbLancamentos[[#This Row],[Data]]="",tbLancamentos[[#This Row],[Competência]]=""),"",MONTH(IF(tbLancamentos[[#This Row],[Competência]]<>"",tbLancamentos[[#This Row],[Competência]],tbLancamentos[[#This Row],[Data]]))) | S62: =IF(AND(tbLancamentos[[#This Row],[Data]]="",tbLancamentos[[#This Row],[Competência]]=""),"",YEAR(IF(tbLancamentos[[#This Row],[Competência]]<>"",tbLancamentos[[#This Row],[Competência]],tbLancamentos[[#This Row],[Data]]))) | T62: =IF(tbLancamentos[[#This Row],[Valor]]="","",IF(AND(tbLancamentos[[#This Row],[Tipo]]<>"Investimento",OR(tbLancamentos[[#This Row],[Situação]]="",tbLancamentos[[#This Row],[Situação]]="Pago",tbLancamentos[[#This Row],[Situação]]="Recebido",tbLancamentos[[#This Row],[Situação]]="Descontar Depois")),"sim","não"))
B63: 46256 | C63: Material escolar 2º semestre | D63: 356.7 | E63: Despesa | F63: Educação | G63: Pago | H63: Essenciais | J63: Cartão Nubank | K63: Cartão de crédito | O63: Material escolar | Q63: EXEMPLO | R63: =IF(AND(tbLancamentos[[#This Row],[Data]]="",tbLancamentos[[#This Row],[Competência]]=""),"",MONTH(IF(tbLancamentos[[#This Row],[Competência]]<>"",tbLancamentos[[#This Row],[Competência]],tbLancamentos[[#This Row],[Data]]))) | S63: =IF(AND(tbLancamentos[[#This Row],[Data]]="",tbLancamentos[[#This Row],[Competência]]=""),"",YEAR(IF(tbLancamentos[[#This Row],[Competência]]<>"",tbLancamentos[[#This Row],[Competência]],tbLancamentos[[#This Row],[Data]]))) | T63: =IF(tbLancamentos[[#This Row],[Valor]]="","",IF(AND(tbLancamentos[[#This Row],[Tipo]]<>"Investimento",OR(tbLancamentos[[#This Row],[Situação]]="",tbLancamentos[[#This Row],[Situação]]="Pago",tbLancamentos[[#This Row],[Situação]]="Recebido",tbLancamentos[[#This Row],[Situação]]="Descontar Depois")),"sim","não"))
B64: 46261 | C64: Cinema / passeio | D64: 96 | E64: Despesa | F64: Lazer | G64: Pago | H64: Lazer | J64: Conta Nubank | K64: PIX | O64: Cinema | Q64: EXEMPLO | R64: =IF(AND(tbLancamentos[[#This Row],[Data]]="",tbLancamentos[[#This Row],[Competência]]=""),"",MONTH(IF(tbLancamentos[[#This Row],[Competência]]<>"",tbLancamentos[[#This Row],[Competência]],tbLancamentos[[#This Row],[Data]]))) | S64: =IF(AND(tbLancamentos[[#This Row],[Data]]="",tbLancamentos[[#This Row],[Competência]]=""),"",YEAR(IF(tbLancamentos[[#This Row],[Competência]]<>"",tbLancamentos[[#This Row],[Competência]],tbLancamentos[[#This Row],[Data]]))) | T64: =IF(tbLancamentos[[#This Row],[Valor]]="","",IF(AND(tbLancamentos[[#This Row],[Tipo]]<>"Investimento",OR(tbLancamentos[[#This Row],[Situação]]="",tbLancamentos[[#This Row],[Situação]]="Pago",tbLancamentos[[#This Row],[Situação]]="Recebido",tbLancamentos[[#This Row],[Situação]]="Descontar Depois")),"sim","não"))
B65: 46268 | C65: Plano de saúde familiar | D65: 890 | E65: Despesa | F65: Saúde | G65: Pago | H65: Essenciais | J65: Conta corrente Itaú | K65: Débito automático | O65: Plano de saúde | Q65: EXEMPLO | R65: =IF(AND(tbLancamentos[[#This Row],[Data]]="",tbLancamentos[[#This Row],[Competência]]=""),"",MONTH(IF(tbLancamentos[[#This Row],[Competência]]<>"",tbLancamentos[[#This Row],[Competência]],tbLancamentos[[#This Row],[Data]]))) | S65: =IF(AND(tbLancamentos[[#This Row],[Data]]="",tbLancamentos[[#This Row],[Competência]]=""),"",YEAR(IF(tbLancamentos[[#This Row],[Competência]]<>"",tbLancamentos[[#This Row],[Competência]],tbLancamentos[[#This Row],[Data]]))) | T65: =IF(tbLancamentos[[#This Row],[Valor]]="","",IF(AND(tbLancamentos[[#This Row],[Tipo]]<>"Investimento",OR(tbLancamentos[[#This Row],[Situação]]="",tbLancamentos[[#This Row],[Situação]]="Pago",tbLancamentos[[#This Row],[Situação]]="Recebido",tbLancamentos[[#This Row],[Situação]]="Descontar Depois")),"sim","não"))
B66: 46270 | C66: Salário — titular | D66: 7800 | E66: Receita | F66: Salário | G66: Recebido | J66: Conta corrente Itaú | K66: Transferência | O66: Mensal | Q66: EXEMPLO | R66: =IF(AND(tbLancamentos[[#This Row],[Data]]="",tbLancamentos[[#This Row],[Competência]]=""),"",MONTH(IF(tbLancamentos[[#This Row],[Competência]]<>"",tbLancamentos[[#This Row],[Competência]],tbLancamentos[[#This Row],[Data]]))) | S66: =IF(AND(tbLancamentos[[#This Row],[Data]]="",tbLancamentos[[#This Row],[Competência]]=""),"",YEAR(IF(tbLancamentos[[#This Row],[Competência]]<>"",tbLancamentos[[#This Row],[Competência]],tbLancamentos[[#This Row],[Data]]))) | T66: =IF(tbLancamentos[[#This Row],[Valor]]="","",IF(AND(tbLancamentos[[#This Row],[Tipo]]<>"Investimento",OR(tbLancamentos[[#This Row],[Situação]]="",tbLancamentos[[#This Row],[Situação]]="Pago",tbLancamentos[[#This Row],[Situação]]="Recebido",tbLancamentos[[#This Row],[Situação]]="Descontar Depois")),"sim","não"))
B67: 46270 | C67: Salário — cônjuge | D67: 5200 | E67: Receita | F67: Salário | G67: Recebido | J67: Conta Nubank | K67: Transferência | O67: Mensal | Q67: EXEMPLO | R67: =IF(AND(tbLancamentos[[#This Row],[Data]]="",tbLancamentos[[#This Row],[Competência]]=""),"",MONTH(IF(tbLancamentos[[#This Row],[Competência]]<>"",tbLancamentos[[#This Row],[Competência]],tbLancamentos[[#This Row],[Data]]))) | S67: =IF(AND(tbLancamentos[[#This Row],[Data]]="",tbLancamentos[[#This Row],[Competência]]=""),"",YEAR(IF(tbLancamentos[[#This Row],[Competência]]<>"",tbLancamentos[[#This Row],[Competência]],tbLancamentos[[#This Row],[Data]]))) | T67: =IF(tbLancamentos[[#This Row],[Valor]]="","",IF(AND(tbLancamentos[[#This Row],[Tipo]]<>"Investimento",OR(tbLancamentos[[#This Row],[Situação]]="",tbLancamentos[[#This Row],[Situação]]="Pago",tbLancamentos[[#This Row],[Situação]]="Recebido",tbLancamentos[[#This Row],[Situação]]="Descontar Depois")),"sim","não"))
B68: 46272 | C68: Mercado do mês | D68: 934.18 | E68: Despesa | F68: Alimentação | G68: Pago | H68: Essenciais | J68: Cartão Nubank | K68: Cartão de crédito | O68: Mercado | Q68: EXEMPLO | R68: =IF(AND(tbLancamentos[[#This Row],[Data]]="",tbLancamentos[[#This Row],[Competência]]=""),"",MONTH(IF(tbLancamentos[[#This Row],[Competência]]<>"",tbLancamentos[[#This Row],[Competência]],tbLancamentos[[#This Row],[Data]]))) | S68: =IF(AND(tbLancamentos[[#This Row],[Data]]="",tbLancamentos[[#This Row],[Competência]]=""),"",YEAR(IF(tbLancamentos[[#This Row],[Competência]]<>"",tbLancamentos[[#This Row],[Competência]],tbLancamentos[[#This Row],[Data]]))) | T68: =IF(tbLancamentos[[#This Row],[Valor]]="","",IF(AND(tbLancamentos[[#This Row],[Tipo]]<>"Investimento",OR(tbLancamentos[[#This Row],[Situação]]="",tbLancamentos[[#This Row],[Situação]]="Pago",tbLancamentos[[#This Row],[Situação]]="Recebido",tbLancamentos[[#This Row],[Situação]]="Descontar Depois")),"sim","não"))
B69: 46273 | C69: Mensalidade escolar | D69: 1450 | E69: Despesa | F69: Educação | G69: Pago | H69: Essenciais | J69: Conta corrente Itaú | K69: Boleto | O69: Escola | Q69: EXEMPLO | R69: =IF(AND(tbLancamentos[[#This Row],[Data]]="",tbLancamentos[[#This Row],[Competência]]=""),"",MONTH(IF(tbLancamentos[[#This Row],[Competência]]<>"",tbLancamentos[[#This Row],[Competência]],tbLancamentos[[#This Row],[Data]]))) | S69: =IF(AND(tbLancamentos[[#This Row],[Data]]="",tbLancamentos[[#This Row],[Competência]]=""),"",YEAR(IF(tbLancamentos[[#This Row],[Competência]]<>"",tbLancamentos[[#This Row],[Competência]],tbLancamentos[[#This Row],[Data]]))) | T69: =IF(tbLancamentos[[#This Row],[Valor]]="","",IF(AND(tbLancamentos[[#This Row],[Tipo]]<>"Investimento",OR(tbLancamentos[[#This Row],[Situação]]="",tbLancamentos[[#This Row],[Situação]]="Pago",tbLancamentos[[#This Row],[Situação]]="Recebido",tbLancamentos[[#This Row],[Situação]]="Descontar Depois")),"sim","não"))
B70: 46275 | C70: Aluguel do apartamento | D70: 2350 | E70: Despesa | F70: Moradia | G70: Pago | H70: Essenciais | J70: Conta corrente Itaú | K70: Boleto | O70: Aluguel/Financiamento | Q70: EXEMPLO | R70: =IF(AND(tbLancamentos[[#This Row],[Data]]="",tbLancamentos[[#This Row],[Competência]]=""),"",MONTH(IF(tbLancamentos[[#This Row],[Competência]]<>"",tbLancamentos[[#This Row],[Competência]],tbLancamentos[[#This Row],[Data]]))) | S70: =IF(AND(tbLancamentos[[#This Row],[Data]]="",tbLancamentos[[#This Row],[Competência]]=""),"",YEAR(IF(tbLancamentos[[#This Row],[Competência]]<>"",tbLancamentos[[#This Row],[Competência]],tbLancamentos[[#This Row],[Data]]))) | T70: =IF(tbLancamentos[[#This Row],[Valor]]="","",IF(AND(tbLancamentos[[#This Row],[Tipo]]<>"Investimento",OR(tbLancamentos[[#This Row],[Situação]]="",tbLancamentos[[#This Row],[Situação]]="Pago",tbLancamentos[[#This Row],[Situação]]="Recebido",tbLancamentos[[#This Row],[Situação]]="Descontar Depois")),"sim","não"))
B71: 46275 | C71: Conta de energia | D71: 347.1 | E71: Despesa | F71: Contas da casa | G71: Pago | H71: Essenciais | J71: Conta corrente Itaú | K71: Débito automático | O71: Energia | Q71: EXEMPLO | R71: =IF(AND(tbLancamentos[[#This Row],[Data]]="",tbLancamentos[[#This Row],[Competência]]=""),"",MONTH(IF(tbLancamentos[[#This Row],[Competência]]<>"",tbLancamentos[[#This Row],[Competência]],tbLancamentos[[#This Row],[Data]]))) | S71: =IF(AND(tbLancamentos[[#This Row],[Data]]="",tbLancamentos[[#This Row],[Competência]]=""),"",YEAR(IF(tbLancamentos[[#This Row],[Competência]]<>"",tbLancamentos[[#This Row],[Competência]],tbLancamentos[[#This Row],[Data]]))) | T71: =IF(tbLancamentos[[#This Row],[Valor]]="","",IF(AND(tbLancamentos[[#This Row],[Tipo]]<>"Investimento",OR(tbLancamentos[[#This Row],[Situação]]="",tbLancamentos[[#This Row],[Situação]]="Pago",tbLancamentos[[#This Row],[Situação]]="Recebido",tbLancamentos[[#This Row],[Situação]]="Descontar Depois")),"sim","não"))
B72: 46277 | C72: Streaming + academia | D72: 174.8 | E72: Despesa | F72: Assinaturas | G72: Pago | H72: Essenciais | J72: Cartão Nubank | K72: Cartão de crédito | O72: Streaming | Q72: EXEMPLO | R72: =IF(AND(tbLancamentos[[#This Row],[Data]]="",tbLancamentos[[#This Row],[Competência]]=""),"",MONTH(IF(tbLancamentos[[#This Row],[Competência]]<>"",tbLancamentos[[#This Row],[Competência]],tbLancamentos[[#This Row],[Data]]))) | S72: =IF(AND(tbLancamentos[[#This Row],[Data]]="",tbLancamentos[[#This Row],[Competência]]=""),"",YEAR(IF(tbLancamentos[[#This Row],[Competência]]<>"",tbLancamentos[[#This Row],[Competência]],tbLancamentos[[#This Row],[Data]]))) | T72: =IF(tbLancamentos[[#This Row],[Valor]]="","",IF(AND(tbLancamentos[[#This Row],[Tipo]]<>"Investimento",OR(tbLancamentos[[#This Row],[Situação]]="",tbLancamentos[[#This Row],[Situação]]="Pago",tbLancamentos[[#This Row],[Situação]]="Recebido",tbLancamentos[[#This Row],[Situação]]="Descontar Depois")),"sim","não"))
B73: 46278 | C73: Aniversário — restaurante | D73: 412 | E73: Despesa | F73: Restaurantes e delivery | G73: Pago | H73: Lazer | J73: Cartão Itaú | K73: Cartão de crédito | O73: Restaurante | Q73: EXEMPLO | R73: =IF(AND(tbLancamentos[[#This Row],[Data]]="",tbLancamentos[[#This Row],[Competência]]=""),"",MONTH(IF(tbLancamentos[[#This Row],[Competência]]<>"",tbLancamentos[[#This Row],[Competência]],tbLancamentos[[#This Row],[Data]]))) | S73: =IF(AND(tbLancamentos[[#This Row],[Data]]="",tbLancamentos[[#This Row],[Competência]]=""),"",YEAR(IF(tbLancamentos[[#This Row],[Competência]]<>"",tbLancamentos[[#This Row],[Competência]],tbLancamentos[[#This Row],[Data]]))) | T73: =IF(tbLancamentos[[#This Row],[Valor]]="","",IF(AND(tbLancamentos[[#This Row],[Tipo]]<>"Investimento",OR(tbLancamentos[[#This Row],[Situação]]="",tbLancamentos[[#This Row],[Situação]]="Pago",tbLancamentos[[#This Row],[Situação]]="Recebido",tbLancamentos[[#This Row],[Situação]]="Descontar Depois")),"sim","não"))
B74: 46280 | C74: Combustível | D74: 362.8 | E74: Despesa | F74: Transporte | G74: Pago | H74: Essenciais | J74: Cartão Itaú | K74: Cartão de crédito | O74: Combustível | Q74: EXEMPLO | R74: =IF(AND(tbLancamentos[[#This Row],[Data]]="",tbLancamentos[[#This Row],[Competência]]=""),"",MONTH(IF(tbLancamentos[[#This Row],[Competência]]<>"",tbLancamentos[[#This Row],[Competência]],tbLancamentos[[#This Row],[Data]]))) | S74: =IF(AND(tbLancamentos[[#This Row],[Data]]="",tbLancamentos[[#This Row],[Competência]]=""),"",YEAR(IF(tbLancamentos[[#This Row],[Competência]]<>"",tbLancamentos[[#This Row],[Competência]],tbLancamentos[[#This Row],[Data]]))) | T74: =IF(tbLancamentos[[#This Row],[Valor]]="","",IF(AND(tbLancamentos[[#This Row],[Tipo]]<>"Investimento",OR(tbLancamentos[[#This Row],[Situação]]="",tbLancamentos[[#This Row],[Situação]]="Pago",tbLancamentos[[#This Row],[Situação]]="Recebido",tbLancamentos[[#This Row],[Situação]]="Descontar Depois")),"sim","não"))
B75: 46285 | C75: Show no fim de semana | D75: 540 | E75: Despesa | F75: Lazer | G75: Pago | H75: Lazer | J75: Cartão Nubank | K75: Cartão de crédito | O75: Hobbies | Q75: EXEMPLO | R75: =IF(AND(tbLancamentos[[#This Row],[Data]]="",tbLancamentos[[#This Row],[Competência]]=""),"",MONTH(IF(tbLancamentos[[#This Row],[Competência]]<>"",tbLancamentos[[#This Row],[Competência]],tbLancamentos[[#This Row],[Data]]))) | S75: =IF(AND(tbLancamentos[[#This Row],[Data]]="",tbLancamentos[[#This Row],[Competência]]=""),"",YEAR(IF(tbLancamentos[[#This Row],[Competência]]<>"",tbLancamentos[[#This Row],[Competência]],tbLancamentos[[#This Row],[Data]]))) | T75: =IF(tbLancamentos[[#This Row],[Valor]]="","",IF(AND(tbLancamentos[[#This Row],[Tipo]]<>"Investimento",OR(tbLancamentos[[#This Row],[Situação]]="",tbLancamentos[[#This Row],[Situação]]="Pago",tbLancamentos[[#This Row],[Situação]]="Recebido",tbLancamentos[[#This Row],[Situação]]="Descontar Depois")),"sim","não"))
B76: 46292 | C76: Cinema / passeio | D76: 188 | E76: Despesa | F76: Lazer | G76: Pago | H76: Lazer | J76: Conta Nubank | K76: PIX | O76: Cinema | Q76: EXEMPLO | R76: =IF(AND(tbLancamentos[[#This Row],[Data]]="",tbLancamentos[[#This Row],[Competência]]=""),"",MONTH(IF(tbLancamentos[[#This Row],[Competência]]<>"",tbLancamentos[[#This Row],[Competência]],tbLancamentos[[#This Row],[Data]]))) | S76: =IF(AND(tbLancamentos[[#This Row],[Data]]="",tbLancamentos[[#This Row],[Competência]]=""),"",YEAR(IF(tbLancamentos[[#This Row],[Competência]]<>"",tbLancamentos[[#This Row],[Competência]],tbLancamentos[[#This Row],[Data]]))) | T76: =IF(tbLancamentos[[#This Row],[Valor]]="","",IF(AND(tbLancamentos[[#This Row],[Tipo]]<>"Investimento",OR(tbLancamentos[[#This Row],[Situação]]="",tbLancamentos[[#This Row],[Situação]]="Pago",tbLancamentos[[#This Row],[Situação]]="Recebido",tbLancamentos[[#This Row],[Situação]]="Descontar Depois")),"sim","não"))

Sheet ContasMes
B2: Contas do mês | E2: ="Mês: "&MesSelecionado&" / "&AnoSelecionado | I2: =HYPERLINK("#Inicio!A1","⌂ Início")
B3: Checklist das contas e receitas recorrentes (marcadas em Favoritos). O status vem dos lançamentos do mês escolhido no Dashboard.
M4: BLOCO PRONTO PARA COLAR — só as contas que faltam lançar
B5: CONTAS LANÇADAS | E5: PREVISTO | F5: JÁ LANÇADO | G5: FALTA LANÇAR (PREVISTO) | M5: 1. Selecione as linhas preenchidas do bloco abaixo e copie (Ctrl+C). | S5: =HYPERLINK("#Lancamentos!B"&(ROWS(tbLancamentos[Data])+5),"✚ Ir para a primeira linha vazia")
B6: =SUMPRODUCT(--(I10:I34>0))&" de "&SUMPRODUCT(--(LEN(B10:B34)>0)) | E6: =SUM(E10:E34) | F6: =SUM(F10:F34) | G6: =SUMPRODUCT((LEFT(G10:G34,1)="✖")*N(+E10:E34)) | M6: 2. Clique no botão ao lado para ir à primeira linha vazia de Lançamentos.
M7: 3. Cole só os valores: Ctrl+Shift+V (ou Ctrl+Alt+V ➜ Valores).
M8: 4. Elas entram como Pendente: troque para Pago quando pagar.
B9: Conta / receita | C9: Categoria | D9: Dia | E9: Previsto | F9: Lançado no mês | G9: Status | H9: Linha | I9: Lançamentos | J9: Pendentes | K9: Falta nº | M9: Data | N9: Descrição | O9: Valor | P9: Tipo | Q9: Categoria | R9: Situação | S9: Pote | T9: Quem | U9: Conta | V9: Forma de pagamento | W9: Parcela
B10: =IF($H10=0,"",INDEX(Atalhos!$B:$B,$H10)&"") | C10: =IF($H10=0,"",INDEX(Atalhos!$D:$D,$H10)&"") | D10: =IF($H10=0,"",IF(INDEX(Atalhos!$K:$K,$H10)="","",INDEX(Atalhos!$K:$K,$H10))) | E10: =IF(B10="","",IF(N(INDEX(Atalhos!$I:$I,$H10))>0,INDEX(Atalhos!$I:$I,$H10),SUMIFS(tbLancamentos[Valor],tbLancamentos[Descrição],B10,tbLancamentos[Mês],Calc!$B$6,tbLancamentos[Ano],Calc!$B$7))) | F10: =IF(B10="","",SUMIFS(tbLancamentos[Valor],tbLancamentos[Descrição],B10,tbLancamentos[Mês],MesNum,tbLancamentos[Ano],AnoSelecionado)) | G10: =IF(B10="","",IF(I10=0,IF(AND(D10<>"",DATE(AnoSelecionado,MesNum,MIN(IF(D10="",1,D10),DAY(EOMONTH(DATE(AnoSelecionado,MesNum,1),0))))<TODAY()),"✖ Atrasada — falta lançar","✖ Falta lançar"),IF(J10>0,IF(DATE(AnoSelecionado,MesNum,MIN(IF(D10="",1,D10),DAY(EOMONTH(DATE(AnoSelecionado,MesNum,1),0))))<TODAY(),"⏳ Pendente — vencida","⏳ Pendente"),IF(INDEX(Atalhos!$C:$C,$H10)="Receita","✔ Recebido","✔ Pago")))) | H10: =Calc!AR2 | I10: =IF(B10="",0,COUNTIFS(tbLancamentos[Descrição],B10,tbLancamentos[Mês],MesNum,tbLancamentos[Ano],AnoSelecionado)) | J10: =IF(B10="",0,COUNTIFS(tbLancamentos[Descrição],B10,tbLancamentos[Mês],MesNum,tbLancamentos[Ano],AnoSelecionado,tbLancamentos[Situação],"Pendente")) | K10: =IF(LEFT(G10,1)="✖",SUMPRODUCT(--(LEFT($G$10:G10,1)="✖")),0) | M10: =IFERROR(DATE(AnoSelecionado,MesNum,MIN(IF(INDEX($D$10:$D$34,MATCH(1,$K$10:$K$34,0))="",1,INDEX($D$10:$D$34,MATCH(1,$K$10:$K$34,0))),DAY(EOMONTH(DATE(AnoSelecionado,MesNum,1),0)))),"") | N10: =IFERROR(INDEX($B$10:$B$34,MATCH(1,$K$10:$K$34,0)),"") | O10: =IFERROR(IF(N(INDEX($E$10:$E$34,MATCH(1,$K$10:$K$34,0)))>0,INDEX($E$10:$E$34,MATCH(1,$K$10:$K$34,0)),""),"") | P10: =IFERROR(INDEX(Atalhos!$C:$C,INDEX($H$10:$H$34,MATCH(1,$K$10:$K$34,0)))&"","") | Q10: =IFERROR(INDEX(Atalhos!$D:$D,INDEX($H$10:$H$34,MATCH(1,$K$10:$K$34,0)))&"","") | R10: =IFERROR(IF(MATCH(1,$K$10:$K$34,0)>0,"Pendente",""),"") | S10: =IFERROR(INDEX(Atalhos!$E:$E,INDEX($H$10:$H$34,MATCH(1,$K$10:$K$34,0)))&"","") | T10: =IFERROR(INDEX(Atalhos!$F:$F,INDEX($H$10:$H$34,MATCH(1,$K$10:$K$34,0)))&"","") | U10: =IFERROR(INDEX(Atalhos!$G:$G,INDEX($H$10:$H$34,MATCH(1,$K$10:$K$34,0)))&"","") | V10: =IFERROR(INDEX(Atalhos!$H:$H,INDEX($H$10:$H$34,MATCH(1,$K$10:$K$34,0)))&"","") | W10: =""
B11: =IF($H11=0,"",INDEX(Atalhos!$B:$B,$H11)&"") | C11: =IF($H11=0,"",INDEX(Atalhos!$D:$D,$H11)&"") | D11: =IF($H11=0,"",IF(INDEX(Atalhos!$K:$K,$H11)="","",INDEX(Atalhos!$K:$K,$H11))) | E11: =IF(B11="","",IF(N(INDEX(Atalhos!$I:$I,$H11))>0,INDEX(Atalhos!$I:$I,$H11),SUMIFS(tbLancamentos[Valor],tbLancamentos[Descrição],B11,tbLancamentos[Mês],Calc!$B$6,tbLancamentos[Ano],Calc!$B$7))) | F11: =IF(B11="","",SUMIFS(tbLancamentos[Valor],tbLancamentos[Descrição],B11,tbLancamentos[Mês],MesNum,tbLancamentos[Ano],AnoSelecionado)) | G11: =IF(B11="","",IF(I11=0,IF(AND(D11<>"",DATE(AnoSelecionado,MesNum,MIN(IF(D11="",1,D11),DAY(EOMONTH(DATE(AnoSelecionado,MesNum,1),0))))<TODAY()),"✖ Atrasada — falta lançar","✖ Falta lançar"),IF(J11>0,IF(DATE(AnoSelecionado,MesNum,MIN(IF(D11="",1,D11),DAY(EOMONTH(DATE(AnoSelecionado,MesNum,1),0))))<TODAY(),"⏳ Pendente — vencida","⏳ Pendente"),IF(INDEX(Atalhos!$C:$C,$H11)="Receita","✔ Recebido","✔ Pago")))) | H11: =Calc!AR3 | I11: =IF(B11="",0,COUNTIFS(tbLancamentos[Descrição],B11,tbLancamentos[Mês],MesNum,tbLancamentos[Ano],AnoSelecionado)) | J11: =IF(B11="",0,COUNTIFS(tbLancamentos[Descrição],B11,tbLancamentos[Mês],MesNum,tbLancamentos[Ano],AnoSelecionado,tbLancamentos[Situação],"Pendente")) | K11: =IF(LEFT(G11,1)="✖",SUMPRODUCT(--(LEFT($G$10:G11,1)="✖")),0) | M11: =IFERROR(DATE(AnoSelecionado,MesNum,MIN(IF(INDEX($D$10:$D$34,MATCH(2,$K$10:$K$34,0))="",1,INDEX($D$10:$D$34,MATCH(2,$K$10:$K$34,0))),DAY(EOMONTH(DATE(AnoSelecionado,MesNum,1),0)))),"") | N11: =IFERROR(INDEX($B$10:$B$34,MATCH(2,$K$10:$K$34,0)),"") | O11: =IFERROR(IF(N(INDEX($E$10:$E$34,MATCH(2,$K$10:$K$34,0)))>0,INDEX($E$10:$E$34,MATCH(2,$K$10:$K$34,0)),""),"") | P11: =IFERROR(INDEX(Atalhos!$C:$C,INDEX($H$10:$H$34,MATCH(2,$K$10:$K$34,0)))&"","") | Q11: =IFERROR(INDEX(Atalhos!$D:$D,INDEX($H$10:$H$34,MATCH(2,$K$10:$K$34,0)))&"","") | R11: =IFERROR(IF(MATCH(2,$K$10:$K$34,0)>0,"Pendente",""),"") | S11: =IFERROR(INDEX(Atalhos!$E:$E,INDEX($H$10:$H$34,MATCH(2,$K$10:$K$34,0)))&"","") | T11: =IFERROR(INDEX(Atalhos!$F:$F,INDEX($H$10:$H$34,MATCH(2,$K$10:$K$34,0)))&"","") | U11: =IFERROR(INDEX(Atalhos!$G:$G,INDEX($H$10:$H$34,MATCH(2,$K$10:$K$34,0)))&"","") | V11: =IFERROR(INDEX(Atalhos!$H:$H,INDEX($H$10:$H$34,MATCH(2,$K$10:$K$34,0)))&"","") | W11: =""
B12: =IF($H12=0,"",INDEX(Atalhos!$B:$B,$H12)&"") | C12: =IF($H12=0,"",INDEX(Atalhos!$D:$D,$H12)&"") | D12: =IF($H12=0,"",IF(INDEX(Atalhos!$K:$K,$H12)="","",INDEX(Atalhos!$K:$K,$H12))) | E12: =IF(B12="","",IF(N(INDEX(Atalhos!$I:$I,$H12))>0,INDEX(Atalhos!$I:$I,$H12),SUMIFS(tbLancamentos[Valor],tbLancamentos[Descrição],B12,tbLancamentos[Mês],Calc!$B$6,tbLancamentos[Ano],Calc!$B$7))) | F12: =IF(B12="","",SUMIFS(tbLancamentos[Valor],tbLancamentos[Descrição],B12,tbLancamentos[Mês],MesNum,tbLancamentos[Ano],AnoSelecionado)) | G12: =IF(B12="","",IF(I12=0,IF(AND(D12<>"",DATE(AnoSelecionado,MesNum,MIN(IF(D12="",1,D12),DAY(EOMONTH(DATE(AnoSelecionado,MesNum,1),0))))<TODAY()),"✖ Atrasada — falta lançar","✖ Falta lançar"),IF(J12>0,IF(DATE(AnoSelecionado,MesNum,MIN(IF(D12="",1,D12),DAY(EOMONTH(DATE(AnoSelecionado,MesNum,1),0))))<TODAY(),"⏳ Pendente — vencida","⏳ Pendente"),IF(INDEX(Atalhos!$C:$C,$H12)="Receita","✔ Recebido","✔ Pago")))) | H12: =Calc!AR4 | I12: =IF(B12="",0,COUNTIFS(tbLancamentos[Descrição],B12,tbLancamentos[Mês],MesNum,tbLancamentos[Ano],AnoSelecionado)) | J12: =IF(B12="",0,COUNTIFS(tbLancamentos[Descrição],B12,tbLancamentos[Mês],MesNum,tbLancamentos[Ano],AnoSelecionado,tbLancamentos[Situação],"Pendente")) | K12: =IF(LEFT(G12,1)="✖",SUMPRODUCT(--(LEFT($G$10:G12,1)="✖")),0) | M12: =IFERROR(DATE(AnoSelecionado,MesNum,MIN(IF(INDEX($D$10:$D$34,MATCH(3,$K$10:$K$34,0))="",1,INDEX($D$10:$D$34,MATCH(3,$K$10:$K$34,0))),DAY(EOMONTH(DATE(AnoSelecionado,MesNum,1),0)))),"") | N12: =IFERROR(INDEX($B$10:$B$34,MATCH(3,$K$10:$K$34,0)),"") | O12: =IFERROR(IF(N(INDEX($E$10:$E$34,MATCH(3,$K$10:$K$34,0)))>0,INDEX($E$10:$E$34,MATCH(3,$K$10:$K$34,0)),""),"") | P12: =IFERROR(INDEX(Atalhos!$C:$C,INDEX($H$10:$H$34,MATCH(3,$K$10:$K$34,0)))&"","") | Q12: =IFERROR(INDEX(Atalhos!$D:$D,INDEX($H$10:$H$34,MATCH(3,$K$10:$K$34,0)))&"","") | R12: =IFERROR(IF(MATCH(3,$K$10:$K$34,0)>0,"Pendente",""),"") | S12: =IFERROR(INDEX(Atalhos!$E:$E,INDEX($H$10:$H$34,MATCH(3,$K$10:$K$34,0)))&"","") | T12: =IFERROR(INDEX(Atalhos!$F:$F,INDEX($H$10:$H$34,MATCH(3,$K$10:$K$34,0)))&"","") | U12: =IFERROR(INDEX(Atalhos!$G:$G,INDEX($H$10:$H$34,MATCH(3,$K$10:$K$34,0)))&"","") | V12: =IFERROR(INDEX(Atalhos!$H:$H,INDEX($H$10:$H$34,MATCH(3,$K$10:$K$34,0)))&"","") | W12: =""
B13: =IF($H13=0,"",INDEX(Atalhos!$B:$B,$H13)&"") | C13: =IF($H13=0,"",INDEX(Atalhos!$D:$D,$H13)&"") | D13: =IF($H13=0,"",IF(INDEX(Atalhos!$K:$K,$H13)="","",INDEX(Atalhos!$K:$K,$H13))) | E13: =IF(B13="","",IF(N(INDEX(Atalhos!$I:$I,$H13))>0,INDEX(Atalhos!$I:$I,$H13),SUMIFS(tbLancamentos[Valor],tbLancamentos[Descrição],B13,tbLancamentos[Mês],Calc!$B$6,tbLancamentos[Ano],Calc!$B$7))) | F13: =IF(B13="","",SUMIFS(tbLancamentos[Valor],tbLancamentos[Descrição],B13,tbLancamentos[Mês],MesNum,tbLancamentos[Ano],AnoSelecionado)) | G13: =IF(B13="","",IF(I13=0,IF(AND(D13<>"",DATE(AnoSelecionado,MesNum,MIN(IF(D13="",1,D13),DAY(EOMONTH(DATE(AnoSelecionado,MesNum,1),0))))<TODAY()),"✖ Atrasada — falta lançar","✖ Falta lançar"),IF(J13>0,IF(DATE(AnoSelecionado,MesNum,MIN(IF(D13="",1,D13),DAY(EOMONTH(DATE(AnoSelecionado,MesNum,1),0))))<TODAY(),"⏳ Pendente — vencida","⏳ Pendente"),IF(INDEX(Atalhos!$C:$C,$H13)="Receita","✔ Recebido","✔ Pago")))) | H13: =Calc!AR5 | I13: =IF(B13="",0,COUNTIFS(tbLancamentos[Descrição],B13,tbLancamentos[Mês],MesNum,tbLancamentos[Ano],AnoSelecionado)) | J13: =IF(B13="",0,COUNTIFS(tbLancamentos[Descrição],B13,tbLancamentos[Mês],MesNum,tbLancamentos[Ano],AnoSelecionado,tbLancamentos[Situação],"Pendente")) | K13: =IF(LEFT(G13,1)="✖",SUMPRODUCT(--(LEFT($G$10:G13,1)="✖")),0) | M13: =IFERROR(DATE(AnoSelecionado,MesNum,MIN(IF(INDEX($D$10:$D$34,MATCH(4,$K$10:$K$34,0))="",1,INDEX($D$10:$D$34,MATCH(4,$K$10:$K$34,0))),DAY(EOMONTH(DATE(AnoSelecionado,MesNum,1),0)))),"") | N13: =IFERROR(INDEX($B$10:$B$34,MATCH(4,$K$10:$K$34,0)),"") | O13: =IFERROR(IF(N(INDEX($E$10:$E$34,MATCH(4,$K$10:$K$34,0)))>0,INDEX($E$10:$E$34,MATCH(4,$K$10:$K$34,0)),""),"") | P13: =IFERROR(INDEX(Atalhos!$C:$C,INDEX($H$10:$H$34,MATCH(4,$K$10:$K$34,0)))&"","") | Q13: =IFERROR(INDEX(Atalhos!$D:$D,INDEX($H$10:$H$34,MATCH(4,$K$10:$K$34,0)))&"","") | R13: =IFERROR(IF(MATCH(4,$K$10:$K$34,0)>0,"Pendente",""),"") | S13: =IFERROR(INDEX(Atalhos!$E:$E,INDEX($H$10:$H$34,MATCH(4,$K$10:$K$34,0)))&"","") | T13: =IFERROR(INDEX(Atalhos!$F:$F,INDEX($H$10:$H$34,MATCH(4,$K$10:$K$34,0)))&"","") | U13: =IFERROR(INDEX(Atalhos!$G:$G,INDEX($H$10:$H$34,MATCH(4,$K$10:$K$34,0)))&"","") | V13: =IFERROR(INDEX(Atalhos!$H:$H,INDEX($H$10:$H$34,MATCH(4,$K$10:$K$34,0)))&"","") | W13: =""
B14: =IF($H14=0,"",INDEX(Atalhos!$B:$B,$H14)&"") | C14: =IF($H14=0,"",INDEX(Atalhos!$D:$D,$H14)&"") | D14: =IF($H14=0,"",IF(INDEX(Atalhos!$K:$K,$H14)="","",INDEX(Atalhos!$K:$K,$H14))) | E14: =IF(B14="","",IF(N(INDEX(Atalhos!$I:$I,$H14))>0,INDEX(Atalhos!$I:$I,$H14),SUMIFS(tbLancamentos[Valor],tbLancamentos[Descrição],B14,tbLancamentos[Mês],Calc!$B$6,tbLancamentos[Ano],Calc!$B$7))) | F14: =IF(B14="","",SUMIFS(tbLancamentos[Valor],tbLancamentos[Descrição],B14,tbLancamentos[Mês],MesNum,tbLancamentos[Ano],AnoSelecionado)) | G14: =IF(B14="","",IF(I14=0,IF(AND(D14<>"",DATE(AnoSelecionado,MesNum,MIN(IF(D14="",1,D14),DAY(EOMONTH(DATE(AnoSelecionado,MesNum,1),0))))<TODAY()),"✖ Atrasada — falta lançar","✖ Falta lançar"),IF(J14>0,IF(DATE(AnoSelecionado,MesNum,MIN(IF(D14="",1,D14),DAY(EOMONTH(DATE(AnoSelecionado,MesNum,1),0))))<TODAY(),"⏳ Pendente — vencida","⏳ Pendente"),IF(INDEX(Atalhos!$C:$C,$H14)="Receita","✔ Recebido","✔ Pago")))) | H14: =Calc!AR6 | I14: =IF(B14="",0,COUNTIFS(tbLancamentos[Descrição],B14,tbLancamentos[Mês],MesNum,tbLancamentos[Ano],AnoSelecionado)) | J14: =IF(B14="",0,COUNTIFS(tbLancamentos[Descrição],B14,tbLancamentos[Mês],MesNum,tbLancamentos[Ano],AnoSelecionado,tbLancamentos[Situação],"Pendente")) | K14: =IF(LEFT(G14,1)="✖",SUMPRODUCT(--(LEFT($G$10:G14,1)="✖")),0) | M14: =IFERROR(DATE(AnoSelecionado,MesNum,MIN(IF(INDEX($D$10:$D$34,MATCH(5,$K$10:$K$34,0))="",1,INDEX($D$10:$D$34,MATCH(5,$K$10:$K$34,0))),DAY(EOMONTH(DATE(AnoSelecionado,MesNum,1),0)))),"") | N14: =IFERROR(INDEX($B$10:$B$34,MATCH(5,$K$10:$K$34,0)),"") | O14: =IFERROR(IF(N(INDEX($E$10:$E$34,MATCH(5,$K$10:$K$34,0)))>0,INDEX($E$10:$E$34,MATCH(5,$K$10:$K$34,0)),""),"") | P14: =IFERROR(INDEX(Atalhos!$C:$C,INDEX($H$10:$H$34,MATCH(5,$K$10:$K$34,0)))&"","") | Q14: =IFERROR(INDEX(Atalhos!$D:$D,INDEX($H$10:$H$34,MATCH(5,$K$10:$K$34,0)))&"","") | R14: =IFERROR(IF(MATCH(5,$K$10:$K$34,0)>0,"Pendente",""),"") | S14: =IFERROR(INDEX(Atalhos!$E:$E,INDEX($H$10:$H$34,MATCH(5,$K$10:$K$34,0)))&"","") | T14: =IFERROR(INDEX(Atalhos!$F:$F,INDEX($H$10:$H$34,MATCH(5,$K$10:$K$34,0)))&"","") | U14: =IFERROR(INDEX(Atalhos!$G:$G,INDEX($H$10:$H$34,MATCH(5,$K$10:$K$34,0)))&"","") | V14: =IFERROR(INDEX(Atalhos!$H:$H,INDEX($H$10:$H$34,MATCH(5,$K$10:$K$34,0)))&"","") | W14: =""
B15: =IF($H15=0,"",INDEX(Atalhos!$B:$B,$H15)&"") | C15: =IF($H15=0,"",INDEX(Atalhos!$D:$D,$H15)&"") | D15: =IF($H15=0,"",IF(INDEX(Atalhos!$K:$K,$H15)="","",INDEX(Atalhos!$K:$K,$H15))) | E15: =IF(B15="","",IF(N(INDEX(Atalhos!$I:$I,$H15))>0,INDEX(Atalhos!$I:$I,$H15),SUMIFS(tbLancamentos[Valor],tbLancamentos[Descrição],B15,tbLancamentos[Mês],Calc!$B$6,tbLancamentos[Ano],Calc!$B$7))) | F15: =IF(B15="","",SUMIFS(tbLancamentos[Valor],tbLancamentos[Descrição],B15,tbLancamentos[Mês],MesNum,tbLancamentos[Ano],AnoSelecionado)) | G15: =IF(B15="","",IF(I15=0,IF(AND(D15<>"",DATE(AnoSelecionado,MesNum,MIN(IF(D15="",1,D15),DAY(EOMONTH(DATE(AnoSelecionado,MesNum,1),0))))<TODAY()),"✖ Atrasada — falta lançar","✖ Falta lançar"),IF(J15>0,IF(DATE(AnoSelecionado,MesNum,MIN(IF(D15="",1,D15),DAY(EOMONTH(DATE(AnoSelecionado,MesNum,1),0))))<TODAY(),"⏳ Pendente — vencida","⏳ Pendente"),IF(INDEX(Atalhos!$C:$C,$H15)="Receita","✔ Recebido","✔ Pago")))) | H15: =Calc!AR7 | I15: =IF(B15="",0,COUNTIFS(tbLancamentos[Descrição],B15,tbLancamentos[Mês],MesNum,tbLancamentos[Ano],AnoSelecionado)) | J15: =IF(B15="",0,COUNTIFS(tbLancamentos[Descrição],B15,tbLancamentos[Mês],MesNum,tbLancamentos[Ano],AnoSelecionado,tbLancamentos[Situação],"Pendente")) | K15: =IF(LEFT(G15,1)="✖",SUMPRODUCT(--(LEFT($G$10:G15,1)="✖")),0) | M15: =IFERROR(DATE(AnoSelecionado,MesNum,MIN(IF(INDEX($D$10:$D$34,MATCH(6,$K$10:$K$34,0))="",1,INDEX($D$10:$D$34,MATCH(6,$K$10:$K$34,0))),DAY(EOMONTH(DATE(AnoSelecionado,MesNum,1),0)))),"") | N15: =IFERROR(INDEX($B$10:$B$34,MATCH(6,$K$10:$K$34,0)),"") | O15: =IFERROR(IF(N(INDEX($E$10:$E$34,MATCH(6,$K$10:$K$34,0)))>0,INDEX($E$10:$E$34,MATCH(6,$K$10:$K$34,0)),""),"") | P15: =IFERROR(INDEX(Atalhos!$C:$C,INDEX($H$10:$H$34,MATCH(6,$K$10:$K$34,0)))&"","") | Q15: =IFERROR(INDEX(Atalhos!$D:$D,INDEX($H$10:$H$34,MATCH(6,$K$10:$K$34,0)))&"","") | R15: =IFERROR(IF(MATCH(6,$K$10:$K$34,0)>0,"Pendente",""),"") | S15: =IFERROR(INDEX(Atalhos!$E:$E,INDEX($H$10:$H$34,MATCH(6,$K$10:$K$34,0)))&"","") | T15: =IFERROR(INDEX(Atalhos!$F:$F,INDEX($H$10:$H$34,MATCH(6,$K$10:$K$34,0)))&"","") | U15: =IFERROR(INDEX(Atalhos!$G:$G,INDEX($H$10:$H$34,MATCH(6,$K$10:$K$34,0)))&"","") | V15: =IFERROR(INDEX(Atalhos!$H:$H,INDEX($H$10:$H$34,MATCH(6,$K$10:$K$34,0)))&"","") | W15: =""
B16: =IF($H16=0,"",INDEX(Atalhos!$B:$B,$H16)&"") | C16: =IF($H16=0,"",INDEX(Atalhos!$D:$D,$H16)&"") | D16: =IF($H16=0,"",IF(INDEX(Atalhos!$K:$K,$H16)="","",INDEX(Atalhos!$K:$K,$H16))) | E16: =IF(B16="","",IF(N(INDEX(Atalhos!$I:$I,$H16))>0,INDEX(Atalhos!$I:$I,$H16),SUMIFS(tbLancamentos[Valor],tbLancamentos[Descrição],B16,tbLancamentos[Mês],Calc!$B$6,tbLancamentos[Ano],Calc!$B$7))) | F16: =IF(B16="","",SUMIFS(tbLancamentos[Valor],tbLancamentos[Descrição],B16,tbLancamentos[Mês],MesNum,tbLancamentos[Ano],AnoSelecionado)) | G16: =IF(B16="","",IF(I16=0,IF(AND(D16<>"",DATE(AnoSelecionado,MesNum,MIN(IF(D16="",1,D16),DAY(EOMONTH(DATE(AnoSelecionado,MesNum,1),0))))<TODAY()),"✖ Atrasada — falta lançar","✖ Falta lançar"),IF(J16>0,IF(DATE(AnoSelecionado,MesNum,MIN(IF(D16="",1,D16),DAY(EOMONTH(DATE(AnoSelecionado,MesNum,1),0))))<TODAY(),"⏳ Pendente — vencida","⏳ Pendente"),IF(INDEX(Atalhos!$C:$C,$H16)="Receita","✔ Recebido","✔ Pago")))) | H16: =Calc!AR8 | I16: =IF(B16="",0,COUNTIFS(tbLancamentos[Descrição],B16,tbLancamentos[Mês],MesNum,tbLancamentos[Ano],AnoSelecionado)) | J16: =IF(B16="",0,COUNTIFS(tbLancamentos[Descrição],B16,tbLancamentos[Mês],MesNum,tbLancamentos[Ano],AnoSelecionado,tbLancamentos[Situação],"Pendente")) | K16: =IF(LEFT(G16,1)="✖",SUMPRODUCT(--(LEFT($G$10:G16,1)="✖")),0) | M16: =IFERROR(DATE(AnoSelecionado,MesNum,MIN(IF(INDEX($D$10:$D$34,MATCH(7,$K$10:$K$34,0))="",1,INDEX($D$10:$D$34,MATCH(7,$K$10:$K$34,0))),DAY(EOMONTH(DATE(AnoSelecionado,MesNum,1),0)))),"") | N16: =IFERROR(INDEX($B$10:$B$34,MATCH(7,$K$10:$K$34,0)),"") | O16: =IFERROR(IF(N(INDEX($E$10:$E$34,MATCH(7,$K$10:$K$34,0)))>0,INDEX($E$10:$E$34,MATCH(7,$K$10:$K$34,0)),""),"") | P16: =IFERROR(INDEX(Atalhos!$C:$C,INDEX($H$10:$H$34,MATCH(7,$K$10:$K$34,0)))&"","") | Q16: =IFERROR(INDEX(Atalhos!$D:$D,INDEX($H$10:$H$34,MATCH(7,$K$10:$K$34,0)))&"","") | R16: =IFERROR(IF(MATCH(7,$K$10:$K$34,0)>0,"Pendente",""),"") | S16: =IFERROR(INDEX(Atalhos!$E:$E,INDEX($H$10:$H$34,MATCH(7,$K$10:$K$34,0)))&"","") | T16: =IFERROR(INDEX(Atalhos!$F:$F,INDEX($H$10:$H$34,MATCH(7,$K$10:$K$34,0)))&"","") | U16: =IFERROR(INDEX(Atalhos!$G:$G,INDEX($H$10:$H$34,MATCH(7,$K$10:$K$34,0)))&"","") | V16: =IFERROR(INDEX(Atalhos!$H:$H,INDEX($H$10:$H$34,MATCH(7,$K$10:$K$34,0)))&"","") | W16: =""
B17: =IF($H17=0,"",INDEX(Atalhos!$B:$B,$H17)&"") | C17: =IF($H17=0,"",INDEX(Atalhos!$D:$D,$H17)&"") | D17: =IF($H17=0,"",IF(INDEX(Atalhos!$K:$K,$H17)="","",INDEX(Atalhos!$K:$K,$H17))) | E17: =IF(B17="","",IF(N(INDEX(Atalhos!$I:$I,$H17))>0,INDEX(Atalhos!$I:$I,$H17),SUMIFS(tbLancamentos[Valor],tbLancamentos[Descrição],B17,tbLancamentos[Mês],Calc!$B$6,tbLancamentos[Ano],Calc!$B$7))) | F17: =IF(B17="","",SUMIFS(tbLancamentos[Valor],tbLancamentos[Descrição],B17,tbLancamentos[Mês],MesNum,tbLancamentos[Ano],AnoSelecionado)) | G17: =IF(B17="","",IF(I17=0,IF(AND(D17<>"",DATE(AnoSelecionado,MesNum,MIN(IF(D17="",1,D17),DAY(EOMONTH(DATE(AnoSelecionado,MesNum,1),0))))<TODAY()),"✖ Atrasada — falta lançar","✖ Falta lançar"),IF(J17>0,IF(DATE(AnoSelecionado,MesNum,MIN(IF(D17="",1,D17),DAY(EOMONTH(DATE(AnoSelecionado,MesNum,1),0))))<TODAY(),"⏳ Pendente — vencida","⏳ Pendente"),IF(INDEX(Atalhos!$C:$C,$H17)="Receita","✔ Recebido","✔ Pago")))) | H17: =Calc!AR9 | I17: =IF(B17="",0,COUNTIFS(tbLancamentos[Descrição],B17,tbLancamentos[Mês],MesNum,tbLancamentos[Ano],AnoSelecionado)) | J17: =IF(B17="",0,COUNTIFS(tbLancamentos[Descrição],B17,tbLancamentos[Mês],MesNum,tbLancamentos[Ano],AnoSelecionado,tbLancamentos[Situação],"Pendente")) | K17: =IF(LEFT(G17,1)="✖",SUMPRODUCT(--(LEFT($G$10:G17,1)="✖")),0) | M17: =IFERROR(DATE(AnoSelecionado,MesNum,MIN(IF(INDEX($D$10:$D$34,MATCH(8,$K$10:$K$34,0))="",1,INDEX($D$10:$D$34,MATCH(8,$K$10:$K$34,0))),DAY(EOMONTH(DATE(AnoSelecionado,MesNum,1),0)))),"") | N17: =IFERROR(INDEX($B$10:$B$34,MATCH(8,$K$10:$K$34,0)),"") | O17: =IFERROR(IF(N(INDEX($E$10:$E$34,MATCH(8,$K$10:$K$34,0)))>0,INDEX($E$10:$E$34,MATCH(8,$K$10:$K$34,0)),""),"") | P17: =IFERROR(INDEX(Atalhos!$C:$C,INDEX($H$10:$H$34,MATCH(8,$K$10:$K$34,0)))&"","") | Q17: =IFERROR(INDEX(Atalhos!$D:$D,INDEX($H$10:$H$34,MATCH(8,$K$10:$K$34,0)))&"","") | R17: =IFERROR(IF(MATCH(8,$K$10:$K$34,0)>0,"Pendente",""),"") | S17: =IFERROR(INDEX(Atalhos!$E:$E,INDEX($H$10:$H$34,MATCH(8,$K$10:$K$34,0)))&"","") | T17: =IFERROR(INDEX(Atalhos!$F:$F,INDEX($H$10:$H$34,MATCH(8,$K$10:$K$34,0)))&"","") | U17: =IFERROR(INDEX(Atalhos!$G:$G,INDEX($H$10:$H$34,MATCH(8,$K$10:$K$34,0)))&"","") | V17: =IFERROR(INDEX(Atalhos!$H:$H,INDEX($H$10:$H$34,MATCH(8,$K$10:$K$34,0)))&"","") | W17: =""
B18: =IF($H18=0,"",INDEX(Atalhos!$B:$B,$H18)&"") | C18: =IF($H18=0,"",INDEX(Atalhos!$D:$D,$H18)&"") | D18: =IF($H18=0,"",IF(INDEX(Atalhos!$K:$K,$H18)="","",INDEX(Atalhos!$K:$K,$H18))) | E18: =IF(B18="","",IF(N(INDEX(Atalhos!$I:$I,$H18))>0,INDEX(Atalhos!$I:$I,$H18),SUMIFS(tbLancamentos[Valor],tbLancamentos[Descrição],B18,tbLancamentos[Mês],Calc!$B$6,tbLancamentos[Ano],Calc!$B$7))) | F18: =IF(B18="","",SUMIFS(tbLancamentos[Valor],tbLancamentos[Descrição],B18,tbLancamentos[Mês],MesNum,tbLancamentos[Ano],AnoSelecionado)) | G18: =IF(B18="","",IF(I18=0,IF(AND(D18<>"",DATE(AnoSelecionado,MesNum,MIN(IF(D18="",1,D18),DAY(EOMONTH(DATE(AnoSelecionado,MesNum,1),0))))<TODAY()),"✖ Atrasada — falta lançar","✖ Falta lançar"),IF(J18>0,IF(DATE(AnoSelecionado,MesNum,MIN(IF(D18="",1,D18),DAY(EOMONTH(DATE(AnoSelecionado,MesNum,1),0))))<TODAY(),"⏳ Pendente — vencida","⏳ Pendente"),IF(INDEX(Atalhos!$C:$C,$H18)="Receita","✔ Recebido","✔ Pago")))) | H18: =Calc!AR10 | I18: =IF(B18="",0,COUNTIFS(tbLancamentos[Descrição],B18,tbLancamentos[Mês],MesNum,tbLancamentos[Ano],AnoSelecionado)) | J18: =IF(B18="",0,COUNTIFS(tbLancamentos[Descrição],B18,tbLancamentos[Mês],MesNum,tbLancamentos[Ano],AnoSelecionado,tbLancamentos[Situação],"Pendente")) | K18: =IF(LEFT(G18,1)="✖",SUMPRODUCT(--(LEFT($G$10:G18,1)="✖")),0) | M18: =IFERROR(DATE(AnoSelecionado,MesNum,MIN(IF(INDEX($D$10:$D$34,MATCH(9,$K$10:$K$34,0))="",1,INDEX($D$10:$D$34,MATCH(9,$K$10:$K$34,0))),DAY(EOMONTH(DATE(AnoSelecionado,MesNum,1),0)))),"") | N18: =IFERROR(INDEX($B$10:$B$34,MATCH(9,$K$10:$K$34,0)),"") | O18: =IFERROR(IF(N(INDEX($E$10:$E$34,MATCH(9,$K$10:$K$34,0)))>0,INDEX($E$10:$E$34,MATCH(9,$K$10:$K$34,0)),""),"") | P18: =IFERROR(INDEX(Atalhos!$C:$C,INDEX($H$10:$H$34,MATCH(9,$K$10:$K$34,0)))&"","") | Q18: =IFERROR(INDEX(Atalhos!$D:$D,INDEX($H$10:$H$34,MATCH(9,$K$10:$K$34,0)))&"","") | R18: =IFERROR(IF(MATCH(9,$K$10:$K$34,0)>0,"Pendente",""),"") | S18: =IFERROR(INDEX(Atalhos!$E:$E,INDEX($H$10:$H$34,MATCH(9,$K$10:$K$34,0)))&"","") | T18: =IFERROR(INDEX(Atalhos!$F:$F,INDEX($H$10:$H$34,MATCH(9,$K$10:$K$34,0)))&"","") | U18: =IFERROR(INDEX(Atalhos!$G:$G,INDEX($H$10:$H$34,MATCH(9,$K$10:$K$34,0)))&"","") | V18: =IFERROR(INDEX(Atalhos!$H:$H,INDEX($H$10:$H$34,MATCH(9,$K$10:$K$34,0)))&"","") | W18: =""
B19: =IF($H19=0,"",INDEX(Atalhos!$B:$B,$H19)&"") | C19: =IF($H19=0,"",INDEX(Atalhos!$D:$D,$H19)&"") | D19: =IF($H19=0,"",IF(INDEX(Atalhos!$K:$K,$H19)="","",INDEX(Atalhos!$K:$K,$H19))) | E19: =IF(B19="","",IF(N(INDEX(Atalhos!$I:$I,$H19))>0,INDEX(Atalhos!$I:$I,$H19),SUMIFS(tbLancamentos[Valor],tbLancamentos[Descrição],B19,tbLancamentos[Mês],Calc!$B$6,tbLancamentos[Ano],Calc!$B$7))) | F19: =IF(B19="","",SUMIFS(tbLancamentos[Valor],tbLancamentos[Descrição],B19,tbLancamentos[Mês],MesNum,tbLancamentos[Ano],AnoSelecionado)) | G19: =IF(B19="","",IF(I19=0,IF(AND(D19<>"",DATE(AnoSelecionado,MesNum,MIN(IF(D19="",1,D19),DAY(EOMONTH(DATE(AnoSelecionado,MesNum,1),0))))<TODAY()),"✖ Atrasada — falta lançar","✖ Falta lançar"),IF(J19>0,IF(DATE(AnoSelecionado,MesNum,MIN(IF(D19="",1,D19),DAY(EOMONTH(DATE(AnoSelecionado,MesNum,1),0))))<TODAY(),"⏳ Pendente — vencida","⏳ Pendente"),IF(INDEX(Atalhos!$C:$C,$H19)="Receita","✔ Recebido","✔ Pago")))) | H19: =Calc!AR11 | I19: =IF(B19="",0,COUNTIFS(tbLancamentos[Descrição],B19,tbLancamentos[Mês],MesNum,tbLancamentos[Ano],AnoSelecionado)) | J19: =IF(B19="",0,COUNTIFS(tbLancamentos[Descrição],B19,tbLancamentos[Mês],MesNum,tbLancamentos[Ano],AnoSelecionado,tbLancamentos[Situação],"Pendente")) | K19: =IF(LEFT(G19,1)="✖",SUMPRODUCT(--(LEFT($G$10:G19,1)="✖")),0) | M19: =IFERROR(DATE(AnoSelecionado,MesNum,MIN(IF(INDEX($D$10:$D$34,MATCH(10,$K$10:$K$34,0))="",1,INDEX($D$10:$D$34,MATCH(10,$K$10:$K$34,0))),DAY(EOMONTH(DATE(AnoSelecionado,MesNum,1),0)))),"") | N19: =IFERROR(INDEX($B$10:$B$34,MATCH(10,$K$10:$K$34,0)),"") | O19: =IFERROR(IF(N(INDEX($E$10:$E$34,MATCH(10,$K$10:$K$34,0)))>0,INDEX($E$10:$E$34,MATCH(10,$K$10:$K$34,0)),""),"") | P19: =IFERROR(INDEX(Atalhos!$C:$C,INDEX($H$10:$H$34,MATCH(10,$K$10:$K$34,0)))&"","") | Q19: =IFERROR(INDEX(Atalhos!$D:$D,INDEX($H$10:$H$34,MATCH(10,$K$10:$K$34,0)))&"","") | R19: =IFERROR(IF(MATCH(10,$K$10:$K$34,0)>0,"Pendente",""),"") | S19: =IFERROR(INDEX(Atalhos!$E:$E,INDEX($H$10:$H$34,MATCH(10,$K$10:$K$34,0)))&"","") | T19: =IFERROR(INDEX(Atalhos!$F:$F,INDEX($H$10:$H$34,MATCH(10,$K$10:$K$34,0)))&"","") | U19: =IFERROR(INDEX(Atalhos!$G:$G,INDEX($H$10:$H$34,MATCH(10,$K$10:$K$34,0)))&"","") | V19: =IFERROR(INDEX(Atalhos!$H:$H,INDEX($H$10:$H$34,MATCH(10,$K$10:$K$34,0)))&"","") | W19: =""
B20: =IF($H20=0,"",INDEX(Atalhos!$B:$B,$H20)&"") | C20: =IF($H20=0,"",INDEX(Atalhos!$D:$D,$H20)&"") | D20: =IF($H20=0,"",IF(INDEX(Atalhos!$K:$K,$H20)="","",INDEX(Atalhos!$K:$K,$H20))) | E20: =IF(B20="","",IF(N(INDEX(Atalhos!$I:$I,$H20))>0,INDEX(Atalhos!$I:$I,$H20),SUMIFS(tbLancamentos[Valor],tbLancamentos[Descrição],B20,tbLancamentos[Mês],Calc!$B$6,tbLancamentos[Ano],Calc!$B$7))) | F20: =IF(B20="","",SUMIFS(tbLancamentos[Valor],tbLancamentos[Descrição],B20,tbLancamentos[Mês],MesNum,tbLancamentos[Ano],AnoSelecionado)) | G20: =IF(B20="","",IF(I20=0,IF(AND(D20<>"",DATE(AnoSelecionado,MesNum,MIN(IF(D20="",1,D20),DAY(EOMONTH(DATE(AnoSelecionado,MesNum,1),0))))<TODAY()),"✖ Atrasada — falta lançar","✖ Falta lançar"),IF(J20>0,IF(DATE(AnoSelecionado,MesNum,MIN(IF(D20="",1,D20),DAY(EOMONTH(DATE(AnoSelecionado,MesNum,1),0))))<TODAY(),"⏳ Pendente — vencida","⏳ Pendente"),IF(INDEX(Atalhos!$C:$C,$H20)="Receita","✔ Recebido","✔ Pago")))) | H20: =Calc!AR12 | I20: =IF(B20="",0,COUNTIFS(tbLancamentos[Descrição],B20,tbLancamentos[Mês],MesNum,tbLancamentos[Ano],AnoSelecionado)) | J20: =IF(B20="",0,COUNTIFS(tbLancamentos[Descrição],B20,tbLancamentos[Mês],MesNum,tbLancamentos[Ano],AnoSelecionado,tbLancamentos[Situação],"Pendente")) | K20: =IF(LEFT(G20,1)="✖",SUMPRODUCT(--(LEFT($G$10:G20,1)="✖")),0) | M20: =IFERROR(DATE(AnoSelecionado,MesNum,MIN(IF(INDEX($D$10:$D$34,MATCH(11,$K$10:$K$34,0))="",1,INDEX($D$10:$D$34,MATCH(11,$K$10:$K$34,0))),DAY(EOMONTH(DATE(AnoSelecionado,MesNum,1),0)))),"") | N20: =IFERROR(INDEX($B$10:$B$34,MATCH(11,$K$10:$K$34,0)),"") | O20: =IFERROR(IF(N(INDEX($E$10:$E$34,MATCH(11,$K$10:$K$34,0)))>0,INDEX($E$10:$E$34,MATCH(11,$K$10:$K$34,0)),""),"") | P20: =IFERROR(INDEX(Atalhos!$C:$C,INDEX($H$10:$H$34,MATCH(11,$K$10:$K$34,0)))&"","") | Q20: =IFERROR(INDEX(Atalhos!$D:$D,INDEX($H$10:$H$34,MATCH(11,$K$10:$K$34,0)))&"","") | R20: =IFERROR(IF(MATCH(11,$K$10:$K$34,0)>0,"Pendente",""),"") | S20: =IFERROR(INDEX(Atalhos!$E:$E,INDEX($H$10:$H$34,MATCH(11,$K$10:$K$34,0)))&"","") | T20: =IFERROR(INDEX(Atalhos!$F:$F,INDEX($H$10:$H$34,MATCH(11,$K$10:$K$34,0)))&"","") | U20: =IFERROR(INDEX(Atalhos!$G:$G,INDEX($H$10:$H$34,MATCH(11,$K$10:$K$34,0)))&"","") | V20: =IFERROR(INDEX(Atalhos!$H:$H,INDEX($H$10:$H$34,MATCH(11,$K$10:$K$34,0)))&"","") | W20: =""
B21: =IF($H21=0,"",INDEX(Atalhos!$B:$B,$H21)&"") | C21: =IF($H21=0,"",INDEX(Atalhos!$D:$D,$H21)&"") | D21: =IF($H21=0,"",IF(INDEX(Atalhos!$K:$K,$H21)="","",INDEX(Atalhos!$K:$K,$H21))) | E21: =IF(B21="","",IF(N(INDEX(Atalhos!$I:$I,$H21))>0,INDEX(Atalhos!$I:$I,$H21),SUMIFS(tbLancamentos[Valor],tbLancamentos[Descrição],B21,tbLancamentos[Mês],Calc!$B$6,tbLancamentos[Ano],Calc!$B$7))) | F21: =IF(B21="","",SUMIFS(tbLancamentos[Valor],tbLancamentos[Descrição],B21,tbLancamentos[Mês],MesNum,tbLancamentos[Ano],AnoSelecionado)) | G21: =IF(B21="","",IF(I21=0,IF(AND(D21<>"",DATE(AnoSelecionado,MesNum,MIN(IF(D21="",1,D21),DAY(EOMONTH(DATE(AnoSelecionado,MesNum,1),0))))<TODAY()),"✖ Atrasada — falta lançar","✖ Falta lançar"),IF(J21>0,IF(DATE(AnoSelecionado,MesNum,MIN(IF(D21="",1,D21),DAY(EOMONTH(DATE(AnoSelecionado,MesNum,1),0))))<TODAY(),"⏳ Pendente — vencida","⏳ Pendente"),IF(INDEX(Atalhos!$C:$C,$H21)="Receita","✔ Recebido","✔ Pago")))) | H21: =Calc!AR13 | I21: =IF(B21="",0,COUNTIFS(tbLancamentos[Descrição],B21,tbLancamentos[Mês],MesNum,tbLancamentos[Ano],AnoSelecionado)) | J21: =IF(B21="",0,COUNTIFS(tbLancamentos[Descrição],B21,tbLancamentos[Mês],MesNum,tbLancamentos[Ano],AnoSelecionado,tbLancamentos[Situação],"Pendente")) | K21: =IF(LEFT(G21,1)="✖",SUMPRODUCT(--(LEFT($G$10:G21,1)="✖")),0) | M21: =IFERROR(DATE(AnoSelecionado,MesNum,MIN(IF(INDEX($D$10:$D$34,MATCH(12,$K$10:$K$34,0))="",1,INDEX($D$10:$D$34,MATCH(12,$K$10:$K$34,0))),DAY(EOMONTH(DATE(AnoSelecionado,MesNum,1),0)))),"") | N21: =IFERROR(INDEX($B$10:$B$34,MATCH(12,$K$10:$K$34,0)),"") | O21: =IFERROR(IF(N(INDEX($E$10:$E$34,MATCH(12,$K$10:$K$34,0)))>0,INDEX($E$10:$E$34,MATCH(12,$K$10:$K$34,0)),""),"") | P21: =IFERROR(INDEX(Atalhos!$C:$C,INDEX($H$10:$H$34,MATCH(12,$K$10:$K$34,0)))&"","") | Q21: =IFERROR(INDEX(Atalhos!$D:$D,INDEX($H$10:$H$34,MATCH(12,$K$10:$K$34,0)))&"","") | R21: =IFERROR(IF(MATCH(12,$K$10:$K$34,0)>0,"Pendente",""),"") | S21: =IFERROR(INDEX(Atalhos!$E:$E,INDEX($H$10:$H$34,MATCH(12,$K$10:$K$34,0)))&"","") | T21: =IFERROR(INDEX(Atalhos!$F:$F,INDEX($H$10:$H$34,MATCH(12,$K$10:$K$34,0)))&"","") | U21: =IFERROR(INDEX(Atalhos!$G:$G,INDEX($H$10:$H$34,MATCH(12,$K$10:$K$34,0)))&"","") | V21: =IFERROR(INDEX(Atalhos!$H:$H,INDEX($H$10:$H$34,MATCH(12,$K$10:$K$34,0)))&"","") | W21: =""
B22: =IF($H22=0,"",INDEX(Atalhos!$B:$B,$H22)&"") | C22: =IF($H22=0,"",INDEX(Atalhos!$D:$D,$H22)&"") | D22: =IF($H22=0,"",IF(INDEX(Atalhos!$K:$K,$H22)="","",INDEX(Atalhos!$K:$K,$H22))) | E22: =IF(B22="","",IF(N(INDEX(Atalhos!$I:$I,$H22))>0,INDEX(Atalhos!$I:$I,$H22),SUMIFS(tbLancamentos[Valor],tbLancamentos[Descrição],B22,tbLancamentos[Mês],Calc!$B$6,tbLancamentos[Ano],Calc!$B$7))) | F22: =IF(B22="","",SUMIFS(tbLancamentos[Valor],tbLancamentos[Descrição],B22,tbLancamentos[Mês],MesNum,tbLancamentos[Ano],AnoSelecionado)) | G22: =IF(B22="","",IF(I22=0,IF(AND(D22<>"",DATE(AnoSelecionado,MesNum,MIN(IF(D22="",1,D22),DAY(EOMONTH(DATE(AnoSelecionado,MesNum,1),0))))<TODAY()),"✖ Atrasada — falta lançar","✖ Falta lançar"),IF(J22>0,IF(DATE(AnoSelecionado,MesNum,MIN(IF(D22="",1,D22),DAY(EOMONTH(DATE(AnoSelecionado,MesNum,1),0))))<TODAY(),"⏳ Pendente — vencida","⏳ Pendente"),IF(INDEX(Atalhos!$C:$C,$H22)="Receita","✔ Recebido","✔ Pago")))) | H22: =Calc!AR14 | I22: =IF(B22="",0,COUNTIFS(tbLancamentos[Descrição],B22,tbLancamentos[Mês],MesNum,tbLancamentos[Ano],AnoSelecionado)) | J22: =IF(B22="",0,COUNTIFS(tbLancamentos[Descrição],B22,tbLancamentos[Mês],MesNum,tbLancamentos[Ano],AnoSelecionado,tbLancamentos[Situação],"Pendente")) | K22: =IF(LEFT(G22,1)="✖",SUMPRODUCT(--(LEFT($G$10:G22,1)="✖")),0) | M22: =IFERROR(DATE(AnoSelecionado,MesNum,MIN(IF(INDEX($D$10:$D$34,MATCH(13,$K$10:$K$34,0))="",1,INDEX($D$10:$D$34,MATCH(13,$K$10:$K$34,0))),DAY(EOMONTH(DATE(AnoSelecionado,MesNum,1),0)))),"") | N22: =IFERROR(INDEX($B$10:$B$34,MATCH(13,$K$10:$K$34,0)),"") | O22: =IFERROR(IF(N(INDEX($E$10:$E$34,MATCH(13,$K$10:$K$34,0)))>0,INDEX($E$10:$E$34,MATCH(13,$K$10:$K$34,0)),""),"") | P22: =IFERROR(INDEX(Atalhos!$C:$C,INDEX($H$10:$H$34,MATCH(13,$K$10:$K$34,0)))&"","") | Q22: =IFERROR(INDEX(Atalhos!$D:$D,INDEX($H$10:$H$34,MATCH(13,$K$10:$K$34,0)))&"","") | R22: =IFERROR(IF(MATCH(13,$K$10:$K$34,0)>0,"Pendente",""),"") | S22: =IFERROR(INDEX(Atalhos!$E:$E,INDEX($H$10:$H$34,MATCH(13,$K$10:$K$34,0)))&"","") | T22: =IFERROR(INDEX(Atalhos!$F:$F,INDEX($H$10:$H$34,MATCH(13,$K$10:$K$34,0)))&"","") | U22: =IFERROR(INDEX(Atalhos!$G:$G,INDEX($H$10:$H$34,MATCH(13,$K$10:$K$34,0)))&"","") | V22: =IFERROR(INDEX(Atalhos!$H:$H,INDEX($H$10:$H$34,MATCH(13,$K$10:$K$34,0)))&"","") | W22: =""
B23: =IF($H23=0,"",INDEX(Atalhos!$B:$B,$H23)&"") | C23: =IF($H23=0,"",INDEX(Atalhos!$D:$D,$H23)&"") | D23: =IF($H23=0,"",IF(INDEX(Atalhos!$K:$K,$H23)="","",INDEX(Atalhos!$K:$K,$H23))) | E23: =IF(B23="","",IF(N(INDEX(Atalhos!$I:$I,$H23))>0,INDEX(Atalhos!$I:$I,$H23),SUMIFS(tbLancamentos[Valor],tbLancamentos[Descrição],B23,tbLancamentos[Mês],Calc!$B$6,tbLancamentos[Ano],Calc!$B$7))) | F23: =IF(B23="","",SUMIFS(tbLancamentos[Valor],tbLancamentos[Descrição],B23,tbLancamentos[Mês],MesNum,tbLancamentos[Ano],AnoSelecionado)) | G23: =IF(B23="","",IF(I23=0,IF(AND(D23<>"",DATE(AnoSelecionado,MesNum,MIN(IF(D23="",1,D23),DAY(EOMONTH(DATE(AnoSelecionado,MesNum,1),0))))<TODAY()),"✖ Atrasada — falta lançar","✖ Falta lançar"),IF(J23>0,IF(DATE(AnoSelecionado,MesNum,MIN(IF(D23="",1,D23),DAY(EOMONTH(DATE(AnoSelecionado,MesNum,1),0))))<TODAY(),"⏳ Pendente — vencida","⏳ Pendente"),IF(INDEX(Atalhos!$C:$C,$H23)="Receita","✔ Recebido","✔ Pago")))) | H23: =Calc!AR15 | I23: =IF(B23="",0,COUNTIFS(tbLancamentos[Descrição],B23,tbLancamentos[Mês],MesNum,tbLancamentos[Ano],AnoSelecionado)) | J23: =IF(B23="",0,COUNTIFS(tbLancamentos[Descrição],B23,tbLancamentos[Mês],MesNum,tbLancamentos[Ano],AnoSelecionado,tbLancamentos[Situação],"Pendente")) | K23: =IF(LEFT(G23,1)="✖",SUMPRODUCT(--(LEFT($G$10:G23,1)="✖")),0) | M23: =IFERROR(DATE(AnoSelecionado,MesNum,MIN(IF(INDEX($D$10:$D$34,MATCH(14,$K$10:$K$34,0))="",1,INDEX($D$10:$D$34,MATCH(14,$K$10:$K$34,0))),DAY(EOMONTH(DATE(AnoSelecionado,MesNum,1),0)))),"") | N23: =IFERROR(INDEX($B$10:$B$34,MATCH(14,$K$10:$K$34,0)),"") | O23: =IFERROR(IF(N(INDEX($E$10:$E$34,MATCH(14,$K$10:$K$34,0)))>0,INDEX($E$10:$E$34,MATCH(14,$K$10:$K$34,0)),""),"") | P23: =IFERROR(INDEX(Atalhos!$C:$C,INDEX($H$10:$H$34,MATCH(14,$K$10:$K$34,0)))&"","") | Q23: =IFERROR(INDEX(Atalhos!$D:$D,INDEX($H$10:$H$34,MATCH(14,$K$10:$K$34,0)))&"","") | R23: =IFERROR(IF(MATCH(14,$K$10:$K$34,0)>0,"Pendente",""),"") | S23: =IFERROR(INDEX(Atalhos!$E:$E,INDEX($H$10:$H$34,MATCH(14,$K$10:$K$34,0)))&"","") | T23: =IFERROR(INDEX(Atalhos!$F:$F,INDEX($H$10:$H$34,MATCH(14,$K$10:$K$34,0)))&"","") | U23: =IFERROR(INDEX(Atalhos!$G:$G,INDEX($H$10:$H$34,MATCH(14,$K$10:$K$34,0)))&"","") | V23: =IFERROR(INDEX(Atalhos!$H:$H,INDEX($H$10:$H$34,MATCH(14,$K$10:$K$34,0)))&"","") | W23: =""
B24: =IF($H24=0,"",INDEX(Atalhos!$B:$B,$H24)&"") | C24: =IF($H24=0,"",INDEX(Atalhos!$D:$D,$H24)&"") | D24: =IF($H24=0,"",IF(INDEX(Atalhos!$K:$K,$H24)="","",INDEX(Atalhos!$K:$K,$H24))) | E24: =IF(B24="","",IF(N(INDEX(Atalhos!$I:$I,$H24))>0,INDEX(Atalhos!$I:$I,$H24),SUMIFS(tbLancamentos[Valor],tbLancamentos[Descrição],B24,tbLancamentos[Mês],Calc!$B$6,tbLancamentos[Ano],Calc!$B$7))) | F24: =IF(B24="","",SUMIFS(tbLancamentos[Valor],tbLancamentos[Descrição],B24,tbLancamentos[Mês],MesNum,tbLancamentos[Ano],AnoSelecionado)) | G24: =IF(B24="","",IF(I24=0,IF(AND(D24<>"",DATE(AnoSelecionado,MesNum,MIN(IF(D24="",1,D24),DAY(EOMONTH(DATE(AnoSelecionado,MesNum,1),0))))<TODAY()),"✖ Atrasada — falta lançar","✖ Falta lançar"),IF(J24>0,IF(DATE(AnoSelecionado,MesNum,MIN(IF(D24="",1,D24),DAY(EOMONTH(DATE(AnoSelecionado,MesNum,1),0))))<TODAY(),"⏳ Pendente — vencida","⏳ Pendente"),IF(INDEX(Atalhos!$C:$C,$H24)="Receita","✔ Recebido","✔ Pago")))) | H24: =Calc!AR16 | I24: =IF(B24="",0,COUNTIFS(tbLancamentos[Descrição],B24,tbLancamentos[Mês],MesNum,tbLancamentos[Ano],AnoSelecionado)) | J24: =IF(B24="",0,COUNTIFS(tbLancamentos[Descrição],B24,tbLancamentos[Mês],MesNum,tbLancamentos[Ano],AnoSelecionado,tbLancamentos[Situação],"Pendente")) | K24: =IF(LEFT(G24,1)="✖",SUMPRODUCT(--(LEFT($G$10:G24,1)="✖")),0) | M24: =IFERROR(DATE(AnoSelecionado,MesNum,MIN(IF(INDEX($D$10:$D$34,MATCH(15,$K$10:$K$34,0))="",1,INDEX($D$10:$D$34,MATCH(15,$K$10:$K$34,0))),DAY(EOMONTH(DATE(AnoSelecionado,MesNum,1),0)))),"") | N24: =IFERROR(INDEX($B$10:$B$34,MATCH(15,$K$10:$K$34,0)),"") | O24: =IFERROR(IF(N(INDEX($E$10:$E$34,MATCH(15,$K$10:$K$34,0)))>0,INDEX($E$10:$E$34,MATCH(15,$K$10:$K$34,0)),""),"") | P24: =IFERROR(INDEX(Atalhos!$C:$C,INDEX($H$10:$H$34,MATCH(15,$K$10:$K$34,0)))&"","") | Q24: =IFERROR(INDEX(Atalhos!$D:$D,INDEX($H$10:$H$34,MATCH(15,$K$10:$K$34,0)))&"","") | R24: =IFERROR(IF(MATCH(15,$K$10:$K$34,0)>0,"Pendente",""),"") | S24: =IFERROR(INDEX(Atalhos!$E:$E,INDEX($H$10:$H$34,MATCH(15,$K$10:$K$34,0)))&"","") | T24: =IFERROR(INDEX(Atalhos!$F:$F,INDEX($H$10:$H$34,MATCH(15,$K$10:$K$34,0)))&"","") | U24: =IFERROR(INDEX(Atalhos!$G:$G,INDEX($H$10:$H$34,MATCH(15,$K$10:$K$34,0)))&"","") | V24: =IFERROR(INDEX(Atalhos!$H:$H,INDEX($H$10:$H$34,MATCH(15,$K$10:$K$34,0)))&"","") | W24: =""
B25: =IF($H25=0,"",INDEX(Atalhos!$B:$B,$H25)&"") | C25: =IF($H25=0,"",INDEX(Atalhos!$D:$D,$H25)&"") | D25: =IF($H25=0,"",IF(INDEX(Atalhos!$K:$K,$H25)="","",INDEX(Atalhos!$K:$K,$H25))) | E25: =IF(B25="","",IF(N(INDEX(Atalhos!$I:$I,$H25))>0,INDEX(Atalhos!$I:$I,$H25),SUMIFS(tbLancamentos[Valor],tbLancamentos[Descrição],B25,tbLancamentos[Mês],Calc!$B$6,tbLancamentos[Ano],Calc!$B$7))) | F25: =IF(B25="","",SUMIFS(tbLancamentos[Valor],tbLancamentos[Descrição],B25,tbLancamentos[Mês],MesNum,tbLancamentos[Ano],AnoSelecionado)) | G25: =IF(B25="","",IF(I25=0,IF(AND(D25<>"",DATE(AnoSelecionado,MesNum,MIN(IF(D25="",1,D25),DAY(EOMONTH(DATE(AnoSelecionado,MesNum,1),0))))<TODAY()),"✖ Atrasada — falta lançar","✖ Falta lançar"),IF(J25>0,IF(DATE(AnoSelecionado,MesNum,MIN(IF(D25="",1,D25),DAY(EOMONTH(DATE(AnoSelecionado,MesNum,1),0))))<TODAY(),"⏳ Pendente — vencida","⏳ Pendente"),IF(INDEX(Atalhos!$C:$C,$H25)="Receita","✔ Recebido","✔ Pago")))) | H25: =Calc!AR17 | I25: =IF(B25="",0,COUNTIFS(tbLancamentos[Descrição],B25,tbLancamentos[Mês],MesNum,tbLancamentos[Ano],AnoSelecionado)) | J25: =IF(B25="",0,COUNTIFS(tbLancamentos[Descrição],B25,tbLancamentos[Mês],MesNum,tbLancamentos[Ano],AnoSelecionado,tbLancamentos[Situação],"Pendente")) | K25: =IF(LEFT(G25,1)="✖",SUMPRODUCT(--(LEFT($G$10:G25,1)="✖")),0) | M25: =IFERROR(DATE(AnoSelecionado,MesNum,MIN(IF(INDEX($D$10:$D$34,MATCH(16,$K$10:$K$34,0))="",1,INDEX($D$10:$D$34,MATCH(16,$K$10:$K$34,0))),DAY(EOMONTH(DATE(AnoSelecionado,MesNum,1),0)))),"") | N25: =IFERROR(INDEX($B$10:$B$34,MATCH(16,$K$10:$K$34,0)),"") | O25: =IFERROR(IF(N(INDEX($E$10:$E$34,MATCH(16,$K$10:$K$34,0)))>0,INDEX($E$10:$E$34,MATCH(16,$K$10:$K$34,0)),""),"") | P25: =IFERROR(INDEX(Atalhos!$C:$C,INDEX($H$10:$H$34,MATCH(16,$K$10:$K$34,0)))&"","") | Q25: =IFERROR(INDEX(Atalhos!$D:$D,INDEX($H$10:$H$34,MATCH(16,$K$10:$K$34,0)))&"","") | R25: =IFERROR(IF(MATCH(16,$K$10:$K$34,0)>0,"Pendente",""),"") | S25: =IFERROR(INDEX(Atalhos!$E:$E,INDEX($H$10:$H$34,MATCH(16,$K$10:$K$34,0)))&"","") | T25: =IFERROR(INDEX(Atalhos!$F:$F,INDEX($H$10:$H$34,MATCH(16,$K$10:$K$34,0)))&"","") | U25: =IFERROR(INDEX(Atalhos!$G:$G,INDEX($H$10:$H$34,MATCH(16,$K$10:$K$34,0)))&"","") | V25: =IFERROR(INDEX(Atalhos!$H:$H,INDEX($H$10:$H$34,MATCH(16,$K$10:$K$34,0)))&"","") | W25: =""
B26: =IF($H26=0,"",INDEX(Atalhos!$B:$B,$H26)&"") | C26: =IF($H26=0,"",INDEX(Atalhos!$D:$D,$H26)&"") | D26: =IF($H26=0,"",IF(INDEX(Atalhos!$K:$K,$H26)="","",INDEX(Atalhos!$K:$K,$H26))) | E26: =IF(B26="","",IF(N(INDEX(Atalhos!$I:$I,$H26))>0,INDEX(Atalhos!$I:$I,$H26),SUMIFS(tbLancamentos[Valor],tbLancamentos[Descrição],B26,tbLancamentos[Mês],Calc!$B$6,tbLancamentos[Ano],Calc!$B$7))) | F26: =IF(B26="","",SUMIFS(tbLancamentos[Valor],tbLancamentos[Descrição],B26,tbLancamentos[Mês],MesNum,tbLancamentos[Ano],AnoSelecionado)) | G26: =IF(B26="","",IF(I26=0,IF(AND(D26<>"",DATE(AnoSelecionado,MesNum,MIN(IF(D26="",1,D26),DAY(EOMONTH(DATE(AnoSelecionado,MesNum,1),0))))<TODAY()),"✖ Atrasada — falta lançar","✖ Falta lançar"),IF(J26>0,IF(DATE(AnoSelecionado,MesNum,MIN(IF(D26="",1,D26),DAY(EOMONTH(DATE(AnoSelecionado,MesNum,1),0))))<TODAY(),"⏳ Pendente — vencida","⏳ Pendente"),IF(INDEX(Atalhos!$C:$C,$H26)="Receita","✔ Recebido","✔ Pago")))) | H26: =Calc!AR18 | I26: =IF(B26="",0,COUNTIFS(tbLancamentos[Descrição],B26,tbLancamentos[Mês],MesNum,tbLancamentos[Ano],AnoSelecionado)) | J26: =IF(B26="",0,COUNTIFS(tbLancamentos[Descrição],B26,tbLancamentos[Mês],MesNum,tbLancamentos[Ano],AnoSelecionado,tbLancamentos[Situação],"Pendente")) | K26: =IF(LEFT(G26,1)="✖",SUMPRODUCT(--(LEFT($G$10:G26,1)="✖")),0) | M26: =IFERROR(DATE(AnoSelecionado,MesNum,MIN(IF(INDEX($D$10:$D$34,MATCH(17,$K$10:$K$34,0))="",1,INDEX($D$10:$D$34,MATCH(17,$K$10:$K$34,0))),DAY(EOMONTH(DATE(AnoSelecionado,MesNum,1),0)))),"") | N26: =IFERROR(INDEX($B$10:$B$34,MATCH(17,$K$10:$K$34,0)),"") | O26: =IFERROR(IF(N(INDEX($E$10:$E$34,MATCH(17,$K$10:$K$34,0)))>0,INDEX($E$10:$E$34,MATCH(17,$K$10:$K$34,0)),""),"") | P26: =IFERROR(INDEX(Atalhos!$C:$C,INDEX($H$10:$H$34,MATCH(17,$K$10:$K$34,0)))&"","") | Q26: =IFERROR(INDEX(Atalhos!$D:$D,INDEX($H$10:$H$34,MATCH(17,$K$10:$K$34,0)))&"","") | R26: =IFERROR(IF(MATCH(17,$K$10:$K$34,0)>0,"Pendente",""),"") | S26: =IFERROR(INDEX(Atalhos!$E:$E,INDEX($H$10:$H$34,MATCH(17,$K$10:$K$34,0)))&"","") | T26: =IFERROR(INDEX(Atalhos!$F:$F,INDEX($H$10:$H$34,MATCH(17,$K$10:$K$34,0)))&"","") | U26: =IFERROR(INDEX(Atalhos!$G:$G,INDEX($H$10:$H$34,MATCH(17,$K$10:$K$34,0)))&"","") | V26: =IFERROR(INDEX(Atalhos!$H:$H,INDEX($H$10:$H$34,MATCH(17,$K$10:$K$34,0)))&"","") | W26: =""
B27: =IF($H27=0,"",INDEX(Atalhos!$B:$B,$H27)&"") | C27: =IF($H27=0,"",INDEX(Atalhos!$D:$D,$H27)&"") | D27: =IF($H27=0,"",IF(INDEX(Atalhos!$K:$K,$H27)="","",INDEX(Atalhos!$K:$K,$H27))) | E27: =IF(B27="","",IF(N(INDEX(Atalhos!$I:$I,$H27))>0,INDEX(Atalhos!$I:$I,$H27),SUMIFS(tbLancamentos[Valor],tbLancamentos[Descrição],B27,tbLancamentos[Mês],Calc!$B$6,tbLancamentos[Ano],Calc!$B$7))) | F27: =IF(B27="","",SUMIFS(tbLancamentos[Valor],tbLancamentos[Descrição],B27,tbLancamentos[Mês],MesNum,tbLancamentos[Ano],AnoSelecionado)) | G27: =IF(B27="","",IF(I27=0,IF(AND(D27<>"",DATE(AnoSelecionado,MesNum,MIN(IF(D27="",1,D27),DAY(EOMONTH(DATE(AnoSelecionado,MesNum,1),0))))<TODAY()),"✖ Atrasada — falta lançar","✖ Falta lançar"),IF(J27>0,IF(DATE(AnoSelecionado,MesNum,MIN(IF(D27="",1,D27),DAY(EOMONTH(DATE(AnoSelecionado,MesNum,1),0))))<TODAY(),"⏳ Pendente — vencida","⏳ Pendente"),IF(INDEX(Atalhos!$C:$C,$H27)="Receita","✔ Recebido","✔ Pago")))) | H27: =Calc!AR19 | I27: =IF(B27="",0,COUNTIFS(tbLancamentos[Descrição],B27,tbLancamentos[Mês],MesNum,tbLancamentos[Ano],AnoSelecionado)) | J27: =IF(B27="",0,COUNTIFS(tbLancamentos[Descrição],B27,tbLancamentos[Mês],MesNum,tbLancamentos[Ano],AnoSelecionado,tbLancamentos[Situação],"Pendente")) | K27: =IF(LEFT(G27,1)="✖",SUMPRODUCT(--(LEFT($G$10:G27,1)="✖")),0) | M27: =IFERROR(DATE(AnoSelecionado,MesNum,MIN(IF(INDEX($D$10:$D$34,MATCH(18,$K$10:$K$34,0))="",1,INDEX($D$10:$D$34,MATCH(18,$K$10:$K$34,0))),DAY(EOMONTH(DATE(AnoSelecionado,MesNum,1),0)))),"") | N27: =IFERROR(INDEX($B$10:$B$34,MATCH(18,$K$10:$K$34,0)),"") | O27: =IFERROR(IF(N(INDEX($E$10:$E$34,MATCH(18,$K$10:$K$34,0)))>0,INDEX($E$10:$E$34,MATCH(18,$K$10:$K$34,0)),""),"") | P27: =IFERROR(INDEX(Atalhos!$C:$C,INDEX($H$10:$H$34,MATCH(18,$K$10:$K$34,0)))&"","") | Q27: =IFERROR(INDEX(Atalhos!$D:$D,INDEX($H$10:$H$34,MATCH(18,$K$10:$K$34,0)))&"","") | R27: =IFERROR(IF(MATCH(18,$K$10:$K$34,0)>0,"Pendente",""),"") | S27: =IFERROR(INDEX(Atalhos!$E:$E,INDEX($H$10:$H$34,MATCH(18,$K$10:$K$34,0)))&"","") | T27: =IFERROR(INDEX(Atalhos!$F:$F,INDEX($H$10:$H$34,MATCH(18,$K$10:$K$34,0)))&"","") | U27: =IFERROR(INDEX(Atalhos!$G:$G,INDEX($H$10:$H$34,MATCH(18,$K$10:$K$34,0)))&"","") | V27: =IFERROR(INDEX(Atalhos!$H:$H,INDEX($H$10:$H$34,MATCH(18,$K$10:$K$34,0)))&"","") | W27: =""
B28: =IF($H28=0,"",INDEX(Atalhos!$B:$B,$H28)&"") | C28: =IF($H28=0,"",INDEX(Atalhos!$D:$D,$H28)&"") | D28: =IF($H28=0,"",IF(INDEX(Atalhos!$K:$K,$H28)="","",INDEX(Atalhos!$K:$K,$H28))) | E28: =IF(B28="","",IF(N(INDEX(Atalhos!$I:$I,$H28))>0,INDEX(Atalhos!$I:$I,$H28),SUMIFS(tbLancamentos[Valor],tbLancamentos[Descrição],B28,tbLancamentos[Mês],Calc!$B$6,tbLancamentos[Ano],Calc!$B$7))) | F28: =IF(B28="","",SUMIFS(tbLancamentos[Valor],tbLancamentos[Descrição],B28,tbLancamentos[Mês],MesNum,tbLancamentos[Ano],AnoSelecionado)) | G28: =IF(B28="","",IF(I28=0,IF(AND(D28<>"",DATE(AnoSelecionado,MesNum,MIN(IF(D28="",1,D28),DAY(EOMONTH(DATE(AnoSelecionado,MesNum,1),0))))<TODAY()),"✖ Atrasada — falta lançar","✖ Falta lançar"),IF(J28>0,IF(DATE(AnoSelecionado,MesNum,MIN(IF(D28="",1,D28),DAY(EOMONTH(DATE(AnoSelecionado,MesNum,1),0))))<TODAY(),"⏳ Pendente — vencida","⏳ Pendente"),IF(INDEX(Atalhos!$C:$C,$H28)="Receita","✔ Recebido","✔ Pago")))) | H28: =Calc!AR20 | I28: =IF(B28="",0,COUNTIFS(tbLancamentos[Descrição],B28,tbLancamentos[Mês],MesNum,tbLancamentos[Ano],AnoSelecionado)) | J28: =IF(B28="",0,COUNTIFS(tbLancamentos[Descrição],B28,tbLancamentos[Mês],MesNum,tbLancamentos[Ano],AnoSelecionado,tbLancamentos[Situação],"Pendente")) | K28: =IF(LEFT(G28,1)="✖",SUMPRODUCT(--(LEFT($G$10:G28,1)="✖")),0) | M28: =IFERROR(DATE(AnoSelecionado,MesNum,MIN(IF(INDEX($D$10:$D$34,MATCH(19,$K$10:$K$34,0))="",1,INDEX($D$10:$D$34,MATCH(19,$K$10:$K$34,0))),DAY(EOMONTH(DATE(AnoSelecionado,MesNum,1),0)))),"") | N28: =IFERROR(INDEX($B$10:$B$34,MATCH(19,$K$10:$K$34,0)),"") | O28: =IFERROR(IF(N(INDEX($E$10:$E$34,MATCH(19,$K$10:$K$34,0)))>0,INDEX($E$10:$E$34,MATCH(19,$K$10:$K$34,0)),""),"") | P28: =IFERROR(INDEX(Atalhos!$C:$C,INDEX($H$10:$H$34,MATCH(19,$K$10:$K$34,0)))&"","") | Q28: =IFERROR(INDEX(Atalhos!$D:$D,INDEX($H$10:$H$34,MATCH(19,$K$10:$K$34,0)))&"","") | R28: =IFERROR(IF(MATCH(19,$K$10:$K$34,0)>0,"Pendente",""),"") | S28: =IFERROR(INDEX(Atalhos!$E:$E,INDEX($H$10:$H$34,MATCH(19,$K$10:$K$34,0)))&"","") | T28: =IFERROR(INDEX(Atalhos!$F:$F,INDEX($H$10:$H$34,MATCH(19,$K$10:$K$34,0)))&"","") | U28: =IFERROR(INDEX(Atalhos!$G:$G,INDEX($H$10:$H$34,MATCH(19,$K$10:$K$34,0)))&"","") | V28: =IFERROR(INDEX(Atalhos!$H:$H,INDEX($H$10:$H$34,MATCH(19,$K$10:$K$34,0)))&"","") | W28: =""
B29: =IF($H29=0,"",INDEX(Atalhos!$B:$B,$H29)&"") | C29: =IF($H29=0,"",INDEX(Atalhos!$D:$D,$H29)&"") | D29: =IF($H29=0,"",IF(INDEX(Atalhos!$K:$K,$H29)="","",INDEX(Atalhos!$K:$K,$H29))) | E29: =IF(B29="","",IF(N(INDEX(Atalhos!$I:$I,$H29))>0,INDEX(Atalhos!$I:$I,$H29),SUMIFS(tbLancamentos[Valor],tbLancamentos[Descrição],B29,tbLancamentos[Mês],Calc!$B$6,tbLancamentos[Ano],Calc!$B$7))) | F29: =IF(B29="","",SUMIFS(tbLancamentos[Valor],tbLancamentos[Descrição],B29,tbLancamentos[Mês],MesNum,tbLancamentos[Ano],AnoSelecionado)) | G29: =IF(B29="","",IF(I29=0,IF(AND(D29<>"",DATE(AnoSelecionado,MesNum,MIN(IF(D29="",1,D29),DAY(EOMONTH(DATE(AnoSelecionado,MesNum,1),0))))<TODAY()),"✖ Atrasada — falta lançar","✖ Falta lançar"),IF(J29>0,IF(DATE(AnoSelecionado,MesNum,MIN(IF(D29="",1,D29),DAY(EOMONTH(DATE(AnoSelecionado,MesNum,1),0))))<TODAY(),"⏳ Pendente — vencida","⏳ Pendente"),IF(INDEX(Atalhos!$C:$C,$H29)="Receita","✔ Recebido","✔ Pago")))) | H29: =Calc!AR21 | I29: =IF(B29="",0,COUNTIFS(tbLancamentos[Descrição],B29,tbLancamentos[Mês],MesNum,tbLancamentos[Ano],AnoSelecionado)) | J29: =IF(B29="",0,COUNTIFS(tbLancamentos[Descrição],B29,tbLancamentos[Mês],MesNum,tbLancamentos[Ano],AnoSelecionado,tbLancamentos[Situação],"Pendente")) | K29: =IF(LEFT(G29,1)="✖",SUMPRODUCT(--(LEFT($G$10:G29,1)="✖")),0) | M29: =IFERROR(DATE(AnoSelecionado,MesNum,MIN(IF(INDEX($D$10:$D$34,MATCH(20,$K$10:$K$34,0))="",1,INDEX($D$10:$D$34,MATCH(20,$K$10:$K$34,0))),DAY(EOMONTH(DATE(AnoSelecionado,MesNum,1),0)))),"") | N29: =IFERROR(INDEX($B$10:$B$34,MATCH(20,$K$10:$K$34,0)),"") | O29: =IFERROR(IF(N(INDEX($E$10:$E$34,MATCH(20,$K$10:$K$34,0)))>0,INDEX($E$10:$E$34,MATCH(20,$K$10:$K$34,0)),""),"") | P29: =IFERROR(INDEX(Atalhos!$C:$C,INDEX($H$10:$H$34,MATCH(20,$K$10:$K$34,0)))&"","") | Q29: =IFERROR(INDEX(Atalhos!$D:$D,INDEX($H$10:$H$34,MATCH(20,$K$10:$K$34,0)))&"","") | R29: =IFERROR(IF(MATCH(20,$K$10:$K$34,0)>0,"Pendente",""),"") | S29: =IFERROR(INDEX(Atalhos!$E:$E,INDEX($H$10:$H$34,MATCH(20,$K$10:$K$34,0)))&"","") | T29: =IFERROR(INDEX(Atalhos!$F:$F,INDEX($H$10:$H$34,MATCH(20,$K$10:$K$34,0)))&"","") | U29: =IFERROR(INDEX(Atalhos!$G:$G,INDEX($H$10:$H$34,MATCH(20,$K$10:$K$34,0)))&"","") | V29: =IFERROR(INDEX(Atalhos!$H:$H,INDEX($H$10:$H$34,MATCH(20,$K$10:$K$34,0)))&"","") | W29: =""
B30: =IF($H30=0,"",INDEX(Atalhos!$B:$B,$H30)&"") | C30: =IF($H30=0,"",INDEX(Atalhos!$D:$D,$H30)&"") | D30: =IF($H30=0,"",IF(INDEX(Atalhos!$K:$K,$H30)="","",INDEX(Atalhos!$K:$K,$H30))) | E30: =IF(B30="","",IF(N(INDEX(Atalhos!$I:$I,$H30))>0,INDEX(Atalhos!$I:$I,$H30),SUMIFS(tbLancamentos[Valor],tbLancamentos[Descrição],B30,tbLancamentos[Mês],Calc!$B$6,tbLancamentos[Ano],Calc!$B$7))) | F30: =IF(B30="","",SUMIFS(tbLancamentos[Valor],tbLancamentos[Descrição],B30,tbLancamentos[Mês],MesNum,tbLancamentos[Ano],AnoSelecionado)) | G30: =IF(B30="","",IF(I30=0,IF(AND(D30<>"",DATE(AnoSelecionado,MesNum,MIN(IF(D30="",1,D30),DAY(EOMONTH(DATE(AnoSelecionado,MesNum,1),0))))<TODAY()),"✖ Atrasada — falta lançar","✖ Falta lançar"),IF(J30>0,IF(DATE(AnoSelecionado,MesNum,MIN(IF(D30="",1,D30),DAY(EOMONTH(DATE(AnoSelecionado,MesNum,1),0))))<TODAY(),"⏳ Pendente — vencida","⏳ Pendente"),IF(INDEX(Atalhos!$C:$C,$H30)="Receita","✔ Recebido","✔ Pago")))) | H30: =Calc!AR22 | I30: =IF(B30="",0,COUNTIFS(tbLancamentos[Descrição],B30,tbLancamentos[Mês],MesNum,tbLancamentos[Ano],AnoSelecionado)) | J30: =IF(B30="",0,COUNTIFS(tbLancamentos[Descrição],B30,tbLancamentos[Mês],MesNum,tbLancamentos[Ano],AnoSelecionado,tbLancamentos[Situação],"Pendente")) | K30: =IF(LEFT(G30,1)="✖",SUMPRODUCT(--(LEFT($G$10:G30,1)="✖")),0) | M30: =IFERROR(DATE(AnoSelecionado,MesNum,MIN(IF(INDEX($D$10:$D$34,MATCH(21,$K$10:$K$34,0))="",1,INDEX($D$10:$D$34,MATCH(21,$K$10:$K$34,0))),DAY(EOMONTH(DATE(AnoSelecionado,MesNum,1),0)))),"") | N30: =IFERROR(INDEX($B$10:$B$34,MATCH(21,$K$10:$K$34,0)),"") | O30: =IFERROR(IF(N(INDEX($E$10:$E$34,MATCH(21,$K$10:$K$34,0)))>0,INDEX($E$10:$E$34,MATCH(21,$K$10:$K$34,0)),""),"") | P30: =IFERROR(INDEX(Atalhos!$C:$C,INDEX($H$10:$H$34,MATCH(21,$K$10:$K$34,0)))&"","") | Q30: =IFERROR(INDEX(Atalhos!$D:$D,INDEX($H$10:$H$34,MATCH(21,$K$10:$K$34,0)))&"","") | R30: =IFERROR(IF(MATCH(21,$K$10:$K$34,0)>0,"Pendente",""),"") | S30: =IFERROR(INDEX(Atalhos!$E:$E,INDEX($H$10:$H$34,MATCH(21,$K$10:$K$34,0)))&"","") | T30: =IFERROR(INDEX(Atalhos!$F:$F,INDEX($H$10:$H$34,MATCH(21,$K$10:$K$34,0)))&"","") | U30: =IFERROR(INDEX(Atalhos!$G:$G,INDEX($H$10:$H$34,MATCH(21,$K$10:$K$34,0)))&"","") | V30: =IFERROR(INDEX(Atalhos!$H:$H,INDEX($H$10:$H$34,MATCH(21,$K$10:$K$34,0)))&"","") | W30: =""
B31: =IF($H31=0,"",INDEX(Atalhos!$B:$B,$H31)&"") | C31: =IF($H31=0,"",INDEX(Atalhos!$D:$D,$H31)&"") | D31: =IF($H31=0,"",IF(INDEX(Atalhos!$K:$K,$H31)="","",INDEX(Atalhos!$K:$K,$H31))) | E31: =IF(B31="","",IF(N(INDEX(Atalhos!$I:$I,$H31))>0,INDEX(Atalhos!$I:$I,$H31),SUMIFS(tbLancamentos[Valor],tbLancamentos[Descrição],B31,tbLancamentos[Mês],Calc!$B$6,tbLancamentos[Ano],Calc!$B$7))) | F31: =IF(B31="","",SUMIFS(tbLancamentos[Valor],tbLancamentos[Descrição],B31,tbLancamentos[Mês],MesNum,tbLancamentos[Ano],AnoSelecionado)) | G31: =IF(B31="","",IF(I31=0,IF(AND(D31<>"",DATE(AnoSelecionado,MesNum,MIN(IF(D31="",1,D31),DAY(EOMONTH(DATE(AnoSelecionado,MesNum,1),0))))<TODAY()),"✖ Atrasada — falta lançar","✖ Falta lançar"),IF(J31>0,IF(DATE(AnoSelecionado,MesNum,MIN(IF(D31="",1,D31),DAY(EOMONTH(DATE(AnoSelecionado,MesNum,1),0))))<TODAY(),"⏳ Pendente — vencida","⏳ Pendente"),IF(INDEX(Atalhos!$C:$C,$H31)="Receita","✔ Recebido","✔ Pago")))) | H31: =Calc!AR23 | I31: =IF(B31="",0,COUNTIFS(tbLancamentos[Descrição],B31,tbLancamentos[Mês],MesNum,tbLancamentos[Ano],AnoSelecionado)) | J31: =IF(B31="",0,COUNTIFS(tbLancamentos[Descrição],B31,tbLancamentos[Mês],MesNum,tbLancamentos[Ano],AnoSelecionado,tbLancamentos[Situação],"Pendente")) | K31: =IF(LEFT(G31,1)="✖",SUMPRODUCT(--(LEFT($G$10:G31,1)="✖")),0) | M31: =IFERROR(DATE(AnoSelecionado,MesNum,MIN(IF(INDEX($D$10:$D$34,MATCH(22,$K$10:$K$34,0))="",1,INDEX($D$10:$D$34,MATCH(22,$K$10:$K$34,0))),DAY(EOMONTH(DATE(AnoSelecionado,MesNum,1),0)))),"") | N31: =IFERROR(INDEX($B$10:$B$34,MATCH(22,$K$10:$K$34,0)),"") | O31: =IFERROR(IF(N(INDEX($E$10:$E$34,MATCH(22,$K$10:$K$34,0)))>0,INDEX($E$10:$E$34,MATCH(22,$K$10:$K$34,0)),""),"") | P31: =IFERROR(INDEX(Atalhos!$C:$C,INDEX($H$10:$H$34,MATCH(22,$K$10:$K$34,0)))&"","") | Q31: =IFERROR(INDEX(Atalhos!$D:$D,INDEX($H$10:$H$34,MATCH(22,$K$10:$K$34,0)))&"","") | R31: =IFERROR(IF(MATCH(22,$K$10:$K$34,0)>0,"Pendente",""),"") | S31: =IFERROR(INDEX(Atalhos!$E:$E,INDEX($H$10:$H$34,MATCH(22,$K$10:$K$34,0)))&"","") | T31: =IFERROR(INDEX(Atalhos!$F:$F,INDEX($H$10:$H$34,MATCH(22,$K$10:$K$34,0)))&"","") | U31: =IFERROR(INDEX(Atalhos!$G:$G,INDEX($H$10:$H$34,MATCH(22,$K$10:$K$34,0)))&"","") | V31: =IFERROR(INDEX(Atalhos!$H:$H,INDEX($H$10:$H$34,MATCH(22,$K$10:$K$34,0)))&"","") | W31: =""
B32: =IF($H32=0,"",INDEX(Atalhos!$B:$B,$H32)&"") | C32: =IF($H32=0,"",INDEX(Atalhos!$D:$D,$H32)&"") | D32: =IF($H32=0,"",IF(INDEX(Atalhos!$K:$K,$H32)="","",INDEX(Atalhos!$K:$K,$H32))) | E32: =IF(B32="","",IF(N(INDEX(Atalhos!$I:$I,$H32))>0,INDEX(Atalhos!$I:$I,$H32),SUMIFS(tbLancamentos[Valor],tbLancamentos[Descrição],B32,tbLancamentos[Mês],Calc!$B$6,tbLancamentos[Ano],Calc!$B$7))) | F32: =IF(B32="","",SUMIFS(tbLancamentos[Valor],tbLancamentos[Descrição],B32,tbLancamentos[Mês],MesNum,tbLancamentos[Ano],AnoSelecionado)) | G32: =IF(B32="","",IF(I32=0,IF(AND(D32<>"",DATE(AnoSelecionado,MesNum,MIN(IF(D32="",1,D32),DAY(EOMONTH(DATE(AnoSelecionado,MesNum,1),0))))<TODAY()),"✖ Atrasada — falta lançar","✖ Falta lançar"),IF(J32>0,IF(DATE(AnoSelecionado,MesNum,MIN(IF(D32="",1,D32),DAY(EOMONTH(DATE(AnoSelecionado,MesNum,1),0))))<TODAY(),"⏳ Pendente — vencida","⏳ Pendente"),IF(INDEX(Atalhos!$C:$C,$H32)="Receita","✔ Recebido","✔ Pago")))) | H32: =Calc!AR24 | I32: =IF(B32="",0,COUNTIFS(tbLancamentos[Descrição],B32,tbLancamentos[Mês],MesNum,tbLancamentos[Ano],AnoSelecionado)) | J32: =IF(B32="",0,COUNTIFS(tbLancamentos[Descrição],B32,tbLancamentos[Mês],MesNum,tbLancamentos[Ano],AnoSelecionado,tbLancamentos[Situação],"Pendente")) | K32: =IF(LEFT(G32,1)="✖",SUMPRODUCT(--(LEFT($G$10:G32,1)="✖")),0) | M32: =IFERROR(DATE(AnoSelecionado,MesNum,MIN(IF(INDEX($D$10:$D$34,MATCH(23,$K$10:$K$34,0))="",1,INDEX($D$10:$D$34,MATCH(23,$K$10:$K$34,0))),DAY(EOMONTH(DATE(AnoSelecionado,MesNum,1),0)))),"") | N32: =IFERROR(INDEX($B$10:$B$34,MATCH(23,$K$10:$K$34,0)),"") | O32: =IFERROR(IF(N(INDEX($E$10:$E$34,MATCH(23,$K$10:$K$34,0)))>0,INDEX($E$10:$E$34,MATCH(23,$K$10:$K$34,0)),""),"") | P32: =IFERROR(INDEX(Atalhos!$C:$C,INDEX($H$10:$H$34,MATCH(23,$K$10:$K$34,0)))&"","") | Q32: =IFERROR(INDEX(Atalhos!$D:$D,INDEX($H$10:$H$34,MATCH(23,$K$10:$K$34,0)))&"","") | R32: =IFERROR(IF(MATCH(23,$K$10:$K$34,0)>0,"Pendente",""),"") | S32: =IFERROR(INDEX(Atalhos!$E:$E,INDEX($H$10:$H$34,MATCH(23,$K$10:$K$34,0)))&"","") | T32: =IFERROR(INDEX(Atalhos!$F:$F,INDEX($H$10:$H$34,MATCH(23,$K$10:$K$34,0)))&"","") | U32: =IFERROR(INDEX(Atalhos!$G:$G,INDEX($H$10:$H$34,MATCH(23,$K$10:$K$34,0)))&"","") | V32: =IFERROR(INDEX(Atalhos!$H:$H,INDEX($H$10:$H$34,MATCH(23,$K$10:$K$34,0)))&"","") | W32: =""
B33: =IF($H33=0,"",INDEX(Atalhos!$B:$B,$H33)&"") | C33: =IF($H33=0,"",INDEX(Atalhos!$D:$D,$H33)&"") | D33: =IF($H33=0,"",IF(INDEX(Atalhos!$K:$K,$H33)="","",INDEX(Atalhos!$K:$K,$H33))) | E33: =IF(B33="","",IF(N(INDEX(Atalhos!$I:$I,$H33))>0,INDEX(Atalhos!$I:$I,$H33),SUMIFS(tbLancamentos[Valor],tbLancamentos[Descrição],B33,tbLancamentos[Mês],Calc!$B$6,tbLancamentos[Ano],Calc!$B$7))) | F33: =IF(B33="","",SUMIFS(tbLancamentos[Valor],tbLancamentos[Descrição],B33,tbLancamentos[Mês],MesNum,tbLancamentos[Ano],AnoSelecionado)) | G33: =IF(B33="","",IF(I33=0,IF(AND(D33<>"",DATE(AnoSelecionado,MesNum,MIN(IF(D33="",1,D33),DAY(EOMONTH(DATE(AnoSelecionado,MesNum,1),0))))<TODAY()),"✖ Atrasada — falta lançar","✖ Falta lançar"),IF(J33>0,IF(DATE(AnoSelecionado,MesNum,MIN(IF(D33="",1,D33),DAY(EOMONTH(DATE(AnoSelecionado,MesNum,1),0))))<TODAY(),"⏳ Pendente — vencida","⏳ Pendente"),IF(INDEX(Atalhos!$C:$C,$H33)="Receita","✔ Recebido","✔ Pago")))) | H33: =Calc!AR25 | I33: =IF(B33="",0,COUNTIFS(tbLancamentos[Descrição],B33,tbLancamentos[Mês],MesNum,tbLancamentos[Ano],AnoSelecionado)) | J33: =IF(B33="",0,COUNTIFS(tbLancamentos[Descrição],B33,tbLancamentos[Mês],MesNum,tbLancamentos[Ano],AnoSelecionado,tbLancamentos[Situação],"Pendente")) | K33: =IF(LEFT(G33,1)="✖",SUMPRODUCT(--(LEFT($G$10:G33,1)="✖")),0) | M33: =IFERROR(DATE(AnoSelecionado,MesNum,MIN(IF(INDEX($D$10:$D$34,MATCH(24,$K$10:$K$34,0))="",1,INDEX($D$10:$D$34,MATCH(24,$K$10:$K$34,0))),DAY(EOMONTH(DATE(AnoSelecionado,MesNum,1),0)))),"") | N33: =IFERROR(INDEX($B$10:$B$34,MATCH(24,$K$10:$K$34,0)),"") | O33: =IFERROR(IF(N(INDEX($E$10:$E$34,MATCH(24,$K$10:$K$34,0)))>0,INDEX($E$10:$E$34,MATCH(24,$K$10:$K$34,0)),""),"") | P33: =IFERROR(INDEX(Atalhos!$C:$C,INDEX($H$10:$H$34,MATCH(24,$K$10:$K$34,0)))&"","") | Q33: =IFERROR(INDEX(Atalhos!$D:$D,INDEX($H$10:$H$34,MATCH(24,$K$10:$K$34,0)))&"","") | R33: =IFERROR(IF(MATCH(24,$K$10:$K$34,0)>0,"Pendente",""),"") | S33: =IFERROR(INDEX(Atalhos!$E:$E,INDEX($H$10:$H$34,MATCH(24,$K$10:$K$34,0)))&"","") | T33: =IFERROR(INDEX(Atalhos!$F:$F,INDEX($H$10:$H$34,MATCH(24,$K$10:$K$34,0)))&"","") | U33: =IFERROR(INDEX(Atalhos!$G:$G,INDEX($H$10:$H$34,MATCH(24,$K$10:$K$34,0)))&"","") | V33: =IFERROR(INDEX(Atalhos!$H:$H,INDEX($H$10:$H$34,MATCH(24,$K$10:$K$34,0)))&"","") | W33: =""
B34: =IF($H34=0,"",INDEX(Atalhos!$B:$B,$H34)&"") | C34: =IF($H34=0,"",INDEX(Atalhos!$D:$D,$H34)&"") | D34: =IF($H34=0,"",IF(INDEX(Atalhos!$K:$K,$H34)="","",INDEX(Atalhos!$K:$K,$H34))) | E34: =IF(B34="","",IF(N(INDEX(Atalhos!$I:$I,$H34))>0,INDEX(Atalhos!$I:$I,$H34),SUMIFS(tbLancamentos[Valor],tbLancamentos[Descrição],B34,tbLancamentos[Mês],Calc!$B$6,tbLancamentos[Ano],Calc!$B$7))) | F34: =IF(B34="","",SUMIFS(tbLancamentos[Valor],tbLancamentos[Descrição],B34,tbLancamentos[Mês],MesNum,tbLancamentos[Ano],AnoSelecionado)) | G34: =IF(B34="","",IF(I34=0,IF(AND(D34<>"",DATE(AnoSelecionado,MesNum,MIN(IF(D34="",1,D34),DAY(EOMONTH(DATE(AnoSelecionado,MesNum,1),0))))<TODAY()),"✖ Atrasada — falta lançar","✖ Falta lançar"),IF(J34>0,IF(DATE(AnoSelecionado,MesNum,MIN(IF(D34="",1,D34),DAY(EOMONTH(DATE(AnoSelecionado,MesNum,1),0))))<TODAY(),"⏳ Pendente — vencida","⏳ Pendente"),IF(INDEX(Atalhos!$C:$C,$H34)="Receita","✔ Recebido","✔ Pago")))) | H34: =Calc!AR26 | I34: =IF(B34="",0,COUNTIFS(tbLancamentos[Descrição],B34,tbLancamentos[Mês],MesNum,tbLancamentos[Ano],AnoSelecionado)) | J34: =IF(B34="",0,COUNTIFS(tbLancamentos[Descrição],B34,tbLancamentos[Mês],MesNum,tbLancamentos[Ano],AnoSelecionado,tbLancamentos[Situação],"Pendente")) | K34: =IF(LEFT(G34,1)="✖",SUMPRODUCT(--(LEFT($G$10:G34,1)="✖")),0) | M34: =IFERROR(DATE(AnoSelecionado,MesNum,MIN(IF(INDEX($D$10:$D$34,MATCH(25,$K$10:$K$34,0))="",1,INDEX($D$10:$D$34,MATCH(25,$K$10:$K$34,0))),DAY(EOMONTH(DATE(AnoSelecionado,MesNum,1),0)))),"") | N34: =IFERROR(INDEX($B$10:$B$34,MATCH(25,$K$10:$K$34,0)),"") | O34: =IFERROR(IF(N(INDEX($E$10:$E$34,MATCH(25,$K$10:$K$34,0)))>0,INDEX($E$10:$E$34,MATCH(25,$K$10:$K$34,0)),""),"") | P34: =IFERROR(INDEX(Atalhos!$C:$C,INDEX($H$10:$H$34,MATCH(25,$K$10:$K$34,0)))&"","") | Q34: =IFERROR(INDEX(Atalhos!$D:$D,INDEX($H$10:$H$34,MATCH(25,$K$10:$K$34,0)))&"","") | R34: =IFERROR(IF(MATCH(25,$K$10:$K$34,0)>0,"Pendente",""),"") | S34: =IFERROR(INDEX(Atalhos!$E:$E,INDEX($H$10:$H$34,MATCH(25,$K$10:$K$34,0)))&"","") | T34: =IFERROR(INDEX(Atalhos!$F:$F,INDEX($H$10:$H$34,MATCH(25,$K$10:$K$34,0)))&"","") | U34: =IFERROR(INDEX(Atalhos!$G:$G,INDEX($H$10:$H$34,MATCH(25,$K$10:$K$34,0)))&"","") | V34: =IFERROR(INDEX(Atalhos!$H:$H,INDEX($H$10:$H$34,MATCH(25,$K$10:$K$34,0)))&"","") | W34: =""

Sheet Parcelar
B2: Parcelar ou repetir | E2: =HYPERLINK("#Lancamentos!B"&(ROWS(tbLancamentos[Data])+5),"✚ Ir para a primeira linha vazia de Lançamentos")
B3: Preencha os campos à esquerda: o bloco à direita gera uma linha por parcela (ou por mês). Copie, vá até a primeira linha vazia de Lançamentos e cole só os valores.
B4: COMPRA / LANÇAMENTO | E4: Data | F4: Descrição | G4: Valor | H4: Tipo | I4: Categoria | J4: Situação | K4: Pote | L4: Quem | M4: Conta | N4: Forma de pagamento | O4: Parcela
B5: Modo | C5: Parcelado | E5: =IF(1<=$C$9,DATE(YEAR($C$10),MONTH($C$10)+0,MIN(DAY($C$10),DAY(EOMONTH(DATE(YEAR($C$10),MONTH($C$10)+0,1),0)))),"") | F5: =IF(1<=$C$9,$C$6,"") | G5: =IF(1<=$C$9,IF($C$5="Repetir todo mês",$C$7,IF($C$8="Total da compra",IF(1<$C$9,ROUND($C$7/$C$9,2),ROUND($C$7-ROUND($C$7/$C$9,2)*($C$9-1),2)),$C$7)),"") | H5: =IF(1<=$C$9,IF($C$11<>"",$C$11,IFERROR(INDEX(tbAtalhos[Tipo],MATCH($C$6,tbAtalhos[Descrição],0))&"","Despesa")),"") | I5: =IF(1<=$C$9,IF($C$12<>"",$C$12,IFERROR(INDEX(tbAtalhos[Categoria],MATCH($C$6,tbAtalhos[Descrição],0))&"","")),"") | J5: =IF(1<=$C$9,IF(AND(1=1,$C$17="sim"),IF(IF($C$11<>"",$C$11,IFERROR(INDEX(tbAtalhos[Tipo],MATCH($C$6,tbAtalhos[Descrição],0))&"","Despesa"))="Receita","Recebido","Pago"),"Pendente"),"") | K5: =IF(1<=$C$9,IF($C$13<>"",$C$13,IFERROR(INDEX(tbAtalhos[Pote],MATCH($C$6,tbAtalhos[Descrição],0))&"","")),"") | L5: =IF(1<=$C$9,IF($C$14<>"",$C$14,IFERROR(INDEX(tbAtalhos[Quem],MATCH($C$6,tbAtalhos[Descrição],0))&"","")),"") | M5: =IF(1<=$C$9,IF($C$15<>"",$C$15,IFERROR(INDEX(tbAtalhos[Conta],MATCH($C$6,tbAtalhos[Descrição],0))&"","")),"") | N5: =IF(1<=$C$9,IF($C$16<>"",$C$16,IFERROR(INDEX(tbAtalhos[Forma de pagamento],MATCH($C$6,tbAtalhos[Descrição],0))&"","")),"") | O5: =IF(AND(1<=$C$9,$C$5="Parcelado"),"1/"&$C$9,"")
B6: Descrição | C6: Geladeira nova (exemplo) | E6: =IF(2<=$C$9,DATE(YEAR($C$10),MONTH($C$10)+1,MIN(DAY($C$10),DAY(EOMONTH(DATE(YEAR($C$10),MONTH($C$10)+1,1),0)))),"") | F6: =IF(2<=$C$9,$C$6,"") | G6: =IF(2<=$C$9,IF($C$5="Repetir todo mês",$C$7,IF($C$8="Total da compra",IF(2<$C$9,ROUND($C$7/$C$9,2),ROUND($C$7-ROUND($C$7/$C$9,2)*($C$9-1),2)),$C$7)),"") | H6: =IF(2<=$C$9,IF($C$11<>"",$C$11,IFERROR(INDEX(tbAtalhos[Tipo],MATCH($C$6,tbAtalhos[Descrição],0))&"","Despesa")),"") | I6: =IF(2<=$C$9,IF($C$12<>"",$C$12,IFERROR(INDEX(tbAtalhos[Categoria],MATCH($C$6,tbAtalhos[Descrição],0))&"","")),"") | J6: =IF(2<=$C$9,IF(AND(2=1,$C$17="sim"),IF(IF($C$11<>"",$C$11,IFERROR(INDEX(tbAtalhos[Tipo],MATCH($C$6,tbAtalhos[Descrição],0))&"","Despesa"))="Receita","Recebido","Pago"),"Pendente"),"") | K6: =IF(2<=$C$9,IF($C$13<>"",$C$13,IFERROR(INDEX(tbAtalhos[Pote],MATCH($C$6,tbAtalhos[Descrição],0))&"","")),"") | L6: =IF(2<=$C$9,IF($C$14<>"",$C$14,IFERROR(INDEX(tbAtalhos[Quem],MATCH($C$6,tbAtalhos[Descrição],0))&"","")),"") | M6: =IF(2<=$C$9,IF($C$15<>"",$C$15,IFERROR(INDEX(tbAtalhos[Conta],MATCH($C$6,tbAtalhos[Descrição],0))&"","")),"") | N6: =IF(2<=$C$9,IF($C$16<>"",$C$16,IFERROR(INDEX(tbAtalhos[Forma de pagamento],MATCH($C$6,tbAtalhos[Descrição],0))&"","")),"") | O6: =IF(AND(2<=$C$9,$C$5="Parcelado"),"2/"&$C$9,"")
B7: Valor (R$) | C7: 3600 | E7: =IF(3<=$C$9,DATE(YEAR($C$10),MONTH($C$10)+2,MIN(DAY($C$10),DAY(EOMONTH(DATE(YEAR($C$10),MONTH($C$10)+2,1),0)))),"") | F7: =IF(3<=$C$9,$C$6,"") | G7: =IF(3<=$C$9,IF($C$5="Repetir todo mês",$C$7,IF($C$8="Total da compra",IF(3<$C$9,ROUND($C$7/$C$9,2),ROUND($C$7-ROUND($C$7/$C$9,2)*($C$9-1),2)),$C$7)),"") | H7: =IF(3<=$C$9,IF($C$11<>"",$C$11,IFERROR(INDEX(tbAtalhos[Tipo],MATCH($C$6,tbAtalhos[Descrição],0))&"","Despesa")),"") | I7: =IF(3<=$C$9,IF($C$12<>"",$C$12,IFERROR(INDEX(tbAtalhos[Categoria],MATCH($C$6,tbAtalhos[Descrição],0))&"","")),"") | J7: =IF(3<=$C$9,IF(AND(3=1,$C$17="sim"),IF(IF($C$11<>"",$C$11,IFERROR(INDEX(tbAtalhos[Tipo],MATCH($C$6,tbAtalhos[Descrição],0))&"","Despesa"))="Receita","Recebido","Pago"),"Pendente"),"") | K7: =IF(3<=$C$9,IF($C$13<>"",$C$13,IFERROR(INDEX(tbAtalhos[Pote],MATCH($C$6,tbAtalhos[Descrição],0))&"","")),"") | L7: =IF(3<=$C$9,IF($C$14<>"",$C$14,IFERROR(INDEX(tbAtalhos[Quem],MATCH($C$6,tbAtalhos[Descrição],0))&"","")),"") | M7: =IF(3<=$C$9,IF($C$15<>"",$C$15,IFERROR(INDEX(tbAtalhos[Conta],MATCH($C$6,tbAtalhos[Descrição],0))&"","")),"") | N7: =IF(3<=$C$9,IF($C$16<>"",$C$16,IFERROR(INDEX(tbAtalhos[Forma de pagamento],MATCH($C$6,tbAtalhos[Descrição],0))&"","")),"") | O7: =IF(AND(3<=$C$9,$C$5="Parcelado"),"3/"&$C$9,"")
B8: O valor informado é | C8: Total da compra | E8: =IF(4<=$C$9,DATE(YEAR($C$10),MONTH($C$10)+3,MIN(DAY($C$10),DAY(EOMONTH(DATE(YEAR($C$10),MONTH($C$10)+3,1),0)))),"") | F8: =IF(4<=$C$9,$C$6,"") | G8: =IF(4<=$C$9,IF($C$5="Repetir todo mês",$C$7,IF($C$8="Total da compra",IF(4<$C$9,ROUND($C$7/$C$9,2),ROUND($C$7-ROUND($C$7/$C$9,2)*($C$9-1),2)),$C$7)),"") | H8: =IF(4<=$C$9,IF($C$11<>"",$C$11,IFERROR(INDEX(tbAtalhos[Tipo],MATCH($C$6,tbAtalhos[Descrição],0))&"","Despesa")),"") | I8: =IF(4<=$C$9,IF($C$12<>"",$C$12,IFERROR(INDEX(tbAtalhos[Categoria],MATCH($C$6,tbAtalhos[Descrição],0))&"","")),"") | J8: =IF(4<=$C$9,IF(AND(4=1,$C$17="sim"),IF(IF($C$11<>"",$C$11,IFERROR(INDEX(tbAtalhos[Tipo],MATCH($C$6,tbAtalhos[Descrição],0))&"","Despesa"))="Receita","Recebido","Pago"),"Pendente"),"") | K8: =IF(4<=$C$9,IF($C$13<>"",$C$13,IFERROR(INDEX(tbAtalhos[Pote],MATCH($C$6,tbAtalhos[Descrição],0))&"","")),"") | L8: =IF(4<=$C$9,IF($C$14<>"",$C$14,IFERROR(INDEX(tbAtalhos[Quem],MATCH($C$6,tbAtalhos[Descrição],0))&"","")),"") | M8: =IF(4<=$C$9,IF($C$15<>"",$C$15,IFERROR(INDEX(tbAtalhos[Conta],MATCH($C$6,tbAtalhos[Descrição],0))&"","")),"") | N8: =IF(4<=$C$9,IF($C$16<>"",$C$16,IFERROR(INDEX(tbAtalhos[Forma de pagamento],MATCH($C$6,tbAtalhos[Descrição],0))&"","")),"") | O8: =IF(AND(4<=$C$9,$C$5="Parcelado"),"4/"&$C$9,"")
B9: Nº de parcelas / meses | C9: 10 | E9: =IF(5<=$C$9,DATE(YEAR($C$10),MONTH($C$10)+4,MIN(DAY($C$10),DAY(EOMONTH(DATE(YEAR($C$10),MONTH($C$10)+4,1),0)))),"") | F9: =IF(5<=$C$9,$C$6,"") | G9: =IF(5<=$C$9,IF($C$5="Repetir todo mês",$C$7,IF($C$8="Total da compra",IF(5<$C$9,ROUND($C$7/$C$9,2),ROUND($C$7-ROUND($C$7/$C$9,2)*($C$9-1),2)),$C$7)),"") | H9: =IF(5<=$C$9,IF($C$11<>"",$C$11,IFERROR(INDEX(tbAtalhos[Tipo],MATCH($C$6,tbAtalhos[Descrição],0))&"","Despesa")),"") | I9: =IF(5<=$C$9,IF($C$12<>"",$C$12,IFERROR(INDEX(tbAtalhos[Categoria],MATCH($C$6,tbAtalhos[Descrição],0))&"","")),"") | J9: =IF(5<=$C$9,IF(AND(5=1,$C$17="sim"),IF(IF($C$11<>"",$C$11,IFERROR(INDEX(tbAtalhos[Tipo],MATCH($C$6,tbAtalhos[Descrição],0))&"","Despesa"))="Receita","Recebido","Pago"),"Pendente"),"") | K9: =IF(5<=$C$9,IF($C$13<>"",$C$13,IFERROR(INDEX(tbAtalhos[Pote],MATCH($C$6,tbAtalhos[Descrição],0))&"","")),"") | L9: =IF(5<=$C$9,IF($C$14<>"",$C$14,IFERROR(INDEX(tbAtalhos[Quem],MATCH($C$6,tbAtalhos[Descrição],0))&"","")),"") | M9: =IF(5<=$C$9,IF($C$15<>"",$C$15,IFERROR(INDEX(tbAtalhos[Conta],MATCH($C$6,tbAtalhos[Descrição],0))&"","")),"") | N9: =IF(5<=$C$9,IF($C$16<>"",$C$16,IFERROR(INDEX(tbAtalhos[Forma de pagamento],MATCH($C$6,tbAtalhos[Descrição],0))&"","")),"") | O9: =IF(AND(5<=$C$9,$C$5="Parcelado"),"5/"&$C$9,"")
B10: Data da 1ª parcela | C10: 46305 | E10: =IF(6<=$C$9,DATE(YEAR($C$10),MONTH($C$10)+5,MIN(DAY($C$10),DAY(EOMONTH(DATE(YEAR($C$10),MONTH($C$10)+5,1),0)))),"") | F10: =IF(6<=$C$9,$C$6,"") | G10: =IF(6<=$C$9,IF($C$5="Repetir todo mês",$C$7,IF($C$8="Total da compra",IF(6<$C$9,ROUND($C$7/$C$9,2),ROUND($C$7-ROUND($C$7/$C$9,2)*($C$9-1),2)),$C$7)),"") | H10: =IF(6<=$C$9,IF($C$11<>"",$C$11,IFERROR(INDEX(tbAtalhos[Tipo],MATCH($C$6,tbAtalhos[Descrição],0))&"","Despesa")),"") | I10: =IF(6<=$C$9,IF($C$12<>"",$C$12,IFERROR(INDEX(tbAtalhos[Categoria],MATCH($C$6,tbAtalhos[Descrição],0))&"","")),"") | J10: =IF(6<=$C$9,IF(AND(6=1,$C$17="sim"),IF(IF($C$11<>"",$C$11,IFERROR(INDEX(tbAtalhos[Tipo],MATCH($C$6,tbAtalhos[Descrição],0))&"","Despesa"))="Receita","Recebido","Pago"),"Pendente"),"") | K10: =IF(6<=$C$9,IF($C$13<>"",$C$13,IFERROR(INDEX(tbAtalhos[Pote],MATCH($C$6,tbAtalhos[Descrição],0))&"","")),"") | L10: =IF(6<=$C$9,IF($C$14<>"",$C$14,IFERROR(INDEX(tbAtalhos[Quem],MATCH($C$6,tbAtalhos[Descrição],0))&"","")),"") | M10: =IF(6<=$C$9,IF($C$15<>"",$C$15,IFERROR(INDEX(tbAtalhos[Conta],MATCH($C$6,tbAtalhos[Descrição],0))&"","")),"") | N10: =IF(6<=$C$9,IF($C$16<>"",$C$16,IFERROR(INDEX(tbAtalhos[Forma de pagamento],MATCH($C$6,tbAtalhos[Descrição],0))&"","")),"") | O10: =IF(AND(6<=$C$9,$C$5="Parcelado"),"6/"&$C$9,"")
B11: Tipo | C11: Despesa | E11: =IF(7<=$C$9,DATE(YEAR($C$10),MONTH($C$10)+6,MIN(DAY($C$10),DAY(EOMONTH(DATE(YEAR($C$10),MONTH($C$10)+6,1),0)))),"") | F11: =IF(7<=$C$9,$C$6,"") | G11: =IF(7<=$C$9,IF($C$5="Repetir todo mês",$C$7,IF($C$8="Total da compra",IF(7<$C$9,ROUND($C$7/$C$9,2),ROUND($C$7-ROUND($C$7/$C$9,2)*($C$9-1),2)),$C$7)),"") | H11: =IF(7<=$C$9,IF($C$11<>"",$C$11,IFERROR(INDEX(tbAtalhos[Tipo],MATCH($C$6,tbAtalhos[Descrição],0))&"","Despesa")),"") | I11: =IF(7<=$C$9,IF($C$12<>"",$C$12,IFERROR(INDEX(tbAtalhos[Categoria],MATCH($C$6,tbAtalhos[Descrição],0))&"","")),"") | J11: =IF(7<=$C$9,IF(AND(7=1,$C$17="sim"),IF(IF($C$11<>"",$C$11,IFERROR(INDEX(tbAtalhos[Tipo],MATCH($C$6,tbAtalhos[Descrição],0))&"","Despesa"))="Receita","Recebido","Pago"),"Pendente"),"") | K11: =IF(7<=$C$9,IF($C$13<>"",$C$13,IFERROR(INDEX(tbAtalhos[Pote],MATCH($C$6,tbAtalhos[Descrição],0))&"","")),"") | L11: =IF(7<=$C$9,IF($C$14<>"",$C$14,IFERROR(INDEX(tbAtalhos[Quem],MATCH($C$6,tbAtalhos[Descrição],0))&"","")),"") | M11: =IF(7<=$C$9,IF($C$15<>"",$C$15,IFERROR(INDEX(tbAtalhos[Conta],MATCH($C$6,tbAtalhos[Descrição],0))&"","")),"") | N11: =IF(7<=$C$9,IF($C$16<>"",$C$16,IFERROR(INDEX(tbAtalhos[Forma de pagamento],MATCH($C$6,tbAtalhos[Descrição],0))&"","")),"") | O11: =IF(AND(7<=$C$9,$C$5="Parcelado"),"7/"&$C$9,"")
B12: Categoria (vazio = do favorito) | E12: =IF(8<=$C$9,DATE(YEAR($C$10),MONTH($C$10)+7,MIN(DAY($C$10),DAY(EOMONTH(DATE(YEAR($C$10),MONTH($C$10)+7,1),0)))),"") | F12: =IF(8<=$C$9,$C$6,"") | G12: =IF(8<=$C$9,IF($C$5="Repetir todo mês",$C$7,IF($C$8="Total da compra",IF(8<$C$9,ROUND($C$7/$C$9,2),ROUND($C$7-ROUND($C$7/$C$9,2)*($C$9-1),2)),$C$7)),"") | H12: =IF(8<=$C$9,IF($C$11<>"",$C$11,IFERROR(INDEX(tbAtalhos[Tipo],MATCH($C$6,tbAtalhos[Descrição],0))&"","Despesa")),"") | I12: =IF(8<=$C$9,IF($C$12<>"",$C$12,IFERROR(INDEX(tbAtalhos[Categoria],MATCH($C$6,tbAtalhos[Descrição],0))&"","")),"") | J12: =IF(8<=$C$9,IF(AND(8=1,$C$17="sim"),IF(IF($C$11<>"",$C$11,IFERROR(INDEX(tbAtalhos[Tipo],MATCH($C$6,tbAtalhos[Descrição],0))&"","Despesa"))="Receita","Recebido","Pago"),"Pendente"),"") | K12: =IF(8<=$C$9,IF($C$13<>"",$C$13,IFERROR(INDEX(tbAtalhos[Pote],MATCH($C$6,tbAtalhos[Descrição],0))&"","")),"") | L12: =IF(8<=$C$9,IF($C$14<>"",$C$14,IFERROR(INDEX(tbAtalhos[Quem],MATCH($C$6,tbAtalhos[Descrição],0))&"","")),"") | M12: =IF(8<=$C$9,IF($C$15<>"",$C$15,IFERROR(INDEX(tbAtalhos[Conta],MATCH($C$6,tbAtalhos[Descrição],0))&"","")),"") | N12: =IF(8<=$C$9,IF($C$16<>"",$C$16,IFERROR(INDEX(tbAtalhos[Forma de pagamento],MATCH($C$6,tbAtalhos[Descrição],0))&"","")),"") | O12: =IF(AND(8<=$C$9,$C$5="Parcelado"),"8/"&$C$9,"")
B13: Pote (vazio = do favorito) | E13: =IF(9<=$C$9,DATE(YEAR($C$10),MONTH($C$10)+8,MIN(DAY($C$10),DAY(EOMONTH(DATE(YEAR($C$10),MONTH($C$10)+8,1),0)))),"") | F13: =IF(9<=$C$9,$C$6,"") | G13: =IF(9<=$C$9,IF($C$5="Repetir todo mês",$C$7,IF($C$8="Total da compra",IF(9<$C$9,ROUND($C$7/$C$9,2),ROUND($C$7-ROUND($C$7/$C$9,2)*($C$9-1),2)),$C$7)),"") | H13: =IF(9<=$C$9,IF($C$11<>"",$C$11,IFERROR(INDEX(tbAtalhos[Tipo],MATCH($C$6,tbAtalhos[Descrição],0))&"","Despesa")),"") | I13: =IF(9<=$C$9,IF($C$12<>"",$C$12,IFERROR(INDEX(tbAtalhos[Categoria],MATCH($C$6,tbAtalhos[Descrição],0))&"","")),"") | J13: =IF(9<=$C$9,IF(AND(9=1,$C$17="sim"),IF(IF($C$11<>"",$C$11,IFERROR(INDEX(tbAtalhos[Tipo],MATCH($C$6,tbAtalhos[Descrição],0))&"","Despesa"))="Receita","Recebido","Pago"),"Pendente"),"") | K13: =IF(9<=$C$9,IF($C$13<>"",$C$13,IFERROR(INDEX(tbAtalhos[Pote],MATCH($C$6,tbAtalhos[Descrição],0))&"","")),"") | L13: =IF(9<=$C$9,IF($C$14<>"",$C$14,IFERROR(INDEX(tbAtalhos[Quem],MATCH($C$6,tbAtalhos[Descrição],0))&"","")),"") | M13: =IF(9<=$C$9,IF($C$15<>"",$C$15,IFERROR(INDEX(tbAtalhos[Conta],MATCH($C$6,tbAtalhos[Descrição],0))&"","")),"") | N13: =IF(9<=$C$9,IF($C$16<>"",$C$16,IFERROR(INDEX(tbAtalhos[Forma de pagamento],MATCH($C$6,tbAtalhos[Descrição],0))&"","")),"") | O13: =IF(AND(9<=$C$9,$C$5="Parcelado"),"9/"&$C$9,"")
B14: Quem | E14: =IF(10<=$C$9,DATE(YEAR($C$10),MONTH($C$10)+9,MIN(DAY($C$10),DAY(EOMONTH(DATE(YEAR($C$10),MONTH($C$10)+9,1),0)))),"") | F14: =IF(10<=$C$9,$C$6,"") | G14: =IF(10<=$C$9,IF($C$5="Repetir todo mês",$C$7,IF($C$8="Total da compra",IF(10<$C$9,ROUND($C$7/$C$9,2),ROUND($C$7-ROUND($C$7/$C$9,2)*($C$9-1),2)),$C$7)),"") | H14: =IF(10<=$C$9,IF($C$11<>"",$C$11,IFERROR(INDEX(tbAtalhos[Tipo],MATCH($C$6,tbAtalhos[Descrição],0))&"","Despesa")),"") | I14: =IF(10<=$C$9,IF($C$12<>"",$C$12,IFERROR(INDEX(tbAtalhos[Categoria],MATCH($C$6,tbAtalhos[Descrição],0))&"","")),"") | J14: =IF(10<=$C$9,IF(AND(10=1,$C$17="sim"),IF(IF($C$11<>"",$C$11,IFERROR(INDEX(tbAtalhos[Tipo],MATCH($C$6,tbAtalhos[Descrição],0))&"","Despesa"))="Receita","Recebido","Pago"),"Pendente"),"") | K14: =IF(10<=$C$9,IF($C$13<>"",$C$13,IFERROR(INDEX(tbAtalhos[Pote],MATCH($C$6,tbAtalhos[Descrição],0))&"","")),"") | L14: =IF(10<=$C$9,IF($C$14<>"",$C$14,IFERROR(INDEX(tbAtalhos[Quem],MATCH($C$6,tbAtalhos[Descrição],0))&"","")),"") | M14: =IF(10<=$C$9,IF($C$15<>"",$C$15,IFERROR(INDEX(tbAtalhos[Conta],MATCH($C$6,tbAtalhos[Descrição],0))&"","")),"") | N14: =IF(10<=$C$9,IF($C$16<>"",$C$16,IFERROR(INDEX(tbAtalhos[Forma de pagamento],MATCH($C$6,tbAtalhos[Descrição],0))&"","")),"") | O14: =IF(AND(10<=$C$9,$C$5="Parcelado"),"10/"&$C$9,"")
B15: Conta / cartão | E15: =IF(11<=$C$9,DATE(YEAR($C$10),MONTH($C$10)+10,MIN(DAY($C$10),DAY(EOMONTH(DATE(YEAR($C$10),MONTH($C$10)+10,1),0)))),"") | F15: =IF(11<=$C$9,$C$6,"") | G15: =IF(11<=$C$9,IF($C$5="Repetir todo mês",$C$7,IF($C$8="Total da compra",IF(11<$C$9,ROUND($C$7/$C$9,2),ROUND($C$7-ROUND($C$7/$C$9,2)*($C$9-1),2)),$C$7)),"") | H15: =IF(11<=$C$9,IF($C$11<>"",$C$11,IFERROR(INDEX(tbAtalhos[Tipo],MATCH($C$6,tbAtalhos[Descrição],0))&"","Despesa")),"") | I15: =IF(11<=$C$9,IF($C$12<>"",$C$12,IFERROR(INDEX(tbAtalhos[Categoria],MATCH($C$6,tbAtalhos[Descrição],0))&"","")),"") | J15: =IF(11<=$C$9,IF(AND(11=1,$C$17="sim"),IF(IF($C$11<>"",$C$11,IFERROR(INDEX(tbAtalhos[Tipo],MATCH($C$6,tbAtalhos[Descrição],0))&"","Despesa"))="Receita","Recebido","Pago"),"Pendente"),"") | K15: =IF(11<=$C$9,IF($C$13<>"",$C$13,IFERROR(INDEX(tbAtalhos[Pote],MATCH($C$6,tbAtalhos[Descrição],0))&"","")),"") | L15: =IF(11<=$C$9,IF($C$14<>"",$C$14,IFERROR(INDEX(tbAtalhos[Quem],MATCH($C$6,tbAtalhos[Descrição],0))&"","")),"") | M15: =IF(11<=$C$9,IF($C$15<>"",$C$15,IFERROR(INDEX(tbAtalhos[Conta],MATCH($C$6,tbAtalhos[Descrição],0))&"","")),"") | N15: =IF(11<=$C$9,IF($C$16<>"",$C$16,IFERROR(INDEX(tbAtalhos[Forma de pagamento],MATCH($C$6,tbAtalhos[Descrição],0))&"","")),"") | O15: =IF(AND(11<=$C$9,$C$5="Parcelado"),"11/"&$C$9,"")
B16: Forma de pagamento | C16: Cartão de crédito | E16: =IF(12<=$C$9,DATE(YEAR($C$10),MONTH($C$10)+11,MIN(DAY($C$10),DAY(EOMONTH(DATE(YEAR($C$10),MONTH($C$10)+11,1),0)))),"") | F16: =IF(12<=$C$9,$C$6,"") | G16: =IF(12<=$C$9,IF($C$5="Repetir todo mês",$C$7,IF($C$8="Total da compra",IF(12<$C$9,ROUND($C$7/$C$9,2),ROUND($C$7-ROUND($C$7/$C$9,2)*($C$9-1),2)),$C$7)),"") | H16: =IF(12<=$C$9,IF($C$11<>"",$C$11,IFERROR(INDEX(tbAtalhos[Tipo],MATCH($C$6,tbAtalhos[Descrição],0))&"","Despesa")),"") | I16: =IF(12<=$C$9,IF($C$12<>"",$C$12,IFERROR(INDEX(tbAtalhos[Categoria],MATCH($C$6,tbAtalhos[Descrição],0))&"","")),"") | J16: =IF(12<=$C$9,IF(AND(12=1,$C$17="sim"),IF(IF($C$11<>"",$C$11,IFERROR(INDEX(tbAtalhos[Tipo],MATCH($C$6,tbAtalhos[Descrição],0))&"","Despesa"))="Receita","Recebido","Pago"),"Pendente"),"") | K16: =IF(12<=$C$9,IF($C$13<>"",$C$13,IFERROR(INDEX(tbAtalhos[Pote],MATCH($C$6,tbAtalhos[Descrição],0))&"","")),"") | L16: =IF(12<=$C$9,IF($C$14<>"",$C$14,IFERROR(INDEX(tbAtalhos[Quem],MATCH($C$6,tbAtalhos[Descrição],0))&"","")),"") | M16: =IF(12<=$C$9,IF($C$15<>"",$C$15,IFERROR(INDEX(tbAtalhos[Conta],MATCH($C$6,tbAtalhos[Descrição],0))&"","")),"") | N16: =IF(12<=$C$9,IF($C$16<>"",$C$16,IFERROR(INDEX(tbAtalhos[Forma de pagamento],MATCH($C$6,tbAtalhos[Descrição],0))&"","")),"") | O16: =IF(AND(12<=$C$9,$C$5="Parcelado"),"12/"&$C$9,"")
B17: 1ª parcela já foi paga? | C17: não | E17: =IF(13<=$C$9,DATE(YEAR($C$10),MONTH($C$10)+12,MIN(DAY($C$10),DAY(EOMONTH(DATE(YEAR($C$10),MONTH($C$10)+12,1),0)))),"") | F17: =IF(13<=$C$9,$C$6,"") | G17: =IF(13<=$C$9,IF($C$5="Repetir todo mês",$C$7,IF($C$8="Total da compra",IF(13<$C$9,ROUND($C$7/$C$9,2),ROUND($C$7-ROUND($C$7/$C$9,2)*($C$9-1),2)),$C$7)),"") | H17: =IF(13<=$C$9,IF($C$11<>"",$C$11,IFERROR(INDEX(tbAtalhos[Tipo],MATCH($C$6,tbAtalhos[Descrição],0))&"","Despesa")),"") | I17: =IF(13<=$C$9,IF($C$12<>"",$C$12,IFERROR(INDEX(tbAtalhos[Categoria],MATCH($C$6,tbAtalhos[Descrição],0))&"","")),"") | J17: =IF(13<=$C$9,IF(AND(13=1,$C$17="sim"),IF(IF($C$11<>"",$C$11,IFERROR(INDEX(tbAtalhos[Tipo],MATCH($C$6,tbAtalhos[Descrição],0))&"","Despesa"))="Receita","Recebido","Pago"),"Pendente"),"") | K17: =IF(13<=$C$9,IF($C$13<>"",$C$13,IFERROR(INDEX(tbAtalhos[Pote],MATCH($C$6,tbAtalhos[Descrição],0))&"","")),"") | L17: =IF(13<=$C$9,IF($C$14<>"",$C$14,IFERROR(INDEX(tbAtalhos[Quem],MATCH($C$6,tbAtalhos[Descrição],0))&"","")),"") | M17: =IF(13<=$C$9,IF($C$15<>"",$C$15,IFERROR(INDEX(tbAtalhos[Conta],MATCH($C$6,tbAtalhos[Descrição],0))&"","")),"") | N17: =IF(13<=$C$9,IF($C$16<>"",$C$16,IFERROR(INDEX(tbAtalhos[Forma de pagamento],MATCH($C$6,tbAtalhos[Descrição],0))&"","")),"") | O17: =IF(AND(13<=$C$9,$C$5="Parcelado"),"13/"&$C$9,"")
E18: =IF(14<=$C$9,DATE(YEAR($C$10),MONTH($C$10)+13,MIN(DAY($C$10),DAY(EOMONTH(DATE(YEAR($C$10),MONTH($C$10)+13,1),0)))),"") | F18: =IF(14<=$C$9,$C$6,"") | G18: =IF(14<=$C$9,IF($C$5="Repetir todo mês",$C$7,IF($C$8="Total da compra",IF(14<$C$9,ROUND($C$7/$C$9,2),ROUND($C$7-ROUND($C$7/$C$9,2)*($C$9-1),2)),$C$7)),"") | H18: =IF(14<=$C$9,IF($C$11<>"",$C$11,IFERROR(INDEX(tbAtalhos[Tipo],MATCH($C$6,tbAtalhos[Descrição],0))&"","Despesa")),"") | I18: =IF(14<=$C$9,IF($C$12<>"",$C$12,IFERROR(INDEX(tbAtalhos[Categoria],MATCH($C$6,tbAtalhos[Descrição],0))&"","")),"") | J18: =IF(14<=$C$9,IF(AND(14=1,$C$17="sim"),IF(IF($C$11<>"",$C$11,IFERROR(INDEX(tbAtalhos[Tipo],MATCH($C$6,tbAtalhos[Descrição],0))&"","Despesa"))="Receita","Recebido","Pago"),"Pendente"),"") | K18: =IF(14<=$C$9,IF($C$13<>"",$C$13,IFERROR(INDEX(tbAtalhos[Pote],MATCH($C$6,tbAtalhos[Descrição],0))&"","")),"") | L18: =IF(14<=$C$9,IF($C$14<>"",$C$14,IFERROR(INDEX(tbAtalhos[Quem],MATCH($C$6,tbAtalhos[Descrição],0))&"","")),"") | M18: =IF(14<=$C$9,IF($C$15<>"",$C$15,IFERROR(INDEX(tbAtalhos[Conta],MATCH($C$6,tbAtalhos[Descrição],0))&"","")),"") | N18: =IF(14<=$C$9,IF($C$16<>"",$C$16,IFERROR(INDEX(tbAtalhos[Forma de pagamento],MATCH($C$6,tbAtalhos[Descrição],0))&"","")),"") | O18: =IF(AND(14<=$C$9,$C$5="Parcelado"),"14/"&$C$9,"")
B19: RESUMO | E19: =IF(15<=$C$9,DATE(YEAR($C$10),MONTH($C$10)+14,MIN(DAY($C$10),DAY(EOMONTH(DATE(YEAR($C$10),MONTH($C$10)+14,1),0)))),"") | F19: =IF(15<=$C$9,$C$6,"") | G19: =IF(15<=$C$9,IF($C$5="Repetir todo mês",$C$7,IF($C$8="Total da compra",IF(15<$C$9,ROUND($C$7/$C$9,2),ROUND($C$7-ROUND($C$7/$C$9,2)*($C$9-1),2)),$C$7)),"") | H19: =IF(15<=$C$9,IF($C$11<>"",$C$11,IFERROR(INDEX(tbAtalhos[Tipo],MATCH($C$6,tbAtalhos[Descrição],0))&"","Despesa")),"") | I19: =IF(15<=$C$9,IF($C$12<>"",$C$12,IFERROR(INDEX(tbAtalhos[Categoria],MATCH($C$6,tbAtalhos[Descrição],0))&"","")),"") | J19: =IF(15<=$C$9,IF(AND(15=1,$C$17="sim"),IF(IF($C$11<>"",$C$11,IFERROR(INDEX(tbAtalhos[Tipo],MATCH($C$6,tbAtalhos[Descrição],0))&"","Despesa"))="Receita","Recebido","Pago"),"Pendente"),"") | K19: =IF(15<=$C$9,IF($C$13<>"",$C$13,IFERROR(INDEX(tbAtalhos[Pote],MATCH($C$6,tbAtalhos[Descrição],0))&"","")),"") | L19: =IF(15<=$C$9,IF($C$14<>"",$C$14,IFERROR(INDEX(tbAtalhos[Quem],MATCH($C$6,tbAtalhos[Descrição],0))&"","")),"") | M19: =IF(15<=$C$9,IF($C$15<>"",$C$15,IFERROR(INDEX(tbAtalhos[Conta],MATCH($C$6,tbAtalhos[Descrição],0))&"","")),"") | N19: =IF(15<=$C$9,IF($C$16<>"",$C$16,IFERROR(INDEX(tbAtalhos[Forma de pagamento],MATCH($C$6,tbAtalhos[Descrição],0))&"","")),"") | O19: =IF(AND(15<=$C$9,$C$5="Parcelado"),"15/"&$C$9,"")
B20: Valor de cada parcela | C20: =IF($C$5="Repetir todo mês",$C$7,IF($C$8="Total da compra",ROUND($C$7/MAX(1,$C$9),2),$C$7)) | E20: =IF(16<=$C$9,DATE(YEAR($C$10),MONTH($C$10)+15,MIN(DAY($C$10),DAY(EOMONTH(DATE(YEAR($C$10),MONTH($C$10)+15,1),0)))),"") | F20: =IF(16<=$C$9,$C$6,"") | G20: =IF(16<=$C$9,IF($C$5="Repetir todo mês",$C$7,IF($C$8="Total da compra",IF(16<$C$9,ROUND($C$7/$C$9,2),ROUND($C$7-ROUND($C$7/$C$9,2)*($C$9-1),2)),$C$7)),"") | H20: =IF(16<=$C$9,IF($C$11<>"",$C$11,IFERROR(INDEX(tbAtalhos[Tipo],MATCH($C$6,tbAtalhos[Descrição],0))&"","Despesa")),"") | I20: =IF(16<=$C$9,IF($C$12<>"",$C$12,IFERROR(INDEX(tbAtalhos[Categoria],MATCH($C$6,tbAtalhos[Descrição],0))&"","")),"") | J20: =IF(16<=$C$9,IF(AND(16=1,$C$17="sim"),IF(IF($C$11<>"",$C$11,IFERROR(INDEX(tbAtalhos[Tipo],MATCH($C$6,tbAtalhos[Descrição],0))&"","Despesa"))="Receita","Recebido","Pago"),"Pendente"),"") | K20: =IF(16<=$C$9,IF($C$13<>"",$C$13,IFERROR(INDEX(tbAtalhos[Pote],MATCH($C$6,tbAtalhos[Descrição],0))&"","")),"") | L20: =IF(16<=$C$9,IF($C$14<>"",$C$14,IFERROR(INDEX(tbAtalhos[Quem],MATCH($C$6,tbAtalhos[Descrição],0))&"","")),"") | M20: =IF(16<=$C$9,IF($C$15<>"",$C$15,IFERROR(INDEX(tbAtalhos[Conta],MATCH($C$6,tbAtalhos[Descrição],0))&"","")),"") | N20: =IF(16<=$C$9,IF($C$16<>"",$C$16,IFERROR(INDEX(tbAtalhos[Forma de pagamento],MATCH($C$6,tbAtalhos[Descrição],0))&"","")),"") | O20: =IF(AND(16<=$C$9,$C$5="Parcelado"),"16/"&$C$9,"")
B21: Total | C21: =IF(AND($C$5="Parcelado",$C$8="Total da compra"),$C$7,IF($C$5="Repetir todo mês",$C$7,IF($C$8="Total da compra",ROUND($C$7/MAX(1,$C$9),2),$C$7))*$C$9) | E21: =IF(17<=$C$9,DATE(YEAR($C$10),MONTH($C$10)+16,MIN(DAY($C$10),DAY(EOMONTH(DATE(YEAR($C$10),MONTH($C$10)+16,1),0)))),"") | F21: =IF(17<=$C$9,$C$6,"") | G21: =IF(17<=$C$9,IF($C$5="Repetir todo mês",$C$7,IF($C$8="Total da compra",IF(17<$C$9,ROUND($C$7/$C$9,2),ROUND($C$7-ROUND($C$7/$C$9,2)*($C$9-1),2)),$C$7)),"") | H21: =IF(17<=$C$9,IF($C$11<>"",$C$11,IFERROR(INDEX(tbAtalhos[Tipo],MATCH($C$6,tbAtalhos[Descrição],0))&"","Despesa")),"") | I21: =IF(17<=$C$9,IF($C$12<>"",$C$12,IFERROR(INDEX(tbAtalhos[Categoria],MATCH($C$6,tbAtalhos[Descrição],0))&"","")),"") | J21: =IF(17<=$C$9,IF(AND(17=1,$C$17="sim"),IF(IF($C$11<>"",$C$11,IFERROR(INDEX(tbAtalhos[Tipo],MATCH($C$6,tbAtalhos[Descrição],0))&"","Despesa"))="Receita","Recebido","Pago"),"Pendente"),"") | K21: =IF(17<=$C$9,IF($C$13<>"",$C$13,IFERROR(INDEX(tbAtalhos[Pote],MATCH($C$6,tbAtalhos[Descrição],0))&"","")),"") | L21: =IF(17<=$C$9,IF($C$14<>"",$C$14,IFERROR(INDEX(tbAtalhos[Quem],MATCH($C$6,tbAtalhos[Descrição],0))&"","")),"") | M21: =IF(17<=$C$9,IF($C$15<>"",$C$15,IFERROR(INDEX(tbAtalhos[Conta],MATCH($C$6,tbAtalhos[Descrição],0))&"","")),"") | N21: =IF(17<=$C$9,IF($C$16<>"",$C$16,IFERROR(INDEX(tbAtalhos[Forma de pagamento],MATCH($C$6,tbAtalhos[Descrição],0))&"","")),"") | O21: =IF(AND(17<=$C$9,$C$5="Parcelado"),"17/"&$C$9,"")
B22: Última parcela em | C22: =IFERROR(DATE(YEAR($C$10),MONTH($C$10)+$C$9-1,1),"") | E22: =IF(18<=$C$9,DATE(YEAR($C$10),MONTH($C$10)+17,MIN(DAY($C$10),DAY(EOMONTH(DATE(YEAR($C$10),MONTH($C$10)+17,1),0)))),"") | F22: =IF(18<=$C$9,$C$6,"") | G22: =IF(18<=$C$9,IF($C$5="Repetir todo mês",$C$7,IF($C$8="Total da compra",IF(18<$C$9,ROUND($C$7/$C$9,2),ROUND($C$7-ROUND($C$7/$C$9,2)*($C$9-1),2)),$C$7)),"") | H22: =IF(18<=$C$9,IF($C$11<>"",$C$11,IFERROR(INDEX(tbAtalhos[Tipo],MATCH($C$6,tbAtalhos[Descrição],0))&"","Despesa")),"") | I22: =IF(18<=$C$9,IF($C$12<>"",$C$12,IFERROR(INDEX(tbAtalhos[Categoria],MATCH($C$6,tbAtalhos[Descrição],0))&"","")),"") | J22: =IF(18<=$C$9,IF(AND(18=1,$C$17="sim"),IF(IF($C$11<>"",$C$11,IFERROR(INDEX(tbAtalhos[Tipo],MATCH($C$6,tbAtalhos[Descrição],0))&"","Despesa"))="Receita","Recebido","Pago"),"Pendente"),"") | K22: =IF(18<=$C$9,IF($C$13<>"",$C$13,IFERROR(INDEX(tbAtalhos[Pote],MATCH($C$6,tbAtalhos[Descrição],0))&"","")),"") | L22: =IF(18<=$C$9,IF($C$14<>"",$C$14,IFERROR(INDEX(tbAtalhos[Quem],MATCH($C$6,tbAtalhos[Descrição],0))&"","")),"") | M22: =IF(18<=$C$9,IF($C$15<>"",$C$15,IFERROR(INDEX(tbAtalhos[Conta],MATCH($C$6,tbAtalhos[Descrição],0))&"","")),"") | N22: =IF(18<=$C$9,IF($C$16<>"",$C$16,IFERROR(INDEX(tbAtalhos[Forma de pagamento],MATCH($C$6,tbAtalhos[Descrição],0))&"","")),"") | O22: =IF(AND(18<=$C$9,$C$5="Parcelado"),"18/"&$C$9,"")
E23: =IF(19<=$C$9,DATE(YEAR($C$10),MONTH($C$10)+18,MIN(DAY($C$10),DAY(EOMONTH(DATE(YEAR($C$10),MONTH($C$10)+18,1),0)))),"") | F23: =IF(19<=$C$9,$C$6,"") | G23: =IF(19<=$C$9,IF($C$5="Repetir todo mês",$C$7,IF($C$8="Total da compra",IF(19<$C$9,ROUND($C$7/$C$9,2),ROUND($C$7-ROUND($C$7/$C$9,2)*($C$9-1),2)),$C$7)),"") | H23: =IF(19<=$C$9,IF($C$11<>"",$C$11,IFERROR(INDEX(tbAtalhos[Tipo],MATCH($C$6,tbAtalhos[Descrição],0))&"","Despesa")),"") | I23: =IF(19<=$C$9,IF($C$12<>"",$C$12,IFERROR(INDEX(tbAtalhos[Categoria],MATCH($C$6,tbAtalhos[Descrição],0))&"","")),"") | J23: =IF(19<=$C$9,IF(AND(19=1,$C$17="sim"),IF(IF($C$11<>"",$C$11,IFERROR(INDEX(tbAtalhos[Tipo],MATCH($C$6,tbAtalhos[Descrição],0))&"","Despesa"))="Receita","Recebido","Pago"),"Pendente"),"") | K23: =IF(19<=$C$9,IF($C$13<>"",$C$13,IFERROR(INDEX(tbAtalhos[Pote],MATCH($C$6,tbAtalhos[Descrição],0))&"","")),"") | L23: =IF(19<=$C$9,IF($C$14<>"",$C$14,IFERROR(INDEX(tbAtalhos[Quem],MATCH($C$6,tbAtalhos[Descrição],0))&"","")),"") | M23: =IF(19<=$C$9,IF($C$15<>"",$C$15,IFERROR(INDEX(tbAtalhos[Conta],MATCH($C$6,tbAtalhos[Descrição],0))&"","")),"") | N23: =IF(19<=$C$9,IF($C$16<>"",$C$16,IFERROR(INDEX(tbAtalhos[Forma de pagamento],MATCH($C$6,tbAtalhos[Descrição],0))&"","")),"") | O23: =IF(AND(19<=$C$9,$C$5="Parcelado"),"19/"&$C$9,"")
B24: =HYPERLINK("#Inicio!A1","⌂ Início") | E24: =IF(20<=$C$9,DATE(YEAR($C$10),MONTH($C$10)+19,MIN(DAY($C$10),DAY(EOMONTH(DATE(YEAR($C$10),MONTH($C$10)+19,1),0)))),"") | F24: =IF(20<=$C$9,$C$6,"") | G24: =IF(20<=$C$9,IF($C$5="Repetir todo mês",$C$7,IF($C$8="Total da compra",IF(20<$C$9,ROUND($C$7/$C$9,2),ROUND($C$7-ROUND($C$7/$C$9,2)*($C$9-1),2)),$C$7)),"") | H24: =IF(20<=$C$9,IF($C$11<>"",$C$11,IFERROR(INDEX(tbAtalhos[Tipo],MATCH($C$6,tbAtalhos[Descrição],0))&"","Despesa")),"") | I24: =IF(20<=$C$9,IF($C$12<>"",$C$12,IFERROR(INDEX(tbAtalhos[Categoria],MATCH($C$6,tbAtalhos[Descrição],0))&"","")),"") | J24: =IF(20<=$C$9,IF(AND(20=1,$C$17="sim"),IF(IF($C$11<>"",$C$11,IFERROR(INDEX(tbAtalhos[Tipo],MATCH($C$6,tbAtalhos[Descrição],0))&"","Despesa"))="Receita","Recebido","Pago"),"Pendente"),"") | K24: =IF(20<=$C$9,IF($C$13<>"",$C$13,IFERROR(INDEX(tbAtalhos[Pote],MATCH($C$6,tbAtalhos[Descrição],0))&"","")),"") | L24: =IF(20<=$C$9,IF($C$14<>"",$C$14,IFERROR(INDEX(tbAtalhos[Quem],MATCH($C$6,tbAtalhos[Descrição],0))&"","")),"") | M24: =IF(20<=$C$9,IF($C$15<>"",$C$15,IFERROR(INDEX(tbAtalhos[Conta],MATCH($C$6,tbAtalhos[Descrição],0))&"","")),"") | N24: =IF(20<=$C$9,IF($C$16<>"",$C$16,IFERROR(INDEX(tbAtalhos[Forma de pagamento],MATCH($C$6,tbAtalhos[Descrição],0))&"","")),"") | O24: =IF(AND(20<=$C$9,$C$5="Parcelado"),"20/"&$C$9,"")
E25: =IF(21<=$C$9,DATE(YEAR($C$10),MONTH($C$10)+20,MIN(DAY($C$10),DAY(EOMONTH(DATE(YEAR($C$10),MONTH($C$10)+20,1),0)))),"") | F25: =IF(21<=$C$9,$C$6,"") | G25: =IF(21<=$C$9,IF($C$5="Repetir todo mês",$C$7,IF($C$8="Total da compra",IF(21<$C$9,ROUND($C$7/$C$9,2),ROUND($C$7-ROUND($C$7/$C$9,2)*($C$9-1),2)),$C$7)),"") | H25: =IF(21<=$C$9,IF($C$11<>"",$C$11,IFERROR(INDEX(tbAtalhos[Tipo],MATCH($C$6,tbAtalhos[Descrição],0))&"","Despesa")),"") | I25: =IF(21<=$C$9,IF($C$12<>"",$C$12,IFERROR(INDEX(tbAtalhos[Categoria],MATCH($C$6,tbAtalhos[Descrição],0))&"","")),"") | J25: =IF(21<=$C$9,IF(AND(21=1,$C$17="sim"),IF(IF($C$11<>"",$C$11,IFERROR(INDEX(tbAtalhos[Tipo],MATCH($C$6,tbAtalhos[Descrição],0))&"","Despesa"))="Receita","Recebido","Pago"),"Pendente"),"") | K25: =IF(21<=$C$9,IF($C$13<>"",$C$13,IFERROR(INDEX(tbAtalhos[Pote],MATCH($C$6,tbAtalhos[Descrição],0))&"","")),"") | L25: =IF(21<=$C$9,IF($C$14<>"",$C$14,IFERROR(INDEX(tbAtalhos[Quem],MATCH($C$6,tbAtalhos[Descrição],0))&"","")),"") | M25: =IF(21<=$C$9,IF($C$15<>"",$C$15,IFERROR(INDEX(tbAtalhos[Conta],MATCH($C$6,tbAtalhos[Descrição],0))&"","")),"") | N25: =IF(21<=$C$9,IF($C$16<>"",$C$16,IFERROR(INDEX(tbAtalhos[Forma de pagamento],MATCH($C$6,tbAtalhos[Descrição],0))&"","")),"") | O25: =IF(AND(21<=$C$9,$C$5="Parcelado"),"21/"&$C$9,"")
E26: =IF(22<=$C$9,DATE(YEAR($C$10),MONTH($C$10)+21,MIN(DAY($C$10),DAY(EOMONTH(DATE(YEAR($C$10),MONTH($C$10)+21,1),0)))),"") | F26: =IF(22<=$C$9,$C$6,"") | G26: =IF(22<=$C$9,IF($C$5="Repetir todo mês",$C$7,IF($C$8="Total da compra",IF(22<$C$9,ROUND($C$7/$C$9,2),ROUND($C$7-ROUND($C$7/$C$9,2)*($C$9-1),2)),$C$7)),"") | H26: =IF(22<=$C$9,IF($C$11<>"",$C$11,IFERROR(INDEX(tbAtalhos[Tipo],MATCH($C$6,tbAtalhos[Descrição],0))&"","Despesa")),"") | I26: =IF(22<=$C$9,IF($C$12<>"",$C$12,IFERROR(INDEX(tbAtalhos[Categoria],MATCH($C$6,tbAtalhos[Descrição],0))&"","")),"") | J26: =IF(22<=$C$9,IF(AND(22=1,$C$17="sim"),IF(IF($C$11<>"",$C$11,IFERROR(INDEX(tbAtalhos[Tipo],MATCH($C$6,tbAtalhos[Descrição],0))&"","Despesa"))="Receita","Recebido","Pago"),"Pendente"),"") | K26: =IF(22<=$C$9,IF($C$13<>"",$C$13,IFERROR(INDEX(tbAtalhos[Pote],MATCH($C$6,tbAtalhos[Descrição],0))&"","")),"") | L26: =IF(22<=$C$9,IF($C$14<>"",$C$14,IFERROR(INDEX(tbAtalhos[Quem],MATCH($C$6,tbAtalhos[Descrição],0))&"","")),"") | M26: =IF(22<=$C$9,IF($C$15<>"",$C$15,IFERROR(INDEX(tbAtalhos[Conta],MATCH($C$6,tbAtalhos[Descrição],0))&"","")),"") | N26: =IF(22<=$C$9,IF($C$16<>"",$C$16,IFERROR(INDEX(tbAtalhos[Forma de pagamento],MATCH($C$6,tbAtalhos[Descrição],0))&"","")),"") | O26: =IF(AND(22<=$C$9,$C$5="Parcelado"),"22/"&$C$9,"")
E27: =IF(23<=$C$9,DATE(YEAR($C$10),MONTH($C$10)+22,MIN(DAY($C$10),DAY(EOMONTH(DATE(YEAR($C$10),MONTH($C$10)+22,1),0)))),"") | F27: =IF(23<=$C$9,$C$6,"") | G27: =IF(23<=$C$9,IF($C$5="Repetir todo mês",$C$7,IF($C$8="Total da compra",IF(23<$C$9,ROUND($C$7/$C$9,2),ROUND($C$7-ROUND($C$7/$C$9,2)*($C$9-1),2)),$C$7)),"") | H27: =IF(23<=$C$9,IF($C$11<>"",$C$11,IFERROR(INDEX(tbAtalhos[Tipo],MATCH($C$6,tbAtalhos[Descrição],0))&"","Despesa")),"") | I27: =IF(23<=$C$9,IF($C$12<>"",$C$12,IFERROR(INDEX(tbAtalhos[Categoria],MATCH($C$6,tbAtalhos[Descrição],0))&"","")),"") | J27: =IF(23<=$C$9,IF(AND(23=1,$C$17="sim"),IF(IF($C$11<>"",$C$11,IFERROR(INDEX(tbAtalhos[Tipo],MATCH($C$6,tbAtalhos[Descrição],0))&"","Despesa"))="Receita","Recebido","Pago"),"Pendente"),"") | K27: =IF(23<=$C$9,IF($C$13<>"",$C$13,IFERROR(INDEX(tbAtalhos[Pote],MATCH($C$6,tbAtalhos[Descrição],0))&"","")),"") | L27: =IF(23<=$C$9,IF($C$14<>"",$C$14,IFERROR(INDEX(tbAtalhos[Quem],MATCH($C$6,tbAtalhos[Descrição],0))&"","")),"") | M27: =IF(23<=$C$9,IF($C$15<>"",$C$15,IFERROR(INDEX(tbAtalhos[Conta],MATCH($C$6,tbAtalhos[Descrição],0))&"","")),"") | N27: =IF(23<=$C$9,IF($C$16<>"",$C$16,IFERROR(INDEX(tbAtalhos[Forma de pagamento],MATCH($C$6,tbAtalhos[Descrição],0))&"","")),"") | O27: =IF(AND(23<=$C$9,$C$5="Parcelado"),"23/"&$C$9,"")
E28: =IF(24<=$C$9,DATE(YEAR($C$10),MONTH($C$10)+23,MIN(DAY($C$10),DAY(EOMONTH(DATE(YEAR($C$10),MONTH($C$10)+23,1),0)))),"") | F28: =IF(24<=$C$9,$C$6,"") | G28: =IF(24<=$C$9,IF($C$5="Repetir todo mês",$C$7,IF($C$8="Total da compra",IF(24<$C$9,ROUND($C$7/$C$9,2),ROUND($C$7-ROUND($C$7/$C$9,2)*($C$9-1),2)),$C$7)),"") | H28: =IF(24<=$C$9,IF($C$11<>"",$C$11,IFERROR(INDEX(tbAtalhos[Tipo],MATCH($C$6,tbAtalhos[Descrição],0))&"","Despesa")),"") | I28: =IF(24<=$C$9,IF($C$12<>"",$C$12,IFERROR(INDEX(tbAtalhos[Categoria],MATCH($C$6,tbAtalhos[Descrição],0))&"","")),"") | J28: =IF(24<=$C$9,IF(AND(24=1,$C$17="sim"),IF(IF($C$11<>"",$C$11,IFERROR(INDEX(tbAtalhos[Tipo],MATCH($C$6,tbAtalhos[Descrição],0))&"","Despesa"))="Receita","Recebido","Pago"),"Pendente"),"") | K28: =IF(24<=$C$9,IF($C$13<>"",$C$13,IFERROR(INDEX(tbAtalhos[Pote],MATCH($C$6,tbAtalhos[Descrição],0))&"","")),"") | L28: =IF(24<=$C$9,IF($C$14<>"",$C$14,IFERROR(INDEX(tbAtalhos[Quem],MATCH($C$6,tbAtalhos[Descrição],0))&"","")),"") | M28: =IF(24<=$C$9,IF($C$15<>"",$C$15,IFERROR(INDEX(tbAtalhos[Conta],MATCH($C$6,tbAtalhos[Descrição],0))&"","")),"") | N28: =IF(24<=$C$9,IF($C$16<>"",$C$16,IFERROR(INDEX(tbAtalhos[Forma de pagamento],MATCH($C$6,tbAtalhos[Descrição],0))&"","")),"") | O28: =IF(AND(24<=$C$9,$C$5="Parcelado"),"24/"&$C$9,"")
E29: =IF(25<=$C$9,DATE(YEAR($C$10),MONTH($C$10)+24,MIN(DAY($C$10),DAY(EOMONTH(DATE(YEAR($C$10),MONTH($C$10)+24,1),0)))),"") | F29: =IF(25<=$C$9,$C$6,"") | G29: =IF(25<=$C$9,IF($C$5="Repetir todo mês",$C$7,IF($C$8="Total da compra",IF(25<$C$9,ROUND($C$7/$C$9,2),ROUND($C$7-ROUND($C$7/$C$9,2)*($C$9-1),2)),$C$7)),"") | H29: =IF(25<=$C$9,IF($C$11<>"",$C$11,IFERROR(INDEX(tbAtalhos[Tipo],MATCH($C$6,tbAtalhos[Descrição],0))&"","Despesa")),"") | I29: =IF(25<=$C$9,IF($C$12<>"",$C$12,IFERROR(INDEX(tbAtalhos[Categoria],MATCH($C$6,tbAtalhos[Descrição],0))&"","")),"") | J29: =IF(25<=$C$9,IF(AND(25=1,$C$17="sim"),IF(IF($C$11<>"",$C$11,IFERROR(INDEX(tbAtalhos[Tipo],MATCH($C$6,tbAtalhos[Descrição],0))&"","Despesa"))="Receita","Recebido","Pago"),"Pendente"),"") | K29: =IF(25<=$C$9,IF($C$13<>"",$C$13,IFERROR(INDEX(tbAtalhos[Pote],MATCH($C$6,tbAtalhos[Descrição],0))&"","")),"") | L29: =IF(25<=$C$9,IF($C$14<>"",$C$14,IFERROR(INDEX(tbAtalhos[Quem],MATCH($C$6,tbAtalhos[Descrição],0))&"","")),"") | M29: =IF(25<=$C$9,IF($C$15<>"",$C$15,IFERROR(INDEX(tbAtalhos[Conta],MATCH($C$6,tbAtalhos[Descrição],0))&"","")),"") | N29: =IF(25<=$C$9,IF($C$16<>"",$C$16,IFERROR(INDEX(tbAtalhos[Forma de pagamento],MATCH($C$6,tbAtalhos[Descrição],0))&"","")),"") | O29: =IF(AND(25<=$C$9,$C$5="Parcelado"),"25/"&$C$9,"")
E30: =IF(26<=$C$9,DATE(YEAR($C$10),MONTH($C$10)+25,MIN(DAY($C$10),DAY(EOMONTH(DATE(YEAR($C$10),MONTH($C$10)+25,1),0)))),"") | F30: =IF(26<=$C$9,$C$6,"") | G30: =IF(26<=$C$9,IF($C$5="Repetir todo mês",$C$7,IF($C$8="Total da compra",IF(26<$C$9,ROUND($C$7/$C$9,2),ROUND($C$7-ROUND($C$7/$C$9,2)*($C$9-1),2)),$C$7)),"") | H30: =IF(26<=$C$9,IF($C$11<>"",$C$11,IFERROR(INDEX(tbAtalhos[Tipo],MATCH($C$6,tbAtalhos[Descrição],0))&"","Despesa")),"") | I30: =IF(26<=$C$9,IF($C$12<>"",$C$12,IFERROR(INDEX(tbAtalhos[Categoria],MATCH($C$6,tbAtalhos[Descrição],0))&"","")),"") | J30: =IF(26<=$C$9,IF(AND(26=1,$C$17="sim"),IF(IF($C$11<>"",$C$11,IFERROR(INDEX(tbAtalhos[Tipo],MATCH($C$6,tbAtalhos[Descrição],0))&"","Despesa"))="Receita","Recebido","Pago"),"Pendente"),"") | K30: =IF(26<=$C$9,IF($C$13<>"",$C$13,IFERROR(INDEX(tbAtalhos[Pote],MATCH($C$6,tbAtalhos[Descrição],0))&"","")),"") | L30: =IF(26<=$C$9,IF($C$14<>"",$C$14,IFERROR(INDEX(tbAtalhos[Quem],MATCH($C$6,tbAtalhos[Descrição],0))&"","")),"") | M30: =IF(26<=$C$9,IF($C$15<>"",$C$15,IFERROR(INDEX(tbAtalhos[Conta],MATCH($C$6,tbAtalhos[Descrição],0))&"","")),"") | N30: =IF(26<=$C$9,IF($C$16<>"",$C$16,IFERROR(INDEX(tbAtalhos[Forma de pagamento],MATCH($C$6,tbAtalhos[Descrição],0))&"","")),"") | O30: =IF(AND(26<=$C$9,$C$5="Parcelado"),"26/"&$C$9,"")
E31: =IF(27<=$C$9,DATE(YEAR($C$10),MONTH($C$10)+26,MIN(DAY($C$10),DAY(EOMONTH(DATE(YEAR($C$10),MONTH($C$10)+26,1),0)))),"") | F31: =IF(27<=$C$9,$C$6,"") | G31: =IF(27<=$C$9,IF($C$5="Repetir todo mês",$C$7,IF($C$8="Total da compra",IF(27<$C$9,ROUND($C$7/$C$9,2),ROUND($C$7-ROUND($C$7/$C$9,2)*($C$9-1),2)),$C$7)),"") | H31: =IF(27<=$C$9,IF($C$11<>"",$C$11,IFERROR(INDEX(tbAtalhos[Tipo],MATCH($C$6,tbAtalhos[Descrição],0))&"","Despesa")),"") | I31: =IF(27<=$C$9,IF($C$12<>"",$C$12,IFERROR(INDEX(tbAtalhos[Categoria],MATCH($C$6,tbAtalhos[Descrição],0))&"","")),"") | J31: =IF(27<=$C$9,IF(AND(27=1,$C$17="sim"),IF(IF($C$11<>"",$C$11,IFERROR(INDEX(tbAtalhos[Tipo],MATCH($C$6,tbAtalhos[Descrição],0))&"","Despesa"))="Receita","Recebido","Pago"),"Pendente"),"") | K31: =IF(27<=$C$9,IF($C$13<>"",$C$13,IFERROR(INDEX(tbAtalhos[Pote],MATCH($C$6,tbAtalhos[Descrição],0))&"","")),"") | L31: =IF(27<=$C$9,IF($C$14<>"",$C$14,IFERROR(INDEX(tbAtalhos[Quem],MATCH($C$6,tbAtalhos[Descrição],0))&"","")),"") | M31: =IF(27<=$C$9,IF($C$15<>"",$C$15,IFERROR(INDEX(tbAtalhos[Conta],MATCH($C$6,tbAtalhos[Descrição],0))&"","")),"") | N31: =IF(27<=$C$9,IF($C$16<>"",$C$16,IFERROR(INDEX(tbAtalhos[Forma de pagamento],MATCH($C$6,tbAtalhos[Descrição],0))&"","")),"") | O31: =IF(AND(27<=$C$9,$C$5="Parcelado"),"27/"&$C$9,"")
E32: =IF(28<=$C$9,DATE(YEAR($C$10),MONTH($C$10)+27,MIN(DAY($C$10),DAY(EOMONTH(DATE(YEAR($C$10),MONTH($C$10)+27,1),0)))),"") | F32: =IF(28<=$C$9,$C$6,"") | G32: =IF(28<=$C$9,IF($C$5="Repetir todo mês",$C$7,IF($C$8="Total da compra",IF(28<$C$9,ROUND($C$7/$C$9,2),ROUND($C$7-ROUND($C$7/$C$9,2)*($C$9-1),2)),$C$7)),"") | H32: =IF(28<=$C$9,IF($C$11<>"",$C$11,IFERROR(INDEX(tbAtalhos[Tipo],MATCH($C$6,tbAtalhos[Descrição],0))&"","Despesa")),"") | I32: =IF(28<=$C$9,IF($C$12<>"",$C$12,IFERROR(INDEX(tbAtalhos[Categoria],MATCH($C$6,tbAtalhos[Descrição],0))&"","")),"") | J32: =IF(28<=$C$9,IF(AND(28=1,$C$17="sim"),IF(IF($C$11<>"",$C$11,IFERROR(INDEX(tbAtalhos[Tipo],MATCH($C$6,tbAtalhos[Descrição],0))&"","Despesa"))="Receita","Recebido","Pago"),"Pendente"),"") | K32: =IF(28<=$C$9,IF($C$13<>"",$C$13,IFERROR(INDEX(tbAtalhos[Pote],MATCH($C$6,tbAtalhos[Descrição],0))&"","")),"") | L32: =IF(28<=$C$9,IF($C$14<>"",$C$14,IFERROR(INDEX(tbAtalhos[Quem],MATCH($C$6,tbAtalhos[Descrição],0))&"","")),"") | M32: =IF(28<=$C$9,IF($C$15<>"",$C$15,IFERROR(INDEX(tbAtalhos[Conta],MATCH($C$6,tbAtalhos[Descrição],0))&"","")),"") | N32: =IF(28<=$C$9,IF($C$16<>"",$C$16,IFERROR(INDEX(tbAtalhos[Forma de pagamento],MATCH($C$6,tbAtalhos[Descrição],0))&"","")),"") | O32: =IF(AND(28<=$C$9,$C$5="Parcelado"),"28/"&$C$9,"")
E33: =IF(29<=$C$9,DATE(YEAR($C$10),MONTH($C$10)+28,MIN(DAY($C$10),DAY(EOMONTH(DATE(YEAR($C$10),MONTH($C$10)+28,1),0)))),"") | F33: =IF(29<=$C$9,$C$6,"") | G33: =IF(29<=$C$9,IF($C$5="Repetir todo mês",$C$7,IF($C$8="Total da compra",IF(29<$C$9,ROUND($C$7/$C$9,2),ROUND($C$7-ROUND($C$7/$C$9,2)*($C$9-1),2)),$C$7)),"") | H33: =IF(29<=$C$9,IF($C$11<>"",$C$11,IFERROR(INDEX(tbAtalhos[Tipo],MATCH($C$6,tbAtalhos[Descrição],0))&"","Despesa")),"") | I33: =IF(29<=$C$9,IF($C$12<>"",$C$12,IFERROR(INDEX(tbAtalhos[Categoria],MATCH($C$6,tbAtalhos[Descrição],0))&"","")),"") | J33: =IF(29<=$C$9,IF(AND(29=1,$C$17="sim"),IF(IF($C$11<>"",$C$11,IFERROR(INDEX(tbAtalhos[Tipo],MATCH($C$6,tbAtalhos[Descrição],0))&"","Despesa"))="Receita","Recebido","Pago"),"Pendente"),"") | K33: =IF(29<=$C$9,IF($C$13<>"",$C$13,IFERROR(INDEX(tbAtalhos[Pote],MATCH($C$6,tbAtalhos[Descrição],0))&"","")),"") | L33: =IF(29<=$C$9,IF($C$14<>"",$C$14,IFERROR(INDEX(tbAtalhos[Quem],MATCH($C$6,tbAtalhos[Descrição],0))&"","")),"") | M33: =IF(29<=$C$9,IF($C$15<>"",$C$15,IFERROR(INDEX(tbAtalhos[Conta],MATCH($C$6,tbAtalhos[Descrição],0))&"","")),"") | N33: =IF(29<=$C$9,IF($C$16<>"",$C$16,IFERROR(INDEX(tbAtalhos[Forma de pagamento],MATCH($C$6,tbAtalhos[Descrição],0))&"","")),"") | O33: =IF(AND(29<=$C$9,$C$5="Parcelado"),"29/"&$C$9,"")
E34: =IF(30<=$C$9,DATE(YEAR($C$10),MONTH($C$10)+29,MIN(DAY($C$10),DAY(EOMONTH(DATE(YEAR($C$10),MONTH($C$10)+29,1),0)))),"") | F34: =IF(30<=$C$9,$C$6,"") | G34: =IF(30<=$C$9,IF($C$5="Repetir todo mês",$C$7,IF($C$8="Total da compra",IF(30<$C$9,ROUND($C$7/$C$9,2),ROUND($C$7-ROUND($C$7/$C$9,2)*($C$9-1),2)),$C$7)),"") | H34: =IF(30<=$C$9,IF($C$11<>"",$C$11,IFERROR(INDEX(tbAtalhos[Tipo],MATCH($C$6,tbAtalhos[Descrição],0))&"","Despesa")),"") | I34: =IF(30<=$C$9,IF($C$12<>"",$C$12,IFERROR(INDEX(tbAtalhos[Categoria],MATCH($C$6,tbAtalhos[Descrição],0))&"","")),"") | J34: =IF(30<=$C$9,IF(AND(30=1,$C$17="sim"),IF(IF($C$11<>"",$C$11,IFERROR(INDEX(tbAtalhos[Tipo],MATCH($C$6,tbAtalhos[Descrição],0))&"","Despesa"))="Receita","Recebido","Pago"),"Pendente"),"") | K34: =IF(30<=$C$9,IF($C$13<>"",$C$13,IFERROR(INDEX(tbAtalhos[Pote],MATCH($C$6,tbAtalhos[Descrição],0))&"","")),"") | L34: =IF(30<=$C$9,IF($C$14<>"",$C$14,IFERROR(INDEX(tbAtalhos[Quem],MATCH($C$6,tbAtalhos[Descrição],0))&"","")),"") | M34: =IF(30<=$C$9,IF($C$15<>"",$C$15,IFERROR(INDEX(tbAtalhos[Conta],MATCH($C$6,tbAtalhos[Descrição],0))&"","")),"") | N34: =IF(30<=$C$9,IF($C$16<>"",$C$16,IFERROR(INDEX(tbAtalhos[Forma de pagamento],MATCH($C$6,tbAtalhos[Descrição],0))&"","")),"") | O34: =IF(AND(30<=$C$9,$C$5="Parcelado"),"30/"&$C$9,"")
E35: =IF(31<=$C$9,DATE(YEAR($C$10),MONTH($C$10)+30,MIN(DAY($C$10),DAY(EOMONTH(DATE(YEAR($C$10),MONTH($C$10)+30,1),0)))),"") | F35: =IF(31<=$C$9,$C$6,"") | G35: =IF(31<=$C$9,IF($C$5="Repetir todo mês",$C$7,IF($C$8="Total da compra",IF(31<$C$9,ROUND($C$7/$C$9,2),ROUND($C$7-ROUND($C$7/$C$9,2)*($C$9-1),2)),$C$7)),"") | H35: =IF(31<=$C$9,IF($C$11<>"",$C$11,IFERROR(INDEX(tbAtalhos[Tipo],MATCH($C$6,tbAtalhos[Descrição],0))&"","Despesa")),"") | I35: =IF(31<=$C$9,IF($C$12<>"",$C$12,IFERROR(INDEX(tbAtalhos[Categoria],MATCH($C$6,tbAtalhos[Descrição],0))&"","")),"") | J35: =IF(31<=$C$9,IF(AND(31=1,$C$17="sim"),IF(IF($C$11<>"",$C$11,IFERROR(INDEX(tbAtalhos[Tipo],MATCH($C$6,tbAtalhos[Descrição],0))&"","Despesa"))="Receita","Recebido","Pago"),"Pendente"),"") | K35: =IF(31<=$C$9,IF($C$13<>"",$C$13,IFERROR(INDEX(tbAtalhos[Pote],MATCH($C$6,tbAtalhos[Descrição],0))&"","")),"") | L35: =IF(31<=$C$9,IF($C$14<>"",$C$14,IFERROR(INDEX(tbAtalhos[Quem],MATCH($C$6,tbAtalhos[Descrição],0))&"","")),"") | M35: =IF(31<=$C$9,IF($C$15<>"",$C$15,IFERROR(INDEX(tbAtalhos[Conta],MATCH($C$6,tbAtalhos[Descrição],0))&"","")),"") | N35: =IF(31<=$C$9,IF($C$16<>"",$C$16,IFERROR(INDEX(tbAtalhos[Forma de pagamento],MATCH($C$6,tbAtalhos[Descrição],0))&"","")),"") | O35: =IF(AND(31<=$C$9,$C$5="Parcelado"),"31/"&$C$9,"")
E36: =IF(32<=$C$9,DATE(YEAR($C$10),MONTH($C$10)+31,MIN(DAY($C$10),DAY(EOMONTH(DATE(YEAR($C$10),MONTH($C$10)+31,1),0)))),"") | F36: =IF(32<=$C$9,$C$6,"") | G36: =IF(32<=$C$9,IF($C$5="Repetir todo mês",$C$7,IF($C$8="Total da compra",IF(32<$C$9,ROUND($C$7/$C$9,2),ROUND($C$7-ROUND($C$7/$C$9,2)*($C$9-1),2)),$C$7)),"") | H36: =IF(32<=$C$9,IF($C$11<>"",$C$11,IFERROR(INDEX(tbAtalhos[Tipo],MATCH($C$6,tbAtalhos[Descrição],0))&"","Despesa")),"") | I36: =IF(32<=$C$9,IF($C$12<>"",$C$12,IFERROR(INDEX(tbAtalhos[Categoria],MATCH($C$6,tbAtalhos[Descrição],0))&"","")),"") | J36: =IF(32<=$C$9,IF(AND(32=1,$C$17="sim"),IF(IF($C$11<>"",$C$11,IFERROR(INDEX(tbAtalhos[Tipo],MATCH($C$6,tbAtalhos[Descrição],0))&"","Despesa"))="Receita","Recebido","Pago"),"Pendente"),"") | K36: =IF(32<=$C$9,IF($C$13<>"",$C$13,IFERROR(INDEX(tbAtalhos[Pote],MATCH($C$6,tbAtalhos[Descrição],0))&"","")),"") | L36: =IF(32<=$C$9,IF($C$14<>"",$C$14,IFERROR(INDEX(tbAtalhos[Quem],MATCH($C$6,tbAtalhos[Descrição],0))&"","")),"") | M36: =IF(32<=$C$9,IF($C$15<>"",$C$15,IFERROR(INDEX(tbAtalhos[Conta],MATCH($C$6,tbAtalhos[Descrição],0))&"","")),"") | N36: =IF(32<=$C$9,IF($C$16<>"",$C$16,IFERROR(INDEX(tbAtalhos[Forma de pagamento],MATCH($C$6,tbAtalhos[Descrição],0))&"","")),"") | O36: =IF(AND(32<=$C$9,$C$5="Parcelado"),"32/"&$C$9,"")
E37: =IF(33<=$C$9,DATE(YEAR($C$10),MONTH($C$10)+32,MIN(DAY($C$10),DAY(EOMONTH(DATE(YEAR($C$10),MONTH($C$10)+32,1),0)))),"") | F37: =IF(33<=$C$9,$C$6,"") | G37: =IF(33<=$C$9,IF($C$5="Repetir todo mês",$C$7,IF($C$8="Total da compra",IF(33<$C$9,ROUND($C$7/$C$9,2),ROUND($C$7-ROUND($C$7/$C$9,2)*($C$9-1),2)),$C$7)),"") | H37: =IF(33<=$C$9,IF($C$11<>"",$C$11,IFERROR(INDEX(tbAtalhos[Tipo],MATCH($C$6,tbAtalhos[Descrição],0))&"","Despesa")),"") | I37: =IF(33<=$C$9,IF($C$12<>"",$C$12,IFERROR(INDEX(tbAtalhos[Categoria],MATCH($C$6,tbAtalhos[Descrição],0))&"","")),"") | J37: =IF(33<=$C$9,IF(AND(33=1,$C$17="sim"),IF(IF($C$11<>"",$C$11,IFERROR(INDEX(tbAtalhos[Tipo],MATCH($C$6,tbAtalhos[Descrição],0))&"","Despesa"))="Receita","Recebido","Pago"),"Pendente"),"") | K37: =IF(33<=$C$9,IF($C$13<>"",$C$13,IFERROR(INDEX(tbAtalhos[Pote],MATCH($C$6,tbAtalhos[Descrição],0))&"","")),"") | L37: =IF(33<=$C$9,IF($C$14<>"",$C$14,IFERROR(INDEX(tbAtalhos[Quem],MATCH($C$6,tbAtalhos[Descrição],0))&"","")),"") | M37: =IF(33<=$C$9,IF($C$15<>"",$C$15,IFERROR(INDEX(tbAtalhos[Conta],MATCH($C$6,tbAtalhos[Descrição],0))&"","")),"") | N37: =IF(33<=$C$9,IF($C$16<>"",$C$16,IFERROR(INDEX(tbAtalhos[Forma de pagamento],MATCH($C$6,tbAtalhos[Descrição],0))&"","")),"") | O37: =IF(AND(33<=$C$9,$C$5="Parcelado"),"33/"&$C$9,"")
E38: =IF(34<=$C$9,DATE(YEAR($C$10),MONTH($C$10)+33,MIN(DAY($C$10),DAY(EOMONTH(DATE(YEAR($C$10),MONTH($C$10)+33,1),0)))),"") | F38: =IF(34<=$C$9,$C$6,"") | G38: =IF(34<=$C$9,IF($C$5="Repetir todo mês",$C$7,IF($C$8="Total da compra",IF(34<$C$9,ROUND($C$7/$C$9,2),ROUND($C$7-ROUND($C$7/$C$9,2)*($C$9-1),2)),$C$7)),"") | H38: =IF(34<=$C$9,IF($C$11<>"",$C$11,IFERROR(INDEX(tbAtalhos[Tipo],MATCH($C$6,tbAtalhos[Descrição],0))&"","Despesa")),"") | I38: =IF(34<=$C$9,IF($C$12<>"",$C$12,IFERROR(INDEX(tbAtalhos[Categoria],MATCH($C$6,tbAtalhos[Descrição],0))&"","")),"") | J38: =IF(34<=$C$9,IF(AND(34=1,$C$17="sim"),IF(IF($C$11<>"",$C$11,IFERROR(INDEX(tbAtalhos[Tipo],MATCH($C$6,tbAtalhos[Descrição],0))&"","Despesa"))="Receita","Recebido","Pago"),"Pendente"),"") | K38: =IF(34<=$C$9,IF($C$13<>"",$C$13,IFERROR(INDEX(tbAtalhos[Pote],MATCH($C$6,tbAtalhos[Descrição],0))&"","")),"") | L38: =IF(34<=$C$9,IF($C$14<>"",$C$14,IFERROR(INDEX(tbAtalhos[Quem],MATCH($C$6,tbAtalhos[Descrição],0))&"","")),"") | M38: =IF(34<=$C$9,IF($C$15<>"",$C$15,IFERROR(INDEX(tbAtalhos[Conta],MATCH($C$6,tbAtalhos[Descrição],0))&"","")),"") | N38: =IF(34<=$C$9,IF($C$16<>"",$C$16,IFERROR(INDEX(tbAtalhos[Forma de pagamento],MATCH($C$6,tbAtalhos[Descrição],0))&"","")),"") | O38: =IF(AND(34<=$C$9,$C$5="Parcelado"),"34/"&$C$9,"")
E39: =IF(35<=$C$9,DATE(YEAR($C$10),MONTH($C$10)+34,MIN(DAY($C$10),DAY(EOMONTH(DATE(YEAR($C$10),MONTH($C$10)+34,1),0)))),"") | F39: =IF(35<=$C$9,$C$6,"") | G39: =IF(35<=$C$9,IF($C$5="Repetir todo mês",$C$7,IF($C$8="Total da compra",IF(35<$C$9,ROUND($C$7/$C$9,2),ROUND($C$7-ROUND($C$7/$C$9,2)*($C$9-1),2)),$C$7)),"") | H39: =IF(35<=$C$9,IF($C$11<>"",$C$11,IFERROR(INDEX(tbAtalhos[Tipo],MATCH($C$6,tbAtalhos[Descrição],0))&"","Despesa")),"") | I39: =IF(35<=$C$9,IF($C$12<>"",$C$12,IFERROR(INDEX(tbAtalhos[Categoria],MATCH($C$6,tbAtalhos[Descrição],0))&"","")),"") | J39: =IF(35<=$C$9,IF(AND(35=1,$C$17="sim"),IF(IF($C$11<>"",$C$11,IFERROR(INDEX(tbAtalhos[Tipo],MATCH($C$6,tbAtalhos[Descrição],0))&"","Despesa"))="Receita","Recebido","Pago"),"Pendente"),"") | K39: =IF(35<=$C$9,IF($C$13<>"",$C$13,IFERROR(INDEX(tbAtalhos[Pote],MATCH($C$6,tbAtalhos[Descrição],0))&"","")),"") | L39: =IF(35<=$C$9,IF($C$14<>"",$C$14,IFERROR(INDEX(tbAtalhos[Quem],MATCH($C$6,tbAtalhos[Descrição],0))&"","")),"") | M39: =IF(35<=$C$9,IF($C$15<>"",$C$15,IFERROR(INDEX(tbAtalhos[Conta],MATCH($C$6,tbAtalhos[Descrição],0))&"","")),"") | N39: =IF(35<=$C$9,IF($C$16<>"",$C$16,IFERROR(INDEX(tbAtalhos[Forma de pagamento],MATCH($C$6,tbAtalhos[Descrição],0))&"","")),"") | O39: =IF(AND(35<=$C$9,$C$5="Parcelado"),"35/"&$C$9,"")
E40: =IF(36<=$C$9,DATE(YEAR($C$10),MONTH($C$10)+35,MIN(DAY($C$10),DAY(EOMONTH(DATE(YEAR($C$10),MONTH($C$10)+35,1),0)))),"") | F40: =IF(36<=$C$9,$C$6,"") | G40: =IF(36<=$C$9,IF($C$5="Repetir todo mês",$C$7,IF($C$8="Total da compra",IF(36<$C$9,ROUND($C$7/$C$9,2),ROUND($C$7-ROUND($C$7/$C$9,2)*($C$9-1),2)),$C$7)),"") | H40: =IF(36<=$C$9,IF($C$11<>"",$C$11,IFERROR(INDEX(tbAtalhos[Tipo],MATCH($C$6,tbAtalhos[Descrição],0))&"","Despesa")),"") | I40: =IF(36<=$C$9,IF($C$12<>"",$C$12,IFERROR(INDEX(tbAtalhos[Categoria],MATCH($C$6,tbAtalhos[Descrição],0))&"","")),"") | J40: =IF(36<=$C$9,IF(AND(36=1,$C$17="sim"),IF(IF($C$11<>"",$C$11,IFERROR(INDEX(tbAtalhos[Tipo],MATCH($C$6,tbAtalhos[Descrição],0))&"","Despesa"))="Receita","Recebido","Pago"),"Pendente"),"") | K40: =IF(36<=$C$9,IF($C$13<>"",$C$13,IFERROR(INDEX(tbAtalhos[Pote],MATCH($C$6,tbAtalhos[Descrição],0))&"","")),"") | L40: =IF(36<=$C$9,IF($C$14<>"",$C$14,IFERROR(INDEX(tbAtalhos[Quem],MATCH($C$6,tbAtalhos[Descrição],0))&"","")),"") | M40: =IF(36<=$C$9,IF($C$15<>"",$C$15,IFERROR(INDEX(tbAtalhos[Conta],MATCH($C$6,tbAtalhos[Descrição],0))&"","")),"") | N40: =IF(36<=$C$9,IF($C$16<>"",$C$16,IFERROR(INDEX(tbAtalhos[Forma de pagamento],MATCH($C$6,tbAtalhos[Descrição],0))&"","")),"") | O40: =IF(AND(36<=$C$9,$C$5="Parcelado"),"36/"&$C$9,"")
E41: =IF(37<=$C$9,DATE(YEAR($C$10),MONTH($C$10)+36,MIN(DAY($C$10),DAY(EOMONTH(DATE(YEAR($C$10),MONTH($C$10)+36,1),0)))),"") | F41: =IF(37<=$C$9,$C$6,"") | G41: =IF(37<=$C$9,IF($C$5="Repetir todo mês",$C$7,IF($C$8="Total da compra",IF(37<$C$9,ROUND($C$7/$C$9,2),ROUND($C$7-ROUND($C$7/$C$9,2)*($C$9-1),2)),$C$7)),"") | H41: =IF(37<=$C$9,IF($C$11<>"",$C$11,IFERROR(INDEX(tbAtalhos[Tipo],MATCH($C$6,tbAtalhos[Descrição],0))&"","Despesa")),"") | I41: =IF(37<=$C$9,IF($C$12<>"",$C$12,IFERROR(INDEX(tbAtalhos[Categoria],MATCH($C$6,tbAtalhos[Descrição],0))&"","")),"") | J41: =IF(37<=$C$9,IF(AND(37=1,$C$17="sim"),IF(IF($C$11<>"",$C$11,IFERROR(INDEX(tbAtalhos[Tipo],MATCH($C$6,tbAtalhos[Descrição],0))&"","Despesa"))="Receita","Recebido","Pago"),"Pendente"),"") | K41: =IF(37<=$C$9,IF($C$13<>"",$C$13,IFERROR(INDEX(tbAtalhos[Pote],MATCH($C$6,tbAtalhos[Descrição],0))&"","")),"") | L41: =IF(37<=$C$9,IF($C$14<>"",$C$14,IFERROR(INDEX(tbAtalhos[Quem],MATCH($C$6,tbAtalhos[Descrição],0))&"","")),"") | M41: =IF(37<=$C$9,IF($C$15<>"",$C$15,IFERROR(INDEX(tbAtalhos[Conta],MATCH($C$6,tbAtalhos[Descrição],0))&"","")),"") | N41: =IF(37<=$C$9,IF($C$16<>"",$C$16,IFERROR(INDEX(tbAtalhos[Forma de pagamento],MATCH($C$6,tbAtalhos[Descrição],0))&"","")),"") | O41: =IF(AND(37<=$C$9,$C$5="Parcelado"),"37/"&$C$9,"")
E42: =IF(38<=$C$9,DATE(YEAR($C$10),MONTH($C$10)+37,MIN(DAY($C$10),DAY(EOMONTH(DATE(YEAR($C$10),MONTH($C$10)+37,1),0)))),"") | F42: =IF(38<=$C$9,$C$6,"") | G42: =IF(38<=$C$9,IF($C$5="Repetir todo mês",$C$7,IF($C$8="Total da compra",IF(38<$C$9,ROUND($C$7/$C$9,2),ROUND($C$7-ROUND($C$7/$C$9,2)*($C$9-1),2)),$C$7)),"") | H42: =IF(38<=$C$9,IF($C$11<>"",$C$11,IFERROR(INDEX(tbAtalhos[Tipo],MATCH($C$6,tbAtalhos[Descrição],0))&"","Despesa")),"") | I42: =IF(38<=$C$9,IF($C$12<>"",$C$12,IFERROR(INDEX(tbAtalhos[Categoria],MATCH($C$6,tbAtalhos[Descrição],0))&"","")),"") | J42: =IF(38<=$C$9,IF(AND(38=1,$C$17="sim"),IF(IF($C$11<>"",$C$11,IFERROR(INDEX(tbAtalhos[Tipo],MATCH($C$6,tbAtalhos[Descrição],0))&"","Despesa"))="Receita","Recebido","Pago"),"Pendente"),"") | K42: =IF(38<=$C$9,IF($C$13<>"",$C$13,IFERROR(INDEX(tbAtalhos[Pote],MATCH($C$6,tbAtalhos[Descrição],0))&"","")),"") | L42: =IF(38<=$C$9,IF($C$14<>"",$C$14,IFERROR(INDEX(tbAtalhos[Quem],MATCH($C$6,tbAtalhos[Descrição],0))&"","")),"") | M42: =IF(38<=$C$9,IF($C$15<>"",$C$15,IFERROR(INDEX(tbAtalhos[Conta],MATCH($C$6,tbAtalhos[Descrição],0))&"","")),"") | N42: =IF(38<=$C$9,IF($C$16<>"",$C$16,IFERROR(INDEX(tbAtalhos[Forma de pagamento],MATCH($C$6,tbAtalhos[Descrição],0))&"","")),"") | O42: =IF(AND(38<=$C$9,$C$5="Parcelado"),"38/"&$C$9,"")
E43: =IF(39<=$C$9,DATE(YEAR($C$10),MONTH($C$10)+38,MIN(DAY($C$10),DAY(EOMONTH(DATE(YEAR($C$10),MONTH($C$10)+38,1),0)))),"") | F43: =IF(39<=$C$9,$C$6,"") | G43: =IF(39<=$C$9,IF($C$5="Repetir todo mês",$C$7,IF($C$8="Total da compra",IF(39<$C$9,ROUND($C$7/$C$9,2),ROUND($C$7-ROUND($C$7/$C$9,2)*($C$9-1),2)),$C$7)),"") | H43: =IF(39<=$C$9,IF($C$11<>"",$C$11,IFERROR(INDEX(tbAtalhos[Tipo],MATCH($C$6,tbAtalhos[Descrição],0))&"","Despesa")),"") | I43: =IF(39<=$C$9,IF($C$12<>"",$C$12,IFERROR(INDEX(tbAtalhos[Categoria],MATCH($C$6,tbAtalhos[Descrição],0))&"","")),"") | J43: =IF(39<=$C$9,IF(AND(39=1,$C$17="sim"),IF(IF($C$11<>"",$C$11,IFERROR(INDEX(tbAtalhos[Tipo],MATCH($C$6,tbAtalhos[Descrição],0))&"","Despesa"))="Receita","Recebido","Pago"),"Pendente"),"") | K43: =IF(39<=$C$9,IF($C$13<>"",$C$13,IFERROR(INDEX(tbAtalhos[Pote],MATCH($C$6,tbAtalhos[Descrição],0))&"","")),"") | L43: =IF(39<=$C$9,IF($C$14<>"",$C$14,IFERROR(INDEX(tbAtalhos[Quem],MATCH($C$6,tbAtalhos[Descrição],0))&"","")),"") | M43: =IF(39<=$C$9,IF($C$15<>"",$C$15,IFERROR(INDEX(tbAtalhos[Conta],MATCH($C$6,tbAtalhos[Descrição],0))&"","")),"") | N43: =IF(39<=$C$9,IF($C$16<>"",$C$16,IFERROR(INDEX(tbAtalhos[Forma de pagamento],MATCH($C$6,tbAtalhos[Descrição],0))&"","")),"") | O43: =IF(AND(39<=$C$9,$C$5="Parcelado"),"39/"&$C$9,"")
E44: =IF(40<=$C$9,DATE(YEAR($C$10),MONTH($C$10)+39,MIN(DAY($C$10),DAY(EOMONTH(DATE(YEAR($C$10),MONTH($C$10)+39,1),0)))),"") | F44: =IF(40<=$C$9,$C$6,"") | G44: =IF(40<=$C$9,IF($C$5="Repetir todo mês",$C$7,IF($C$8="Total da compra",IF(40<$C$9,ROUND($C$7/$C$9,2),ROUND($C$7-ROUND($C$7/$C$9,2)*($C$9-1),2)),$C$7)),"") | H44: =IF(40<=$C$9,IF($C$11<>"",$C$11,IFERROR(INDEX(tbAtalhos[Tipo],MATCH($C$6,tbAtalhos[Descrição],0))&"","Despesa")),"") | I44: =IF(40<=$C$9,IF($C$12<>"",$C$12,IFERROR(INDEX(tbAtalhos[Categoria],MATCH($C$6,tbAtalhos[Descrição],0))&"","")),"") | J44: =IF(40<=$C$9,IF(AND(40=1,$C$17="sim"),IF(IF($C$11<>"",$C$11,IFERROR(INDEX(tbAtalhos[Tipo],MATCH($C$6,tbAtalhos[Descrição],0))&"","Despesa"))="Receita","Recebido","Pago"),"Pendente"),"") | K44: =IF(40<=$C$9,IF($C$13<>"",$C$13,IFERROR(INDEX(tbAtalhos[Pote],MATCH($C$6,tbAtalhos[Descrição],0))&"","")),"") | L44: =IF(40<=$C$9,IF($C$14<>"",$C$14,IFERROR(INDEX(tbAtalhos[Quem],MATCH($C$6,tbAtalhos[Descrição],0))&"","")),"") | M44: =IF(40<=$C$9,IF($C$15<>"",$C$15,IFERROR(INDEX(tbAtalhos[Conta],MATCH($C$6,tbAtalhos[Descrição],0))&"","")),"") | N44: =IF(40<=$C$9,IF($C$16<>"",$C$16,IFERROR(INDEX(tbAtalhos[Forma de pagamento],MATCH($C$6,tbAtalhos[Descrição],0))&"","")),"") | O44: =IF(AND(40<=$C$9,$C$5="Parcelado"),"40/"&$C$9,"")
E45: =IF(41<=$C$9,DATE(YEAR($C$10),MONTH($C$10)+40,MIN(DAY($C$10),DAY(EOMONTH(DATE(YEAR($C$10),MONTH($C$10)+40,1),0)))),"") | F45: =IF(41<=$C$9,$C$6,"") | G45: =IF(41<=$C$9,IF($C$5="Repetir todo mês",$C$7,IF($C$8="Total da compra",IF(41<$C$9,ROUND($C$7/$C$9,2),ROUND($C$7-ROUND($C$7/$C$9,2)*($C$9-1),2)),$C$7)),"") | H45: =IF(41<=$C$9,IF($C$11<>"",$C$11,IFERROR(INDEX(tbAtalhos[Tipo],MATCH($C$6,tbAtalhos[Descrição],0))&"","Despesa")),"") | I45: =IF(41<=$C$9,IF($C$12<>"",$C$12,IFERROR(INDEX(tbAtalhos[Categoria],MATCH($C$6,tbAtalhos[Descrição],0))&"","")),"") | J45: =IF(41<=$C$9,IF(AND(41=1,$C$17="sim"),IF(IF($C$11<>"",$C$11,IFERROR(INDEX(tbAtalhos[Tipo],MATCH($C$6,tbAtalhos[Descrição],0))&"","Despesa"))="Receita","Recebido","Pago"),"Pendente"),"") | K45: =IF(41<=$C$9,IF($C$13<>"",$C$13,IFERROR(INDEX(tbAtalhos[Pote],MATCH($C$6,tbAtalhos[Descrição],0))&"","")),"") | L45: =IF(41<=$C$9,IF($C$14<>"",$C$14,IFERROR(INDEX(tbAtalhos[Quem],MATCH($C$6,tbAtalhos[Descrição],0))&"","")),"") | M45: =IF(41<=$C$9,IF($C$15<>"",$C$15,IFERROR(INDEX(tbAtalhos[Conta],MATCH($C$6,tbAtalhos[Descrição],0))&"","")),"") | N45: =IF(41<=$C$9,IF($C$16<>"",$C$16,IFERROR(INDEX(tbAtalhos[Forma de pagamento],MATCH($C$6,tbAtalhos[Descrição],0))&"","")),"") | O45: =IF(AND(41<=$C$9,$C$5="Parcelado"),"41/"&$C$9,"")
E46: =IF(42<=$C$9,DATE(YEAR($C$10),MONTH($C$10)+41,MIN(DAY($C$10),DAY(EOMONTH(DATE(YEAR($C$10),MONTH($C$10)+41,1),0)))),"") | F46: =IF(42<=$C$9,$C$6,"") | G46: =IF(42<=$C$9,IF($C$5="Repetir todo mês",$C$7,IF($C$8="Total da compra",IF(42<$C$9,ROUND($C$7/$C$9,2),ROUND($C$7-ROUND($C$7/$C$9,2)*($C$9-1),2)),$C$7)),"") | H46: =IF(42<=$C$9,IF($C$11<>"",$C$11,IFERROR(INDEX(tbAtalhos[Tipo],MATCH($C$6,tbAtalhos[Descrição],0))&"","Despesa")),"") | I46: =IF(42<=$C$9,IF($C$12<>"",$C$12,IFERROR(INDEX(tbAtalhos[Categoria],MATCH($C$6,tbAtalhos[Descrição],0))&"","")),"") | J46: =IF(42<=$C$9,IF(AND(42=1,$C$17="sim"),IF(IF($C$11<>"",$C$11,IFERROR(INDEX(tbAtalhos[Tipo],MATCH($C$6,tbAtalhos[Descrição],0))&"","Despesa"))="Receita","Recebido","Pago"),"Pendente"),"") | K46: =IF(42<=$C$9,IF($C$13<>"",$C$13,IFERROR(INDEX(tbAtalhos[Pote],MATCH($C$6,tbAtalhos[Descrição],0))&"","")),"") | L46: =IF(42<=$C$9,IF($C$14<>"",$C$14,IFERROR(INDEX(tbAtalhos[Quem],MATCH($C$6,tbAtalhos[Descrição],0))&"","")),"") | M46: =IF(42<=$C$9,IF($C$15<>"",$C$15,IFERROR(INDEX(tbAtalhos[Conta],MATCH($C$6,tbAtalhos[Descrição],0))&"","")),"") | N46: =IF(42<=$C$9,IF($C$16<>"",$C$16,IFERROR(INDEX(tbAtalhos[Forma de pagamento],MATCH($C$6,tbAtalhos[Descrição],0))&"","")),"") | O46: =IF(AND(42<=$C$9,$C$5="Parcelado"),"42/"&$C$9,"")
E47: =IF(43<=$C$9,DATE(YEAR($C$10),MONTH($C$10)+42,MIN(DAY($C$10),DAY(EOMONTH(DATE(YEAR($C$10),MONTH($C$10)+42,1),0)))),"") | F47: =IF(43<=$C$9,$C$6,"") | G47: =IF(43<=$C$9,IF($C$5="Repetir todo mês",$C$7,IF($C$8="Total da compra",IF(43<$C$9,ROUND($C$7/$C$9,2),ROUND($C$7-ROUND($C$7/$C$9,2)*($C$9-1),2)),$C$7)),"") | H47: =IF(43<=$C$9,IF($C$11<>"",$C$11,IFERROR(INDEX(tbAtalhos[Tipo],MATCH($C$6,tbAtalhos[Descrição],0))&"","Despesa")),"") | I47: =IF(43<=$C$9,IF($C$12<>"",$C$12,IFERROR(INDEX(tbAtalhos[Categoria],MATCH($C$6,tbAtalhos[Descrição],0))&"","")),"") | J47: =IF(43<=$C$9,IF(AND(43=1,$C$17="sim"),IF(IF($C$11<>"",$C$11,IFERROR(INDEX(tbAtalhos[Tipo],MATCH($C$6,tbAtalhos[Descrição],0))&"","Despesa"))="Receita","Recebido","Pago"),"Pendente"),"") | K47: =IF(43<=$C$9,IF($C$13<>"",$C$13,IFERROR(INDEX(tbAtalhos[Pote],MATCH($C$6,tbAtalhos[Descrição],0))&"","")),"") | L47: =IF(43<=$C$9,IF($C$14<>"",$C$14,IFERROR(INDEX(tbAtalhos[Quem],MATCH($C$6,tbAtalhos[Descrição],0))&"","")),"") | M47: =IF(43<=$C$9,IF($C$15<>"",$C$15,IFERROR(INDEX(tbAtalhos[Conta],MATCH($C$6,tbAtalhos[Descrição],0))&"","")),"") | N47: =IF(43<=$C$9,IF($C$16<>"",$C$16,IFERROR(INDEX(tbAtalhos[Forma de pagamento],MATCH($C$6,tbAtalhos[Descrição],0))&"","")),"") | O47: =IF(AND(43<=$C$9,$C$5="Parcelado"),"43/"&$C$9,"")
E48: =IF(44<=$C$9,DATE(YEAR($C$10),MONTH($C$10)+43,MIN(DAY($C$10),DAY(EOMONTH(DATE(YEAR($C$10),MONTH($C$10)+43,1),0)))),"") | F48: =IF(44<=$C$9,$C$6,"") | G48: =IF(44<=$C$9,IF($C$5="Repetir todo mês",$C$7,IF($C$8="Total da compra",IF(44<$C$9,ROUND($C$7/$C$9,2),ROUND($C$7-ROUND($C$7/$C$9,2)*($C$9-1),2)),$C$7)),"") | H48: =IF(44<=$C$9,IF($C$11<>"",$C$11,IFERROR(INDEX(tbAtalhos[Tipo],MATCH($C$6,tbAtalhos[Descrição],0))&"","Despesa")),"") | I48: =IF(44<=$C$9,IF($C$12<>"",$C$12,IFERROR(INDEX(tbAtalhos[Categoria],MATCH($C$6,tbAtalhos[Descrição],0))&"","")),"") | J48: =IF(44<=$C$9,IF(AND(44=1,$C$17="sim"),IF(IF($C$11<>"",$C$11,IFERROR(INDEX(tbAtalhos[Tipo],MATCH($C$6,tbAtalhos[Descrição],0))&"","Despesa"))="Receita","Recebido","Pago"),"Pendente"),"") | K48: =IF(44<=$C$9,IF($C$13<>"",$C$13,IFERROR(INDEX(tbAtalhos[Pote],MATCH($C$6,tbAtalhos[Descrição],0))&"","")),"") | L48: =IF(44<=$C$9,IF($C$14<>"",$C$14,IFERROR(INDEX(tbAtalhos[Quem],MATCH($C$6,tbAtalhos[Descrição],0))&"","")),"") | M48: =IF(44<=$C$9,IF($C$15<>"",$C$15,IFERROR(INDEX(tbAtalhos[Conta],MATCH($C$6,tbAtalhos[Descrição],0))&"","")),"") | N48: =IF(44<=$C$9,IF($C$16<>"",$C$16,IFERROR(INDEX(tbAtalhos[Forma de pagamento],MATCH($C$6,tbAtalhos[Descrição],0))&"","")),"") | O48: =IF(AND(44<=$C$9,$C$5="Parcelado"),"44/"&$C$9,"")
E49: =IF(45<=$C$9,DATE(YEAR($C$10),MONTH($C$10)+44,MIN(DAY($C$10),DAY(EOMONTH(DATE(YEAR($C$10),MONTH($C$10)+44,1),0)))),"") | F49: =IF(45<=$C$9,$C$6,"") | G49: =IF(45<=$C$9,IF($C$5="Repetir todo mês",$C$7,IF($C$8="Total da compra",IF(45<$C$9,ROUND($C$7/$C$9,2),ROUND($C$7-ROUND($C$7/$C$9,2)*($C$9-1),2)),$C$7)),"") | H49: =IF(45<=$C$9,IF($C$11<>"",$C$11,IFERROR(INDEX(tbAtalhos[Tipo],MATCH($C$6,tbAtalhos[Descrição],0))&"","Despesa")),"") | I49: =IF(45<=$C$9,IF($C$12<>"",$C$12,IFERROR(INDEX(tbAtalhos[Categoria],MATCH($C$6,tbAtalhos[Descrição],0))&"","")),"") | J49: =IF(45<=$C$9,IF(AND(45=1,$C$17="sim"),IF(IF($C$11<>"",$C$11,IFERROR(INDEX(tbAtalhos[Tipo],MATCH($C$6,tbAtalhos[Descrição],0))&"","Despesa"))="Receita","Recebido","Pago"),"Pendente"),"") | K49: =IF(45<=$C$9,IF($C$13<>"",$C$13,IFERROR(INDEX(tbAtalhos[Pote],MATCH($C$6,tbAtalhos[Descrição],0))&"","")),"") | L49: =IF(45<=$C$9,IF($C$14<>"",$C$14,IFERROR(INDEX(tbAtalhos[Quem],MATCH($C$6,tbAtalhos[Descrição],0))&"","")),"") | M49: =IF(45<=$C$9,IF($C$15<>"",$C$15,IFERROR(INDEX(tbAtalhos[Conta],MATCH($C$6,tbAtalhos[Descrição],0))&"","")),"") | N49: =IF(45<=$C$9,IF($C$16<>"",$C$16,IFERROR(INDEX(tbAtalhos[Forma de pagamento],MATCH($C$6,tbAtalhos[Descrição],0))&"","")),"") | O49: =IF(AND(45<=$C$9,$C$5="Parcelado"),"45/"&$C$9,"")
E50: =IF(46<=$C$9,DATE(YEAR($C$10),MONTH($C$10)+45,MIN(DAY($C$10),DAY(EOMONTH(DATE(YEAR($C$10),MONTH($C$10)+45,1),0)))),"") | F50: =IF(46<=$C$9,$C$6,"") | G50: =IF(46<=$C$9,IF($C$5="Repetir todo mês",$C$7,IF($C$8="Total da compra",IF(46<$C$9,ROUND($C$7/$C$9,2),ROUND($C$7-ROUND($C$7/$C$9,2)*($C$9-1),2)),$C$7)),"") | H50: =IF(46<=$C$9,IF($C$11<>"",$C$11,IFERROR(INDEX(tbAtalhos[Tipo],MATCH($C$6,tbAtalhos[Descrição],0))&"","Despesa")),"") | I50: =IF(46<=$C$9,IF($C$12<>"",$C$12,IFERROR(INDEX(tbAtalhos[Categoria],MATCH($C$6,tbAtalhos[Descrição],0))&"","")),"") | J50: =IF(46<=$C$9,IF(AND(46=1,$C$17="sim"),IF(IF($C$11<>"",$C$11,IFERROR(INDEX(tbAtalhos[Tipo],MATCH($C$6,tbAtalhos[Descrição],0))&"","Despesa"))="Receita","Recebido","Pago"),"Pendente"),"") | K50: =IF(46<=$C$9,IF($C$13<>"",$C$13,IFERROR(INDEX(tbAtalhos[Pote],MATCH($C$6,tbAtalhos[Descrição],0))&"","")),"") | L50: =IF(46<=$C$9,IF($C$14<>"",$C$14,IFERROR(INDEX(tbAtalhos[Quem],MATCH($C$6,tbAtalhos[Descrição],0))&"","")),"") | M50: =IF(46<=$C$9,IF($C$15<>"",$C$15,IFERROR(INDEX(tbAtalhos[Conta],MATCH($C$6,tbAtalhos[Descrição],0))&"","")),"") | N50: =IF(46<=$C$9,IF($C$16<>"",$C$16,IFERROR(INDEX(tbAtalhos[Forma de pagamento],MATCH($C$6,tbAtalhos[Descrição],0))&"","")),"") | O50: =IF(AND(46<=$C$9,$C$5="Parcelado"),"46/"&$C$9,"")
E51: =IF(47<=$C$9,DATE(YEAR($C$10),MONTH($C$10)+46,MIN(DAY($C$10),DAY(EOMONTH(DATE(YEAR($C$10),MONTH($C$10)+46,1),0)))),"") | F51: =IF(47<=$C$9,$C$6,"") | G51: =IF(47<=$C$9,IF($C$5="Repetir todo mês",$C$7,IF($C$8="Total da compra",IF(47<$C$9,ROUND($C$7/$C$9,2),ROUND($C$7-ROUND($C$7/$C$9,2)*($C$9-1),2)),$C$7)),"") | H51: =IF(47<=$C$9,IF($C$11<>"",$C$11,IFERROR(INDEX(tbAtalhos[Tipo],MATCH($C$6,tbAtalhos[Descrição],0))&"","Despesa")),"") | I51: =IF(47<=$C$9,IF($C$12<>"",$C$12,IFERROR(INDEX(tbAtalhos[Categoria],MATCH($C$6,tbAtalhos[Descrição],0))&"","")),"") | J51: =IF(47<=$C$9,IF(AND(47=1,$C$17="sim"),IF(IF($C$11<>"",$C$11,IFERROR(INDEX(tbAtalhos[Tipo],MATCH($C$6,tbAtalhos[Descrição],0))&"","Despesa"))="Receita","Recebido","Pago"),"Pendente"),"") | K51: =IF(47<=$C$9,IF($C$13<>"",$C$13,IFERROR(INDEX(tbAtalhos[Pote],MATCH($C$6,tbAtalhos[Descrição],0))&"","")),"") | L51: =IF(47<=$C$9,IF($C$14<>"",$C$14,IFERROR(INDEX(tbAtalhos[Quem],MATCH($C$6,tbAtalhos[Descrição],0))&"","")),"") | M51: =IF(47<=$C$9,IF($C$15<>"",$C$15,IFERROR(INDEX(tbAtalhos[Conta],MATCH($C$6,tbAtalhos[Descrição],0))&"","")),"") | N51: =IF(47<=$C$9,IF($C$16<>"",$C$16,IFERROR(INDEX(tbAtalhos[Forma de pagamento],MATCH($C$6,tbAtalhos[Descrição],0))&"","")),"") | O51: =IF(AND(47<=$C$9,$C$5="Parcelado"),"47/"&$C$9,"")
E52: =IF(48<=$C$9,DATE(YEAR($C$10),MONTH($C$10)+47,MIN(DAY($C$10),DAY(EOMONTH(DATE(YEAR($C$10),MONTH($C$10)+47,1),0)))),"") | F52: =IF(48<=$C$9,$C$6,"") | G52: =IF(48<=$C$9,IF($C$5="Repetir todo mês",$C$7,IF($C$8="Total da compra",IF(48<$C$9,ROUND($C$7/$C$9,2),ROUND($C$7-ROUND($C$7/$C$9,2)*($C$9-1),2)),$C$7)),"") | H52: =IF(48<=$C$9,IF($C$11<>"",$C$11,IFERROR(INDEX(tbAtalhos[Tipo],MATCH($C$6,tbAtalhos[Descrição],0))&"","Despesa")),"") | I52: =IF(48<=$C$9,IF($C$12<>"",$C$12,IFERROR(INDEX(tbAtalhos[Categoria],MATCH($C$6,tbAtalhos[Descrição],0))&"","")),"") | J52: =IF(48<=$C$9,IF(AND(48=1,$C$17="sim"),IF(IF($C$11<>"",$C$11,IFERROR(INDEX(tbAtalhos[Tipo],MATCH($C$6,tbAtalhos[Descrição],0))&"","Despesa"))="Receita","Recebido","Pago"),"Pendente"),"") | K52: =IF(48<=$C$9,IF($C$13<>"",$C$13,IFERROR(INDEX(tbAtalhos[Pote],MATCH($C$6,tbAtalhos[Descrição],0))&"","")),"") | L52: =IF(48<=$C$9,IF($C$14<>"",$C$14,IFERROR(INDEX(tbAtalhos[Quem],MATCH($C$6,tbAtalhos[Descrição],0))&"","")),"") | M52: =IF(48<=$C$9,IF($C$15<>"",$C$15,IFERROR(INDEX(tbAtalhos[Conta],MATCH($C$6,tbAtalhos[Descrição],0))&"","")),"") | N52: =IF(48<=$C$9,IF($C$16<>"",$C$16,IFERROR(INDEX(tbAtalhos[Forma de pagamento],MATCH($C$6,tbAtalhos[Descrição],0))&"","")),"") | O52: =IF(AND(48<=$C$9,$C$5="Parcelado"),"48/"&$C$9,"")
